Workbook

Sheet BaseRelatório
A1: ID | B1: DATA CONTABIL | C1: COD.FILIAL | D1: FILIAL | E1: CONGENERE | F1: TIPO DE COBRANÇA | G1: Valor Orçado | H1: Volume Orçado
A2: 1503 | B2: 45658 | C2: 1 | D2: Betim | E2: Atlantica | F2: Avanço Espaço | G2: 0 | H2: 0
A3: 1503 | B3: 45658 | C3: 1 | D3: Betim | E3: Atlantica | F3: Avanço Horário | G3: 0 | H3: 0
A4: 1503 | B4: 45658 | C4: 1 | D4: Betim | E4: Atlantica | F4: Operação Normal | G4: 89789.37 | H4: 2040
A5: 1503 | B5: 45658 | C5: 1 | D5: Betim | E5: Atlantica | F5: Outras Receitas | G5: 0 | H5: 0
A6: 1102 | B6: 45658 | C6: 1 | D6: Betim | E6: Ciapetro | F6: Avanço Espaço | G6: 0 | H6: 0
A7: 1102 | B7: 45658 | C7: 1 | D7: Betim | E7: Ciapetro | F7: Avanço Horário | G7: 0 | H7: 0
A8: 1102 | B8: 45658 | C8: 1 | D8: Betim | E8: Ciapetro | F8: Operação Normal | G8: 28839.059 | H8: 1500
A9: 1102 | B9: 45658 | C9: 1 | D9: Betim | E9: Ciapetro | F9: Outras Receitas | G9: 0 | H9: 0
A10: 16 | B10: 45658 | C10: 1 | D10: Betim | E10: Rede Sol | F10: Avanço Espaço | G10: 0 | H10: 0
A11: 16 | B11: 45658 | C11: 1 | D11: Betim | E11: Rede Sol | F11: Avanço Horário | G11: 0 | H11: 0
A12: 16 | B12: 45658 | C12: 1 | D12: Betim | E12: Rede Sol | F12: Operação Normal | G12: 9355.5094 | H12: 300
A13: 16 | B13: 45658 | C13: 1 | D13: Betim | E13: Rede Sol | F13: Outras Receitas | G13: 0 | H13: 0
... A17: 1401 | B17: 45658 | C17: 1 | D17: Betim | E17: Tobras | F17: Outras Receitas | G17: 0 | H17: 0
A18: 115 | B18: 45658 | C18: 11 | D18: Duque de Caxias | E18: =_xlfn.XLOOKUP(TabReceitas[[#This Row],[ID]],TabCondicoesComerciais[ID],TabCondicoesComerciais[Congênere],"Verificar") -> Rede Sol | F18: Avanço Espaço | G18: 0 | H18: 0
A19: 115 | B19: 45658 | C19: 11 | D19: Duque de Caxias | E19: =_xlfn.XLOOKUP(TabReceitas[[#This Row],[ID]],TabCondicoesComerciais[ID],TabCondicoesComerciais[Congênere],"Verificar") -> Rede Sol | F19: Avanço Horário | G19: 0 | H19: 0
A20: 115 | B20: 45658 | C20: 11 | D20: Duque de Caxias | E20: =_xlfn.XLOOKUP(TabReceitas[[#This Row],[ID]],TabCondicoesComerciais[ID],TabCondicoesComerciais[Congênere],"Verificar") -> Rede Sol | F20: Operação Normal | G20: 56842.105 | H20: 2000
A21: 115 | B21: 45658 | C21: 11 | D21: Duque de Caxias | E21: =_xlfn.XLOOKUP(TabReceitas[[#This Row],[ID]],TabCondicoesComerciais[ID],TabCondicoesComerciais[Congênere],"Verificar") -> Rede Sol | F21: Outras Receitas | G21: 0 | H21: 0
A22: 11104 | B22: 45658 | C22: 11 | D22: Duque de Caxias | E22: =_xlfn.XLOOKUP(TabReceitas[[#This Row],[ID]],TabCondicoesComerciais[ID],TabCondicoesComerciais[Congênere],"Verificar") -> Ruff | F22: Avanço Espaço | G22: 0 | H22: 0
A23: 11104 | B23: 45658 | C23: 11 | D23: Duque de Caxias | E23: =_xlfn.XLOOKUP(TabReceitas[[#This Row],[ID]],TabCondicoesComerciais[ID],TabCondicoesComerciais[Congênere],"Verificar") -> Ruff | F23: Avanço Horário | G23: 0 | H23: 0
A24: 11104 | B24: 45658 | C24: 11 | D24: Duque de Caxias | E24: =_xlfn.XLOOKUP(TabReceitas[[#This Row],[ID]],TabCondicoesComerciais[ID],TabCondicoesComerciais[Congênere],"Verificar") -> Ruff | F24: Operação Normal | G24: 0 | H24: 0
A25: 11104 | B25: 45658 | C25: 11 | D25: Duque de Caxias | E25: =_xlfn.XLOOKUP(TabReceitas[[#This Row],[ID]],TabCondicoesComerciais[ID],TabCondicoesComerciais[Congênere],"Verificar") -> Ruff | F25: Outras Receitas | G25: 0 | H25: 0
A26: 13300 | B26: 45658 | C26: 13 | D26: Goiânia | E26: Petrobahia | F26: Avanço Espaço | G26: 0 | H26: 0
A27: 13300 | B27: 45658 | C27: 13 | D27: Goiânia | E27: Petrobahia | F27: Avanço Horário | G27: 0 | H27: 0
A28: 13300 | B28: 45658 | C28: 13 | D28: Goiânia | E28: Petrobahia | F28: Operação Normal | G28: 86210.526 | H28: 4200
A29: 13300 | B29: 45658 | C29: 13 | D29: Goiânia | E29: Petrobahia | F29: Outras Receitas | G29: 0 | H29: 0
A30: 38203 | B30: 45658 | C30: 38 | D30: Guamaré | E30: Raízen | F30: Avanço Espaço | G30: 0 | H30: 0
A31: 38203 | B31: 45658 | C31: 38 | D31: Guamaré | E31: Raízen | F31: Avanço Horário | G31: 0 | H31: 0
A32: 38203 | B32: 45658 | C32: 38 | D32: Guamaré | E32: Raízen | F32: Operação Normal | G32: 137499.16 | H32: 4200
A33: 38203 | B33: 45658 | C33: 38 | D33: Guamaré | E33: Raízen | F33: Outras Receitas | G33: 0 | H33: 0
A34: 16203 | B34: 45658 | C34: 16 | D34: Guarulhos | E34: Raízen | F34: Avanço Espaço | G34: 0 | H34: 0
A35: 16203 | B35: 45658 | C35: 16 | D35: Guarulhos | E35: Raízen | F35: Avanço Horário | G35: 0 | H35: 0
A36: 16203 | B36: 45658 | C36: 16 | D36: Guarulhos | E36: Raízen | F36: Operação Normal | G36: 164947.61 | H36: 6100
A37: 16203 | B37: 45658 | C37: 16 | D37: Guarulhos | E37: Raízen | F37: Outras Receitas | G37: 0 | H37: 0
... A41: 49102 | B41: 45658 | C41: 49 | D41: Luis Eduardo Magalhães | E41: Ipiranga | F41: Outras Receitas | G41: 0 | H41: 0
A42: 20105 | B42: 45658 | C42: 20 | D42: São José do Rio Preto | E42: Ruff | F42: Avanço Espaço | G42: 0 | H42: 0
A43: 20105 | B43: 45658 | C43: 20 | D43: São José do Rio Preto | E43: Ruff | F43: Avanço Horário | G43: 0 | H43: 0
A44: 20105 | B44: 45658 | C44: 20 | D44: São José do Rio Preto | E44: Ruff | F44: Operação Normal | G44: 16282.577 | H44: 545
A45: 20105 | B45: 45658 | C45: 20 | D45: São José do Rio Preto | E45: Ruff | F45: Outras Receitas | G45: 0 | H45: 0
A46: 1503 | B46: 45689 | C46: 1 | D46: Betim | E46: Atlantica | F46: Avanço Espaço | G46: 0 | H46: 0
A47: 1503 | B47: 45689 | C47: 1 | D47: Betim | E47: Atlantica | F47: Avanço Horário | G47: 0 | H47: 0
A48: 1503 | B48: 45689 | C48: 1 | D48: Betim | E48: Atlantica | F48: Operação Normal | G48: 89789.37 | H48: 2040
A49: 1503 | B49: 45689 | C49: 1 | D49: Betim | E49: Atlantica | F49: Outras Receitas | G49: 0 | H49: 0
A50: 1102 | B50: 45689 | C50: 1 | D50: Betim | E50: Ciapetro | F50: Avanço Espaço | G50: 0 | H50: 0
A51: 1102 | B51: 45689 | C51: 1 | D51: Betim | E51: Ciapetro | F51: Avanço Horário | G51: 0 | H51: 0
A52: 1102 | B52: 45689 | C52: 1 | D52: Betim | E52: Ciapetro | F52: Operação Normal | G52: 28839.059 | H52: 1500
A53: 1102 | B53: 45689 | C53: 1 | D53: Betim | E53: Ciapetro | F53: Outras Receitas | G53: 0 | H53: 0
A54: 16 | B54: 45689 | C54: 1 | D54: Betim | E54: Rede Sol | F54: Avanço Espaço | G54: 0 | H54: 0
A55: 16 | B55: 45689 | C55: 1 | D55: Betim | E55: Rede Sol | F55: Avanço Horário | G55: 0 | H55: 0
A56: 16 | B56: 45689 | C56: 1 | D56: Betim | E56: Rede Sol | F56: Operação Normal | G56: 9729.7297 | H56: 300
A57: 16 | B57: 45689 | C57: 1 | D57: Betim | E57: Rede Sol | F57: Outras Receitas | G57: 0 | H57: 0
... A61: 1401 | B61: 45689 | C61: 1 | D61: Betim | E61: Tobras | F61: Outras Receitas | G61: 0 | H61: 0
A62: 115 | B62: 45689 | C62: 11 | D62: Duque de Caxias | E62: =_xlfn.XLOOKUP(TabReceitas[[#This Row],[ID]],TabCondicoesComerciais[ID],TabCondicoesComerciais[Congênere],"Verificar") -> Rede Sol | F62: Avanço Espaço | G62: 0 | H62: 0
A63: 115 | B63: 45689 | C63: 11 | D63: Duque de Caxias | E63: =_xlfn.XLOOKUP(TabReceitas[[#This Row],[ID]],TabCondicoesComerciais[ID],TabCondicoesComerciais[Congênere],"Verificar") -> Rede Sol | F63: Avanço Horário | G63: 0 | H63: 0
A64: 115 | B64: 45689 | C64: 11 | D64: Duque de Caxias | E64: =_xlfn.XLOOKUP(TabReceitas[[#This Row],[ID]],TabCondicoesComerciais[ID],TabCondicoesComerciais[Congênere],"Verificar") -> Rede Sol | F64: Operação Normal | G64: 59115.789 | H64: 2000
A65: 115 | B65: 45689 | C65: 11 | D65: Duque de Caxias | E65: =_xlfn.XLOOKUP(TabReceitas[[#This Row],[ID]],TabCondicoesComerciais[ID],TabCondicoesComerciais[Congênere],"Verificar") -> Rede Sol | F65: Outras Receitas | G65: 0 | H65: 0
A66: 11104 | B66: 45689 | C66: 11 | D66: Duque de Caxias | E66: =_xlfn.XLOOKUP(TabReceitas[[#This Row],[ID]],TabCondicoesComerciais[ID],TabCondicoesComerciais[Congênere],"Verificar") -> Ruff | F66: Avanço Espaço | G66: 0 | H66: 0
A67: 11104 | B67: 45689 | C67: 11 | D67: Duque de Caxias | E67: =_xlfn.XLOOKUP(TabReceitas[[#This Row],[ID]],TabCondicoesComerciais[ID],TabCondicoesComerciais[Congênere],"Verificar") -> Ruff | F67: Avanço Horário | G67: 0 | H67: 0
A68: 11104 | B68: 45689 | C68: 11 | D68: Duque de Caxias | E68: =_xlfn.XLOOKUP(TabReceitas[[#This Row],[ID]],TabCondicoesComerciais[ID],TabCondicoesComerciais[Congênere],"Verificar") -> Ruff | F68: Operação Normal | G68: 0 | H68: 0
A69: 11104 | B69: 45689 | C69: 11 | D69: Duque de Caxias | E69: =_xlfn.XLOOKUP(TabReceitas[[#This Row],[ID]],TabCondicoesComerciais[ID],TabCondicoesComerciais[Congênere],"Verificar") -> Ruff | F69: Outras Receitas | G69: 0 | H69: 0
A70: 13300 | B70: 45689 | C70: 13 | D70: Goiânia | E70: Petrobahia | F70: Avanço Espaço | G70: 0 | H70: 0
A71: 13300 | B71: 45689 | C71: 13 | D71: Goiânia | E71: Petrobahia | F71: Avanço Horário | G71: 0 | H71: 0
A72: 13300 | B72: 45689 | C72: 13 | D72: Goiânia | E72: Petrobahia | F72: Operação Normal | G72: 89658.947 | H72: 4200
A73: 13300 | B73: 45689 | C73: 13 | D73: Goiânia | E73: Petrobahia | F73: Outras Receitas | G73: 0 | H73: 0
A74: 38203 | B74: 45689 | C74: 38 | D74: Guamaré | E74: Raízen | F74: Avanço Espaço | G74: 0 | H74: 0
A75: 38203 | B75: 45689 | C75: 38 | D75: Guamaré | E75: Raízen | F75: Avanço Horário | G75: 0 | H75: 0
A76: 38203 | B76: 45689 | C76: 38 | D76: Guamaré | E76: Raízen | F76: Operação Normal | G76: 137499.16 | H76: 4200
A77: 38203 | B77: 45689 | C77: 38 | D77: Guamaré | E77: Raízen | F77: Outras Receitas | G77: 0 | H77: 0
A78: 16203 | B78: 45689 | C78: 16 | D78: Guarulhos | E78: Raízen | F78: Avanço Espaço | G78: 0 | H78: 0
A79: 16203 | B79: 45689 | C79: 16 | D79: Guarulhos | E79: Raízen | F79: Avanço Horário | G79: 0 | H79: 0
A80: 16203 | B80: 45689 | C80: 16 | D80: Guarulhos | E80: Raízen | F80: Operação Normal | G80: 164947.61 | H80: 6100
A81: 16203 | B81: 45689 | C81: 16 | D81: Guarulhos | E81: Raízen | F81: Outras Receitas | G81: 0 | H81: 0
... A85: 49102 | B85: 45689 | C85: 49 | D85: Luis Eduardo Magalhães | E85: Ipiranga | F85: Outras Receitas | G85: 0 | H85: 0
A86: 20105 | B86: 45689 | C86: 20 | D86: São José do Rio Preto | E86: Ruff | F86: Avanço Espaço | G86: 0 | H86: 0
A87: 20105 | B87: 45689 | C87: 20 | D87: São José do Rio Preto | E87: Ruff | F87: Avanço Horário | G87: 0 | H87: 0
A88: 20105 | B88: 45689 | C88: 20 | D88: São José do Rio Preto | E88: Ruff | F88: Operação Normal | G88: 16933.88 | H88: 545
A89: 20105 | B89: 45689 | C89: 20 | D89: São José do Rio Preto | E89: Ruff | F89: Outras Receitas | G89: 0 | H89: 0
A90: 1503 | B90: 45717 | C90: 1 | D90: Betim | E90: Atlantica | F90: Avanço Espaço | G90: 0 | H90: 0
A91: 1503 | B91: 45717 | C91: 1 | D91: Betim | E91: Atlantica | F91: Avanço Horário | G91: 0 | H91: 0
A92: 1503 | B92: 45717 | C92: 1 | D92: Betim | E92: Atlantica | F92: Operação Normal | G92: 89789.37 | H92: 2040
A93: 1503 | B93: 45717 | C93: 1 | D93: Betim | E93: Atlantica | F93: Outras Receitas | G93: 0 | H93: 0
A94: 1102 | B94: 45717 | C94: 1 | D94: Betim | E94: Ciapetro | F94: Avanço Espaço | G94: 0 | H94: 0
A95: 1102 | B95: 45717 | C95: 1 | D95: Betim | E95: Ciapetro | F95: Avanço Horário | G95: 0 | H95: 0
A96: 1102 | B96: 45717 | C96: 1 | D96: Betim | E96: Ciapetro | F96: Operação Normal | G96: 28839.059 | H96: 1500
A97: 1102 | B97: 45717 | C97: 1 | D97: Betim | E97: Ciapetro | F97: Outras Receitas | G97: 0 | H97: 0
A98: 16 | B98: 45717 | C98: 1 | D98: Betim | E98: Rede Sol | F98: Avanço Espaço | G98: 0 | H98: 0
A99: 16 | B99: 45717 | C99: 1 | D99: Betim | E99: Rede Sol | F99: Avanço Horário | G99: 0 | H99: 0
A100: 16 | B100: 45717 | C100: 1 | D100: Betim | E100: Rede Sol | F100: Operação Normal | G100: 9729.7297 | H100: 300
A101: 16 | B101: 45717 | C101: 1 | D101: Betim | E101: Rede Sol | F101: Outras Receitas | G101: 0 | H101: 0
... A105: 1401 | B105: 45717 | C105: 1 | D105: Betim | E105: Tobras | F105: Outras Receitas | G105: 0 | H105: 0
A106: 115 | B106: 45717 | C106: 11 | D106: Duque de Caxias | E106: =_xlfn.XLOOKUP(TabReceitas[[#This Row],[ID]],TabCondicoesComerciais[ID],TabCondicoesComerciais[Congênere],"Verificar") -> Rede Sol | F106: Avanço Espaço | G106: 0 | H106: 0
A107: 115 | B107: 45717 | C107: 11 | D107: Duque de Caxias | E107: =_xlfn.XLOOKUP(TabReceitas[[#This Row],[ID]],TabCondicoesComerciais[ID],TabCondicoesComerciais[Congênere],"Verificar") -> Rede Sol | F107: Avanço Horário | G107: 0 | H107: 0
A108: 115 | B108: 45717 | C108: 11 | D108: Duque de Caxias | E108: =_xlfn.XLOOKUP(TabReceitas[[#This Row],[ID]],TabCondicoesComerciais[ID],TabCondicoesComerciais[Congênere],"Verificar") -> Rede Sol | F108: Operação Normal | G108: 59115.789 | H108: 2000
A109: 115 | B109: 45717 | C109: 11 | D109: Duque de Caxias | E109: =_xlfn.XLOOKUP(TabReceitas[[#This Row],[ID]],TabCondicoesComerciais[ID],TabCondicoesComerciais[Congênere],"Verificar") -> Rede Sol | F109: Outras Receitas | G109: 0 | H109: 0
A110: 11104 | B110: 45717 | C110: 11 | D110: Duque de Caxias | E110: =_xlfn.XLOOKUP(TabReceitas[[#This Row],[ID]],TabCondicoesComerciais[ID],TabCondicoesComerciais[Congênere],"Verificar") -> Ruff | F110: Avanço Espaço | G110: 0 | H110: 0
A111: 11104 | B111: 45717 | C111: 11 | D111: Duque de Caxias | E111: =_xlfn.XLOOKUP(TabReceitas[[#This Row],[ID]],TabCondicoesComerciais[ID],TabCondicoesComerciais[Congênere],"Verificar") -> Ruff | F111: Avanço Horário | G111: 0 | H111: 0
A112: 11104 | B112: 45717 | C112: 11 | D112: Duque de Caxias | E112: =_xlfn.XLOOKUP(TabReceitas[[#This Row],[ID]],TabCondicoesComerciais[ID],TabCondicoesComerciais[Congênere],"Verificar") -> Ruff | F112: Operação Normal | G112: 0 | H112: 0
A113: 11104 | B113: 45717 | C113: 11 | D113: Duque de Caxias | E113: =_xlfn.XLOOKUP(TabReceitas[[#This Row],[ID]],TabCondicoesComerciais[ID],TabCondicoesComerciais[Congênere],"Verificar") -> Ruff | F113: Outras Receitas | G113: 0 | H113: 0
A114: 13300 | B114: 45717 | C114: 13 | D114: Goiânia | E114: Petrobahia | F114: Avanço Espaço | G114: 0 | H114: 0
A115: 13300 | B115: 45717 | C115: 13 | D115: Goiânia | E115: Petrobahia | F115: Avanço Horário | G115: 0 | H115: 0
...

Sheet Receitas
A1: ID | B1: DATA CONTABIL | C1: Gerência | D1: Núcleo | E1: Corredor | F1: COD.FILIAL | G1: FILIAL | H1: CONGENERE | I1: TIPO DE COBRANÇA | J1: Valor Orçado | K1: Volume Orçado | L1: Valor Total R$ | M1: Vol. Movimentado M³ | N1: Nº NF | O1: Justificativas | P1: Volume Mínimo | Q1: Volume 1º Giro | R1: Tarifa 1º Giro | S1: Tarifa 2º Giro | T1: Tarifa Cobrada | U1: Tarifa Efetiva | V1: Valor Contrato | W1: Valor Movimentado | X1: Check Tarifa
A2: 1503 | B2: 45658 | C2: BRASILIA | D2: MG RJ ES | E2: MINAS CENTRAL | F2: 1 | G2: Betim | H2: Atlantica | I2: Avanço Espaço | J2: 0 | K2: 0 | P2: =IF(BD_Receitas[[#This Row],[TIPO DE COBRANÇA]]="Operação Normal", _xlfn.XLOOKUP(BD_Receitas[[#This Row],[ID]],TabCondicoesComerciais[ID],TabCondicoesComerciais[Volume mínimo (m3)],0),"") | Q2: =_xlfn.XLOOKUP(BD_Receitas[[#This Row],[ID]],TabCondicoesComerciais[ID],TabCondicoesComerciais[Vol. 1ºGiro],0) -> 360 | R2: =IF(BD_Receitas[[#This Row],[TIPO DE COBRANÇA]]="Avanço Espaço", _xlfn.XLOOKUP(BD_Receitas[[#This Row],[ID]],TabCondicoesComerciais[ID],TabCondicoesComerciais[Avanço Espaço],0), IF(BD_Receitas[[#This Row],[TIPO DE COBRANÇA]]="Avanço Horário", _xlfn.XLOOKUP(BD_Receitas[[#This Row],[ID]],TabCondicoesComerciais[ID],TabCondicoesComerciais[Avanço Horário],0), IF(BD_Receitas[[#This Row],[TIPO DE COBRANÇA]]="Operação Normal", _xlfn.XLOOKUP(BD_Receitas[[#This Row],[ID]],TabCondicoesComerciais[ID],TabCondicoesComerciais[Tarifa 1º Giro],0),0))) -> 16.364 | S2: =IF(BD_Receitas[[#This Row],[TIPO DE COBRANÇA]]="Operação Normal", _xlfn.XLOOKUP(BD_Receitas[[#This Row],[ID]],TabCondicoesComerciais[ID],TabCondicoesComerciais[Tarifa 2º Giro],0),0) -> 0 | T2: =IFERROR(IF(BD_Receitas[[#This Row],[TIPO DE COBRANÇA]]<>"Operação Normal","",BD_Receitas[[#This Row],[Valor Total R$]]/ MAX(BD_Receitas[[#This Row],[Vol. Movimentado M³]], BD_Receitas[[#This Row],[Volume Mínimo ]]) ),0) | U2: =IFERROR(IF(BD_Receitas[[#This Row],[TIPO DE COBRANÇA]]<>"Operação Normal","", SUMIFS(BD_Receitas[Valor Total R$],BD_Receitas[CONGENERE],BD_Receitas[[#This Row],[CONGENERE]],BD_Receitas[FILIAL],BD_Receitas[[#This Row],[FILIAL]],BD_Receitas[DATA CONTABIL],BD_Receitas[[#This Row],[DATA CONTABIL]]) /BD_Receitas[[#This Row],[Vol. Movimentado M³]] ),0) | V2: =IF(BD_Receitas[[#This Row],[TIPO DE COBRANÇA]]<>"Operação Normal","",(BD_Receitas[[#This Row],[Volume 1º Giro]]*BD_Receitas[[#This Row],[Tarifa 1º Giro]])+(BD_Receitas[[#This Row],[Volume Mínimo ]]-BD_Receitas[[#This Row],[Volume 1º Giro]])*BD_Receitas[[#This Row],[Tarifa 2º Giro]]) | W2: =IF(BD_Receitas[[#This Row],[TIPO DE COBRANÇA]]<>"OPERAÇÃO NORMAL","", IF(BD_Receitas[[#This Row],[Vol. Movimentado M³]]<BD_Receitas[[#This Row],[Volume 1º Giro]],BD_Receitas[[#This Row],[Vol. Movimentado M³]]* BD_Receitas[[#This Row],[Tarifa 1º Giro]], (BD_Receitas[[#This Row],[Volume 1º Giro]]*BD_Receitas[[#This Row],[Tarifa 1º Giro]])+(BD_Receitas[[#This Row],[Vol. Movimentado M³]]-BD_Receitas[[#This Row],[Volume 1º Giro]])*BD_Receitas[[#This Row],[Tarifa 2º Giro]]) ) | X2: =IF(BD_Receitas[[#This Row],[TIPO DE COBRANÇA]] <> "OPERAÇÃO NORMAL","", IF(BD_Receitas[[#This Row],[Vol. Movimentado M³]]= BD_Receitas[[#This Row],[Volume Mínimo ]], "Vol. Movimentado igual ao Vol. Mínimo", IF(ROUND(BD_Receitas[[#This Row],[Tarifa 1º Giro]],3) <> ROUND(BD_Receitas[[#This Row],[Tarifa Cobrada]],3), "Conferir tarifa cobrada", IF(BD_Receitas[[#This Row],[Volume Mínimo ]]=0,"Ok", IF(BD_Receitas[[#This Row],[Vol. Movimentado M³]]<= BD_Receitas[[#This Row],[Volume Mínimo ]], IF(ROUND(BD_Receitas[[#This Row],[Valor Total R$]],2) = ROUND(BD_Receitas[[#This Row],[Valor Total R$]],2), "Ok","Verificar Cobrança"), IF(ROUND(BD_Receitas[[#This Row],[Valor Contrato]],2) = ROUND(BD_Receitas[[#This Row],[Valor Movimentado]],2), "OK","Verificar cobrança") )))))
A3: 1503 | B3: 45658 | C3: BRASILIA | D3: MG RJ ES | E3: MINAS CENTRAL | F3: 1 | G3: Betim | H3: Atlantica | I3: Avanço Horário | J3: 0 | K3: 0 | P3: =IF(BD_Receitas[[#This Row],[TIPO DE COBRANÇA]]="Operação Normal", _xlfn.XLOOKUP(BD_Receitas[[#This Row],[ID]],TabCondicoesComerciais[ID],TabCondicoesComerciais[Volume mínimo (m3)],0),"") | Q3: =_xlfn.XLOOKUP(BD_Receitas[[#This Row],[ID]],TabCondicoesComerciais[ID],TabCondicoesComerciais[Vol. 1ºGiro],0) -> 360 | R3: =IF(BD_Receitas[[#This Row],[TIPO DE COBRANÇA]]="Avanço Espaço", _xlfn.XLOOKUP(BD_Receitas[[#This Row],[ID]],TabCondicoesComerciais[ID],TabCondicoesComerciais[Avanço Espaço],0), IF(BD_Receitas[[#This Row],[TIPO DE COBRANÇA]]="Avanço Horário", _xlfn.XLOOKUP(BD_Receitas[[#This Row],[ID]],TabCondicoesComerciais[ID],TabCondicoesComerciais[Avanço Horário],0), IF(BD_Receitas[[#This Row],[TIPO DE COBRANÇA]]="Operação Normal", _xlfn.XLOOKUP(BD_Receitas[[#This Row],[ID]],TabCondicoesComerciais[ID],TabCondicoesComerciais[Tarifa 1º Giro],0),0))) -> 15 | S3: =IF(BD_Receitas[[#This Row],[TIPO DE COBRANÇA]]="Operação Normal", _xlfn.XLOOKUP(BD_Receitas[[#This Row],[ID]],TabCondicoesComerciais[ID],TabCondicoesComerciais[Tarifa 2º Giro],0),0) -> 0 | T3: =IFERROR(IF(BD_Receitas[[#This Row],[TIPO DE COBRANÇA]]<>"Operação Normal","",BD_Receitas[[#This Row],[Valor Total R$]]/ MAX(BD_Receitas[[#This Row],[Vol. Movimentado M³]], BD_Receitas[[#This Row],[Volume Mínimo ]]) ),0) | U3: =IFERROR(IF(BD_Receitas[[#This Row],[TIPO DE COBRANÇA]]<>"Operação Normal","", SUMIFS(BD_Receitas[Valor Total R$],BD_Receitas[CONGENERE],BD_Receitas[[#This Row],[CONGENERE]],BD_Receitas[FILIAL],BD_Receitas[[#This Row],[FILIAL]],BD_Receitas[DATA CONTABIL],BD_Receitas[[#This Row],[DATA CONTABIL]]) /BD_Receitas[[#This Row],[Vol. Movimentado M³]] ),0) | V3: =IF(BD_Receitas[[#This Row],[TIPO DE COBRANÇA]]<>"Operação Normal","",(BD_Receitas[[#This Row],[Volume 1º Giro]]*BD_Receitas[[#This Row],[Tarifa 1º Giro]])+(BD_Receitas[[#This Row],[Volume Mínimo ]]-BD_Receitas[[#This Row],[Volume 1º Giro]])*BD_Receitas[[#This Row],[Tarifa 2º Giro]]) | W3: =IF(BD_Receitas[[#This Row],[TIPO DE COBRANÇA]]<>"OPERAÇÃO NORMAL","", IF(BD_Receitas[[#This Row],[Vol. Movimentado M³]]<BD_Receitas[[#This Row],[Volume 1º Giro]],BD_Receitas[[#This Row],[Vol. Movimentado M³]]* BD_Receitas[[#This Row],[Tarifa 1º Giro]], (BD_Receitas[[#This Row],[Volume 1º Giro]]*BD_Receitas[[#This Row],[Tarifa 1º Giro]])+(BD_Receitas[[#This Row],[Vol. Movimentado M³]]-BD_Receitas[[#This Row],[Volume 1º Giro]])*BD_Receitas[[#This Row],[Tarifa 2º Giro]]) ) | X3: =IF(BD_Receitas[[#This Row],[TIPO DE COBRANÇA]] <> "OPERAÇÃO NORMAL","", IF(BD_Receitas[[#This Row],[Vol. Movimentado M³]]= BD_Receitas[[#This Row],[Volume Mínimo ]], "Vol. Movimentado igual ao Vol. Mínimo", IF(ROUND(BD_Receitas[[#This Row],[Tarifa 1º Giro]],3) <> ROUND(BD_Receitas[[#This Row],[Tarifa Cobrada]],3), "Conferir tarifa cobrada", IF(BD_Receitas[[#This Row],[Volume Mínimo ]]=0,"Ok", IF(BD_Receitas[[#This Row],[Vol. Movimentado M³]]<= BD_Receitas[[#This Row],[Volume Mínimo ]], IF(ROUND(BD_Receitas[[#This Row],[Valor Total R$]],2) = ROUND(BD_Receitas[[#This Row],[Valor Total R$]],2), "Ok","Verificar Cobrança"), IF(ROUND(BD_Receitas[[#This Row],[Valor Contrato]],2) = ROUND(BD_Receitas[[#This Row],[Valor Movimentado]],2), "OK","Verificar cobrança") )))))
A4: 1503 | B4: 45658 | C4: BRASILIA | D4: MG RJ ES | E4: MINAS CENTRAL | F4: 1 | G4: Betim | H4: Atlantica | I4: Operação Normal | J4: 89789.37 | K4: 2040 | L4: 86753.01 | M4: 671.893 | N4: 17616 | O4: COBRANÇA DE ARMAZENAGEM CONJUNTA REFERENTE A DEZ/2024 | P4: =IF(BD_Receitas[[#This Row],[TIPO DE COBRANÇA]]="Operação Normal", _xlfn.XLOOKUP(BD_Receitas[[#This Row],[ID]],TabCondicoesComerciais[ID],TabCondicoesComerciais[Volume mínimo (m3)],0),"") -> 2040 | Q4: =_xlfn.XLOOKUP(BD_Receitas[[#This Row],[ID]],TabCondicoesComerciais[ID],TabCondicoesComerciais[Vol. 1ºGiro],0) -> 360 | R4: =IF(BD_Receitas[[#This Row],[TIPO DE COBRANÇA]]="Avanço Espaço", _xlfn.XLOOKUP(BD_Receitas[[#This Row],[ID]],TabCondicoesComerciais[ID],TabCondicoesComerciais[Avanço Espaço],0), IF(BD_Receitas[[#This Row],[TIPO DE COBRANÇA]]="Avanço Horário", _xlfn.XLOOKUP(BD_Receitas[[#This Row],[ID]],TabCondicoesComerciais[ID],TabCondicoesComerciais[Avanço Horário],0), IF(BD_Receitas[[#This Row],[TIPO DE COBRANÇA]]="Operação Normal", _xlfn.XLOOKUP(BD_Receitas[[#This Row],[ID]],TabCondicoesComerciais[ID],TabCondicoesComerciais[Tarifa 1º Giro],0),0))) -> 42.64 | S4: =IF(BD_Receitas[[#This Row],[TIPO DE COBRANÇA]]="Operação Normal", _xlfn.XLOOKUP(BD_Receitas[[#This Row],[ID]],TabCondicoesComerciais[ID],TabCondicoesComerciais[Tarifa 2º Giro],0),0) -> 42.64 | T4: =IFERROR(IF(BD_Receitas[[#This Row],[TIPO DE COBRANÇA]]<>"Operação Normal","",BD_Receitas[[#This Row],[Valor Total R$]]/ MAX(BD_Receitas[[#This Row],[Vol. Movimentado M³]], BD_Receitas[[#This Row],[Volume Mínimo ]]) ),0) -> 42.525985 | U4: =IFERROR(IF(BD_Receitas[[#This Row],[TIPO DE COBRANÇA]]<>"Operação Normal","", SUMIFS(BD_Receitas[Valor Total R$],BD_Receitas[CONGENERE],BD_Receitas[[#This Row],[CONGENERE]],BD_Receitas[FILIAL],BD_Receitas[[#This Row],[FILIAL]],BD_Receitas[DATA CONTABIL],BD_Receitas[[#This Row],[DATA CONTABIL]]) /BD_Receitas[[#This Row],[Vol. Movimentado M³]] ),0) -> 129.1173 | V4: =IF(BD_Receitas[[#This Row],[TIPO DE COBRANÇA]]<>"Operação Normal","",(BD_Receitas[[#This Row],[Volume 1º Giro]]*BD_Receitas[[#This Row],[Tarifa 1º Giro]])+(BD_Receitas[[#This Row],[Volume Mínimo ]]-BD_Receitas[[#This Row],[Volume 1º Giro]])*BD_Receitas[[#This Row],[Tarifa 2º Giro]]) -> 86985.6 | W4: =IF(BD_Receitas[[#This Row],[TIPO DE COBRANÇA]]<>"OPERAÇÃO NORMAL","", IF(BD_Receitas[[#This Row],[Vol. Movimentado M³]]<BD_Receitas[[#This Row],[Volume 1º Giro]],BD_Receitas[[#This Row],[Vol. Movimentado M³]]* BD_Receitas[[#This Row],[Tarifa 1º Giro]], (BD_Receitas[[#This Row],[Volume 1º Giro]]*BD_Receitas[[#This Row],[Tarifa 1º Giro]])+(BD_Receitas[[#This Row],[Vol. Movimentado M³]]-BD_Receitas[[#This Row],[Volume 1º Giro]])*BD_Receitas[[#This Row],[Tarifa 2º Giro]]) ) -> 28649.518 | X4: =IF(BD_Receitas[[#This Row],[TIPO DE COBRANÇA]] <> "OPERAÇÃO NORMAL","", IF(BD_Receitas[[#This Row],[Vol. Movimentado M³]]= BD_Receitas[[#This Row],[Volume Mínimo ]], "Vol. Movimentado igual ao Vol. Mínimo", IF(ROUND(BD_Receitas[[#This Row],[Tarifa 1º Giro]],3) <> ROUND(BD_Receitas[[#This Row],[Tarifa Cobrada]],3), "Conferir tarifa cobrada", IF(BD_Receitas[[#This Row],[Volume Mínimo ]]=0,"Ok", IF(BD_Receitas[[#This Row],[Vol. Movimentado M³]]<= BD_Receitas[[#This Row],[Volume Mínimo ]], IF(ROUND(BD_Receitas[[#This Row],[Valor Total R$]],2) = ROUND(BD_Receitas[[#This Row],[Valor Total R$]],2), "Ok","Verificar Cobrança"), IF(ROUND(BD_Receitas[[#This Row],[Valor Contrato]],2) = ROUND(BD_Receitas[[#This Row],[Valor Movimentado]],2), "OK","Verificar cobrança") ))))) -> Conferir tarifa cobrada
A5: 1503 | B5: 45658 | C5: BRASILIA | D5: MG RJ ES | E5: MINAS CENTRAL | F5: 1 | G5: Betim | H5: Atlantica | I5: Outras Receitas | J5: 0 | K5: 0 | P5: =IF(BD_Receitas[[#This Row],[TIPO DE COBRANÇA]]="Operação Normal", _xlfn.XLOOKUP(BD_Receitas[[#This Row],[ID]],TabCondicoesComerciais[ID],TabCondicoesComerciais[Volume mínimo (m3)],0),"") | Q5: =_xlfn.XLOOKUP(BD_Receitas[[#This Row],[ID]],TabCondicoesComerciais[ID],TabCondicoesComerciais[Vol. 1ºGiro],0) -> 360 | R5: =IF(BD_Receitas[[#This Row],[TIPO DE COBRANÇA]]="Avanço Espaço", _xlfn.XLOOKUP(BD_Receitas[[#This Row],[ID]],TabCondicoesComerciais[ID],TabCondicoesComerciais[Avanço Espaço],0), IF(BD_Receitas[[#This Row],[TIPO DE COBRANÇA]]="Avanço Horário", _xlfn.XLOOKUP(BD_Receitas[[#This Row],[ID]],TabCondicoesComerciais[ID],TabCondicoesComerciais[Avanço Horário],0), IF(BD_Receitas[[#This Row],[TIPO DE COBRANÇA]]="Operação Normal", _xlfn.XLOOKUP(BD_Receitas[[#This Row],[ID]],TabCondicoesComerciais[ID],TabCondicoesComerciais[Tarifa 1º Giro],0),0))) -> 0 | S5: =IF(BD_Receitas[[#This Row],[TIPO DE COBRANÇA]]="Operação Normal", _xlfn.XLOOKUP(BD_Receitas[[#This Row],[ID]],TabCondicoesComerciais[ID],TabCondicoesComerciais[Tarifa 2º Giro],0),0) -> 0 | T5: =IFERROR(IF(BD_Receitas[[#This Row],[TIPO DE COBRANÇA]]<>"Operação Normal","",BD_Receitas[[#This Row],[Valor Total R$]]/ MAX(BD_Receitas[[#This Row],[Vol. Movimentado M³]], BD_Receitas[[#This Row],[Volume Mínimo ]]) ),0) | U5: =IFERROR(IF(BD_Receitas[[#This Row],[TIPO DE COBRANÇA]]<>"Operação Normal","", SUMIFS(BD_Receitas[Valor Total R$],BD_Receitas[CONGENERE],BD_Receitas[[#This Row],[CONGENERE]],BD_Receitas[FILIAL],BD_Receitas[[#This Row],[FILIAL]],BD_Receitas[DATA CONTABIL],BD_Receitas[[#This Row],[DATA CONTABIL]]) /BD_Receitas[[#This Row],[Vol. Movimentado M³]] ),0) | V5: =IF(BD_Receitas[[#This Row],[TIPO DE COBRANÇA]]<>"Operação Normal","",(BD_Receitas[[#This Row],[Volume 1º Giro]]*BD_Receitas[[#This Row],[Tarifa 1º Giro]])+(BD_Receitas[[#This Row],[Volume Mínimo ]]-BD_Receitas[[#This Row],[Volume 1º Giro]])*BD_Receitas[[#This Row],[Tarifa 2º Giro]]) | W5: =IF(BD_Receitas[[#This Row],[TIPO DE COBRANÇA]]<>"OPERAÇÃO NORMAL","", IF(BD_Receitas[[#This Row],[Vol. Movimentado M³]]<BD_Receitas[[#This Row],[Volume 1º Giro]],BD_Receitas[[#This Row],[Vol. Movimentado M³]]* BD_Receitas[[#This Row],[Tarifa 1º Giro]], (BD_Receitas[[#This Row],[Volume 1º Giro]]*BD_Receitas[[#This Row],[Tarifa 1º Giro]])+(BD_Receitas[[#This Row],[Vol. Movimentado M³]]-BD_Receitas[[#This Row],[Volume 1º Giro]])*BD_Receitas[[#This Row],[Tarifa 2º Giro]]) ) | X5: =IF(BD_Receitas[[#This Row],[TIPO DE COBRANÇA]] <> "OPERAÇÃO NORMAL","", IF(BD_Receitas[[#This Row],[Vol. Movimentado M³]]= BD_Receitas[[#This Row],[Volume Mínimo ]], "Vol. Movimentado igual ao Vol. Mínimo", IF(ROUND(BD_Receitas[[#This Row],[Tarifa 1º Giro]],3) <> ROUND(BD_Receitas[[#This Row],[Tarifa Cobrada]],3), "Conferir tarifa cobrada", IF(BD_Receitas[[#This Row],[Volume Mínimo ]]=0,"Ok", IF(BD_Receitas[[#This Row],[Vol. Movimentado M³]]<= BD_Receitas[[#This Row],[Volume Mínimo ]], IF(ROUND(BD_Receitas[[#This Row],[Valor Total R$]],2) = ROUND(BD_Receitas[[#This Row],[Valor Total R$]],2), "Ok","Verificar Cobrança"), IF(ROUND(BD_Receitas[[#This Row],[Valor Contrato]],2) = ROUND(BD_Receitas[[#This Row],[Valor Movimentado]],2), "OK","Verificar cobrança") )))))
A6: 1102 | B6: 45658 | C6: BRASILIA | D6: MG RJ ES | E6: MINAS CENTRAL | F6: 1 | G6: Betim | H6: Ciapetro | I6: Avanço Espaço | J6: 0 | K6: 0 | P6: =IF(BD_Receitas[[#This Row],[TIPO DE COBRANÇA]]="Operação Normal", _xlfn.XLOOKUP(BD_Receitas[[#This Row],[ID]],TabCondicoesComerciais[ID],TabCondicoesComerciais[Volume mínimo (m3)],0),"") | Q6: =_xlfn.XLOOKUP(BD_Receitas[[#This Row],[ID]],TabCondicoesComerciais[ID],TabCondicoesComerciais[Vol. 1ºGiro],0) -> 365 | R6: =IF(BD_Receitas[[#This Row],[TIPO DE COBRANÇA]]="Avanço Espaço", _xlfn.XLOOKUP(BD_Receitas[[#This Row],[ID]],TabCondicoesComerciais[ID],TabCondicoesComerciais[Avanço Espaço],0), IF(BD_Receitas[[#This Row],[TIPO DE COBRANÇA]]="Avanço Horário", _xlfn.XLOOKUP(BD_Receitas[[#This Row],[ID]],TabCondicoesComerciais[ID],TabCondicoesComerciais[Avanço Horário],0), IF(BD_Receitas[[#This Row],[TIPO DE COBRANÇA]]="Operação Normal", _xlfn.XLOOKUP(BD_Receitas[[#This Row],[ID]],TabCondicoesComerciais[ID],TabCondicoesComerciais[Tarifa 1º Giro],0),0))) -> 0 | S6: =IF(BD_Receitas[[#This Row],[TIPO DE COBRANÇA]]="Operação Normal", _xlfn.XLOOKUP(BD_Receitas[[#This Row],[ID]],TabCondicoesComerciais[ID],TabCondicoesComerciais[Tarifa 2º Giro],0),0) -> 0 | T6: =IFERROR(IF(BD_Receitas[[#This Row],[TIPO DE COBRANÇA]]<>"Operação Normal","",BD_Receitas[[#This Row],[Valor Total R$]]/ MAX(BD_Receitas[[#This Row],[Vol. Movimentado M³]], BD_Receitas[[#This Row],[Volume Mínimo ]]) ),0) | U6: =IFERROR(IF(BD_Receitas[[#This Row],[TIPO DE COBRANÇA]]<>"Operação Normal","", SUMIFS(BD_Receitas[Valor Total R$],BD_Receitas[CONGENERE],BD_Receitas[[#This Row],[CONGENERE]],BD_Receitas[FILIAL],BD_Receitas[[#This Row],[FILIAL]],BD_Receitas[DATA CONTABIL],BD_Receitas[[#This Row],[DATA CONTABIL]]) /BD_Receitas[[#This Row],[Vol. Movimentado M³]] ),0) | V6: =IF(BD_Receitas[[#This Row],[TIPO DE COBRANÇA]]<>"Operação Normal","",(BD_Receitas[[#This Row],[Volume 1º Giro]]*BD_Receitas[[#This Row],[Tarifa 1º Giro]])+(BD_Receitas[[#This Row],[Volume Mínimo ]]-BD_Receitas[[#This Row],[Volume 1º Giro]])*BD_Receitas[[#This Row],[Tarifa 2º Giro]]) | W6: =IF(BD_Receitas[[#This Row],[TIPO DE COBRANÇA]]<>"OPERAÇÃO NORMAL","", IF(BD_Receitas[[#This Row],[Vol. Movimentado M³]]<BD_Receitas[[#This Row],[Volume 1º Giro]],BD_Receitas[[#This Row],[Vol. Movimentado M³]]* BD_Receitas[[#This Row],[Tarifa 1º Giro]], (BD_Receitas[[#This Row],[Volume 1º Giro]]*BD_Receitas[[#This Row],[Tarifa 1º Giro]])+(BD_Receitas[[#This Row],[Vol. Movimentado M³]]-BD_Receitas[[#This Row],[Volume 1º Giro]])*BD_Receitas[[#This Row],[Tarifa 2º Giro]]) ) | X6: =IF(BD_Receitas[[#This Row],[TIPO DE COBRANÇA]] <> "OPERAÇÃO NORMAL","", IF(BD_Receitas[[#This Row],[Vol. Movimentado M³]]= BD_Receitas[[#This Row],[Volume Mínimo ]], "Vol. Movimentado igual ao Vol. Mínimo", IF(ROUND(BD_Receitas[[#This Row],[Tarifa 1º Giro]],3) <> ROUND(BD_Receitas[[#This Row],[Tarifa Cobrada]],3), "Conferir tarifa cobrada", IF(BD_Receitas[[#This Row],[Volume Mínimo ]]=0,"Ok", IF(BD_Receitas[[#This Row],[Vol. Movimentado M³]]<= BD_Receitas[[#This Row],[Volume Mínimo ]], IF(ROUND(BD_Receitas[[#This Row],[Valor Total R$]],2) = ROUND(BD_Receitas[[#This Row],[Valor Total R$]],2), "Ok","Verificar Cobrança"), IF(ROUND(BD_Receitas[[#This Row],[Valor Contrato]],2) = ROUND(BD_Receitas[[#This Row],[Valor Movimentado]],2), "OK","Verificar cobrança") )))))
A7: 1102 | B7: 45658 | C7: BRASILIA | D7: MG RJ ES | E7: MINAS CENTRAL | F7: 1 | G7: Betim | H7: Ciapetro | I7: Avanço Horário | J7: 0 | K7: 0 | P7: =IF(BD_Receitas[[#This Row],[TIPO DE COBRANÇA]]="Operação Normal", _xlfn.XLOOKUP(BD_Receitas[[#This Row],[ID]],TabCondicoesComerciais[ID],TabCondicoesComerciais[Volume mínimo (m3)],0),"") | Q7: =_xlfn.XLOOKUP(BD_Receitas[[#This Row],[ID]],TabCondicoesComerciais[ID],TabCondicoesComerciais[Vol. 1ºGiro],0) -> 365 | R7: =IF(BD_Receitas[[#This Row],[TIPO DE COBRANÇA]]="Avanço Espaço", _xlfn.XLOOKUP(BD_Receitas[[#This Row],[ID]],TabCondicoesComerciais[ID],TabCondicoesComerciais[Avanço Espaço],0), IF(BD_Receitas[[#This Row],[TIPO DE COBRANÇA]]="Avanço Horário", _xlfn.XLOOKUP(BD_Receitas[[#This Row],[ID]],TabCondicoesComerciais[ID],TabCondicoesComerciais[Avanço Horário],0), IF(BD_Receitas[[#This Row],[TIPO DE COBRANÇA]]="Operação Normal", _xlfn.XLOOKUP(BD_Receitas[[#This Row],[ID]],TabCondicoesComerciais[ID],TabCondicoesComerciais[Tarifa 1º Giro],0),0))) -> 0 | S7: =IF(BD_Receitas[[#This Row],[TIPO DE COBRANÇA]]="Operação Normal", _xlfn.XLOOKUP(BD_Receitas[[#This Row],[ID]],TabCondicoesComerciais[ID],TabCondicoesComerciais[Tarifa 2º Giro],0),0) -> 0 | T7: =IFERROR(IF(BD_Receitas[[#This Row],[TIPO DE COBRANÇA]]<>"Operação Normal","",BD_Receitas[[#This Row],[Valor Total R$]]/ MAX(BD_Receitas[[#This Row],[Vol. Movimentado M³]], BD_Receitas[[#This Row],[Volume Mínimo ]]) ),0) | U7: =IFERROR(IF(BD_Receitas[[#This Row],[TIPO DE COBRANÇA]]<>"Operação Normal","", SUMIFS(BD_Receitas[Valor Total R$],BD_Receitas[CONGENERE],BD_Receitas[[#This Row],[CONGENERE]],BD_Receitas[FILIAL],BD_Receitas[[#This Row],[FILIAL]],BD_Receitas[DATA CONTABIL],BD_Receitas[[#This Row],[DATA CONTABIL]]) /BD_Receitas[[#This Row],[Vol. Movimentado M³]] ),0) | V7: =IF(BD_Receitas[[#This Row],[TIPO DE COBRANÇA]]<>"Operação Normal","",(BD_Receitas[[#This Row],[Volume 1º Giro]]*BD_Receitas[[#This Row],[Tarifa 1º Giro]])+(BD_Receitas[[#This Row],[Volume Mínimo ]]-BD_Receitas[[#This Row],[Volume 1º Giro]])*BD_Receitas[[#This Row],[Tarifa 2º Giro]]) | W7: =IF(BD_Receitas[[#This Row],[TIPO DE COBRANÇA]]<>"OPERAÇÃO NORMAL","", IF(BD_Receitas[[#This Row],[Vol. Movimentado M³]]<BD_Receitas[[#This Row],[Volume 1º Giro]],BD_Receitas[[#This Row],[Vol. Movimentado M³]]* BD_Receitas[[#This Row],[Tarifa 1º Giro]], (BD_Receitas[[#This Row],[Volume 1º Giro]]*BD_Receitas[[#This Row],[Tarifa 1º Giro]])+(BD_Receitas[[#This Row],[Vol. Movimentado M³]]-BD_Receitas[[#This Row],[Volume 1º Giro]])*BD_Receitas[[#This Row],[Tarifa 2º Giro]]) ) | X7: =IF(BD_Receitas[[#This Row],[TIPO DE COBRANÇA]] <> "OPERAÇÃO NORMAL","", IF(BD_Receitas[[#This Row],[Vol. Movimentado M³]]= BD_Receitas[[#This Row],[Volume Mínimo ]], "Vol. Movimentado igual ao Vol. Mínimo", IF(ROUND(BD_Receitas[[#This Row],[Tarifa 1º Giro]],3) <> ROUND(BD_Receitas[[#This Row],[Tarifa Cobrada]],3), "Conferir tarifa cobrada", IF(BD_Receitas[[#This Row],[Volume Mínimo ]]=0,"Ok", IF(BD_Receitas[[#This Row],[Vol. Movimentado M³]]<= BD_Receitas[[#This Row],[Volume Mínimo ]], IF(ROUND(BD_Receitas[[#This Row],[Valor Total R$]],2) = ROUND(BD_Receitas[[#This Row],[Valor Total R$]],2), "Ok","Verificar Cobrança"), IF(ROUND(BD_Receitas[[#This Row],[Valor Contrato]],2) = ROUND(BD_Receitas[[#This Row],[Valor Movimentado]],2), "OK","Verificar cobrança") )))))
A8: 1102 | B8: 45658 | C8: BRASILIA | D8: MG RJ ES | E8: MINAS CENTRAL | F8: 1 | G8: Betim | H8: Ciapetro | I8: Operação Normal | J8: 28839.059 | K8: 1500 | L8: 17387.03 | M8: 608.175 | N8: 17617 | O8: COBRANÇA DE ARMAZENAGEM CONJUNTA REFERENTE A DEZ/2024 | P8: =IF(BD_Receitas[[#This Row],[TIPO DE COBRANÇA]]="Operação Normal", _xlfn.XLOOKUP(BD_Receitas[[#This Row],[ID]],TabCondicoesComerciais[ID],TabCondicoesComerciais[Volume mínimo (m3)],0),"") -> 936 | Q8: =_xlfn.XLOOKUP(BD_Receitas[[#This Row],[ID]],TabCondicoesComerciais[ID],TabCondicoesComerciais[Vol. 1ºGiro],0) -> 365 | R8: =IF(BD_Receitas[[#This Row],[TIPO DE COBRANÇA]]="Avanço Espaço", _xlfn.XLOOKUP(BD_Receitas[[#This Row],[ID]],TabCondicoesComerciais[ID],TabCondicoesComerciais[Avanço Espaço],0), IF(BD_Receitas[[#This Row],[TIPO DE COBRANÇA]]="Avanço Horário", _xlfn.XLOOKUP(BD_Receitas[[#This Row],[ID]],TabCondicoesComerciais[ID],TabCondicoesComerciais[Avanço Horário],0), IF(BD_Receitas[[#This Row],[TIPO DE COBRANÇA]]="Operação Normal", _xlfn.XLOOKUP(BD_Receitas[[#This Row],[ID]],TabCondicoesComerciais[ID],TabCondicoesComerciais[Tarifa 1º Giro],0),0))) -> 17.87 | S8: =IF(BD_Receitas[[#This Row],[TIPO DE COBRANÇA]]="Operação Normal", _xlfn.XLOOKUP(BD_Receitas[[#This Row],[ID]],TabCondicoesComerciais[ID],TabCondicoesComerciais[Tarifa 2º Giro],0),0) -> 17.87 | T8: =IFERROR(IF(BD_Receitas[[#This Row],[TIPO DE COBRANÇA]]<>"Operação Normal","",BD_Receitas[[#This Row],[Valor Total R$]]/ MAX(BD_Receitas[[#This Row],[Vol. Movimentado M³]], BD_Receitas[[#This Row],[Volume Mínimo ]]) ),0) -> 18.575887 | U8: =IFERROR(IF(BD_Receitas[[#This Row],[TIPO DE COBRANÇA]]<>"Operação Normal","", SUMIFS(BD_Receitas[Valor Total R$],BD_Receitas[CONGENERE],BD_Receitas[[#This Row],[CONGENERE]],BD_Receitas[FILIAL],BD_Receitas[[#This Row],[FILIAL]],BD_Receitas[DATA CONTABIL],BD_Receitas[[#This Row],[DATA CONTABIL]]) /BD_Receitas[[#This Row],[Vol. Movimentado M³]] ),0) -> 28.58886 | V8: =IF(BD_Receitas[[#This Row],[TIPO DE COBRANÇA]]<>"Operação Normal","",(BD_Receitas[[#This Row],[Volume 1º Giro]]*BD_Receitas[[#This Row],[Tarifa 1º Giro]])+(BD_Receitas[[#This Row],[Volume Mínimo ]]-BD_Receitas[[#This Row],[Volume 1º Giro]])*BD_Receitas[[#This Row],[Tarifa 2º Giro]]) -> 16726.32 | W8: =IF(BD_Receitas[[#This Row],[TIPO DE COBRANÇA]]<>"OPERAÇÃO NORMAL","", IF(BD_Receitas[[#This Row],[Vol. Movimentado M³]]<BD_Receitas[[#This Row],[Volume 1º Giro]],BD_Receitas[[#This Row],[Vol. Movimentado M³]]* BD_Receitas[[#This Row],[Tarifa 1º Giro]], (BD_Receitas[[#This Row],[Volume 1º Giro]]*BD_Receitas[[#This Row],[Tarifa 1º Giro]])+(BD_Receitas[[#This Row],[Vol. Movimentado M³]]-BD_Receitas[[#This Row],[Volume 1º Giro]])*BD_Receitas[[#This Row],[Tarifa 2º Giro]]) ) -> 10868.087 | X8: =IF(BD_Receitas[[#This Row],[TIPO DE COBRANÇA]] <> "OPERAÇÃO NORMAL","", IF(BD_Receitas[[#This Row],[Vol. Movimentado M³]]= BD_Receitas[[#This Row],[Volume Mínimo ]], "Vol. Movimentado igual ao Vol. Mínimo", IF(ROUND(BD_Receitas[[#This Row],[Tarifa 1º Giro]],3) <> ROUND(BD_Receitas[[#This Row],[Tarifa Cobrada]],3), "Conferir tarifa cobrada", IF(BD_Receitas[[#This Row],[Volume Mínimo ]]=0,"Ok", IF(BD_Receitas[[#This Row],[Vol. Movimentado M³]]<= BD_Receitas[[#This Row],[Volume Mínimo ]], IF(ROUND(BD_Receitas[[#This Row],[Valor Total R$]],2) = ROUND(BD_Receitas[[#This Row],[Valor Total R$]],2), "Ok","Verificar Cobrança"), IF(ROUND(BD_Receitas[[#This Row],[Valor Contrato]],2) = ROUND(BD_Receitas[[#This Row],[Valor Movimentado]],2), "OK","Verificar cobrança") ))))) -> Conferir tarifa cobrada
A9: 1102 | B9: 45658 | C9: BRASILIA | D9: MG RJ ES | E9: MINAS CENTRAL | F9: 1 | G9: Betim | H9: Ciapetro | I9: Outras Receitas | J9: 0 | K9: 0 | P9: =IF(BD_Receitas[[#This Row],[TIPO DE COBRANÇA]]="Operação Normal", _xlfn.XLOOKUP(BD_Receitas[[#This Row],[ID]],TabCondicoesComerciais[ID],TabCondicoesComerciais[Volume mínimo (m3)],0),"") | Q9: =_xlfn.XLOOKUP(BD_Receitas[[#This Row],[ID]],TabCondicoesComerciais[ID],TabCondicoesComerciais[Vol. 1ºGiro],0) -> 365 | R9: =IF(BD_Receitas[[#This Row],[TIPO DE COBRANÇA]]="Avanço Espaço", _xlfn.XLOOKUP(BD_Receitas[[#This Row],[ID]],TabCondicoesComerciais[ID],TabCondicoesComerciais[Avanço Espaço],0), IF(BD_Receitas[[#This Row],[TIPO DE COBRANÇA]]="Avanço Horário", _xlfn.XLOOKUP(BD_Receitas[[#This Row],[ID]],TabCondicoesComerciais[ID],TabCondicoesComerciais[Avanço Horário],0), IF(BD_Receitas[[#This Row],[TIPO DE COBRANÇA]]="Operação Normal", _xlfn.XLOOKUP(BD_Receitas[[#This Row],[ID]],TabCondicoesComerciais[ID],TabCondicoesComerciais[Tarifa 1º Giro],0),0))) -> 0 | S9: =IF(BD_Receitas[[#This Row],[TIPO DE COBRANÇA]]="Operação Normal", _xlfn.XLOOKUP(BD_Receitas[[#This Row],[ID]],TabCondicoesComerciais[ID],TabCondicoesComerciais[Tarifa 2º Giro],0),0) -> 0 | T9: =IFERROR(IF(BD_Receitas[[#This Row],[TIPO DE COBRANÇA]]<>"Operação Normal","",BD_Receitas[[#This Row],[Valor Total R$]]/ MAX(BD_Receitas[[#This Row],[Vol. Movimentado M³]], BD_Receitas[[#This Row],[Volume Mínimo ]]) ),0) | U9: =IFERROR(IF(BD_Receitas[[#This Row],[TIPO DE COBRANÇA]]<>"Operação Normal","", SUMIFS(BD_Receitas[Valor Total R$],BD_Receitas[CONGENERE],BD_Receitas[[#This Row],[CONGENERE]],BD_Receitas[FILIAL],BD_Receitas[[#This Row],[FILIAL]],BD_Receitas[DATA CONTABIL],BD_Receitas[[#This Row],[DATA CONTABIL]]) /BD_Receitas[[#This Row],[Vol. Movimentado M³]] ),0) | V9: =IF(BD_Receitas[[#This Row],[TIPO DE COBRANÇA]]<>"Operação Normal","",(BD_Receitas[[#This Row],[Volume 1º Giro]]*BD_Receitas[[#This Row],[Tarifa 1º Giro]])+(BD_Receitas[[#This Row],[Volume Mínimo ]]-BD_Receitas[[#This Row],[Volume 1º Giro]])*BD_Receitas[[#This Row],[Tarifa 2º Giro]]) | W9: =IF(BD_Receitas[[#This Row],[TIPO DE COBRANÇA]]<>"OPERAÇÃO NORMAL","", IF(BD_Receitas[[#This Row],[Vol. Movimentado M³]]<BD_Receitas[[#This Row],[Volume 1º Giro]],BD_Receitas[[#This Row],[Vol. Movimentado M³]]* BD_Receitas[[#This Row],[Tarifa 1º Giro]], (BD_Receitas[[#This Row],[Volume 1º Giro]]*BD_Receitas[[#This Row],[Tarifa 1º Giro]])+(BD_Receitas[[#This Row],[Vol. Movimentado M³]]-BD_Receitas[[#This Row],[Volume 1º Giro]])*BD_Receitas[[#This Row],[Tarifa 2º Giro]]) ) | X9: =IF(BD_Receitas[[#This Row],[TIPO DE COBRANÇA]] <> "OPERAÇÃO NORMAL","", IF(BD_Receitas[[#This Row],[Vol. Movimentado M³]]= BD_Receitas[[#This Row],[Volume Mínimo ]], "Vol. Movimentado igual ao Vol. Mínimo", IF(ROUND(BD_Receitas[[#This Row],[Tarifa 1º Giro]],3) <> ROUND(BD_Receitas[[#This Row],[Tarifa Cobrada]],3), "Conferir tarifa cobrada", IF(BD_Receitas[[#This Row],[Volume Mínimo ]]=0,"Ok", IF(BD_Receitas[[#This Row],[Vol. Movimentado M³]]<= BD_Receitas[[#This Row],[Volume Mínimo ]], IF(ROUND(BD_Receitas[[#This Row],[Valor Total R$]],2) = ROUND(BD_Receitas[[#This Row],[Valor Total R$]],2), "Ok","Verificar Cobrança"), IF(ROUND(BD_Receitas[[#This Row],[Valor Contrato]],2) = ROUND(BD_Receitas[[#This Row],[Valor Movimentado]],2), "OK","Verificar cobrança") )))))
A10: 16 | B10: 45658 | C10: BRASILIA | D10: MG RJ ES | E10: MINAS CENTRAL | F10: 1 | G10: Betim | H10: Rede Sol | I10: Avanço Espaço | J10: 0 | K10: 0 | P10: =IF(BD_Receitas[[#This Row],[TIPO DE COBRANÇA]]="Operação Normal", _xlfn.XLOOKUP(BD_Receitas[[#This Row],[ID]],TabCondicoesComerciais[ID],TabCondicoesComerciais[Volume mínimo (m3)],0),"") | Q10: =_xlfn.XLOOKUP(BD_Receitas[[#This Row],[ID]],TabCondicoesComerciais[ID],TabCondicoesComerciais[Vol. 1ºGiro],0) -> 100 | R10: =IF(BD_Receitas[[#This Row],[TIPO DE COBRANÇA]]="Avanço Espaço", _xlfn.XLOOKUP(BD_Receitas[[#This Row],[ID]],TabCondicoesComerciais[ID],TabCondicoesComerciais[Avanço Espaço],0), IF(BD_Receitas[[#This Row],[TIPO DE COBRANÇA]]="Avanço Horário", _xlfn.XLOOKUP(BD_Receitas[[#This Row],[ID]],TabCondicoesComerciais[ID],TabCondicoesComerciais[Avanço Horário],0), IF(BD_Receitas[[#This Row],[TIPO DE COBRANÇA]]="Operação Normal", _xlfn.XLOOKUP(BD_Receitas[[#This Row],[ID]],TabCondicoesComerciais[ID],TabCondicoesComerciais[Tarifa 1º Giro],0),0))) -> 0 | S10: =IF(BD_Receitas[[#This Row],[TIPO DE COBRANÇA]]="Operação Normal", _xlfn.XLOOKUP(BD_Receitas[[#This Row],[ID]],TabCondicoesComerciais[ID],TabCondicoesComerciais[Tarifa 2º Giro],0),0) -> 0 | T10: =IFERROR(IF(BD_Receitas[[#This Row],[TIPO DE COBRANÇA]]<>"Operação Normal","",BD_Receitas[[#This Row],[Valor Total R$]]/ MAX(BD_Receitas[[#This Row],[Vol. Movimentado M³]], BD_Receitas[[#This Row],[Volume Mínimo ]]) ),0) | U10: =IFERROR(IF(BD_Receitas[[#This Row],[TIPO DE COBRANÇA]]<>"Operação Normal","", SUMIFS(BD_Receitas[Valor Total R$],BD_Receitas[CONGENERE],BD_Receitas[[#This Row],[CONGENERE]],BD_Receitas[FILIAL],BD_Receitas[[#This Row],[FILIAL]],BD_Receitas[DATA CONTABIL],BD_Receitas[[#This Row],[DATA CONTABIL]]) /BD_Receitas[[#This Row],[Vol. Movimentado M³]] ),0) | V10: =IF(BD_Receitas[[#This Row],[TIPO DE COBRANÇA]]<>"Operação Normal","",(BD_Receitas[[#This Row],[Volume 1º Giro]]*BD_Receitas[[#This Row],[Tarifa 1º Giro]])+(BD_Receitas[[#This Row],[Volume Mínimo ]]-BD_Receitas[[#This Row],[Volume 1º Giro]])*BD_Receitas[[#This Row],[Tarifa 2º Giro]]) | W10: =IF(BD_Receitas[[#This Row],[TIPO DE COBRANÇA]]<>"OPERAÇÃO NORMAL","", IF(BD_Receitas[[#This Row],[Vol. Movimentado M³]]<BD_Receitas[[#This Row],[Volume 1º Giro]],BD_Receitas[[#This Row],[Vol. Movimentado M³]]* BD_Receitas[[#This Row],[Tarifa 1º Giro]], (BD_Receitas[[#This Row],[Volume 1º Giro]]*BD_Receitas[[#This Row],[Tarifa 1º Giro]])+(BD_Receitas[[#This Row],[Vol. Movimentado M³]]-BD_Receitas[[#This Row],[Volume 1º Giro]])*BD_Receitas[[#This Row],[Tarifa 2º Giro]]) ) | X10: =IF(BD_Receitas[[#This Row],[TIPO DE COBRANÇA]] <> "OPERAÇÃO NORMAL","", IF(BD_Receitas[[#This Row],[Vol. Movimentado M³]]= BD_Receitas[[#This Row],[Volume Mínimo ]], "Vol. Movimentado igual ao Vol. Mínimo", IF(ROUND(BD_Receitas[[#This Row],[Tarifa 1º Giro]],3) <> ROUND(BD_Receitas[[#This Row],[Tarifa Cobrada]],3), "Conferir tarifa cobrada", IF(BD_Receitas[[#This Row],[Volume Mínimo ]]=0,"Ok", IF(BD_Receitas[[#This Row],[Vol. Movimentado M³]]<= BD_Receitas[[#This Row],[Volume Mínimo ]], IF(ROUND(BD_Receitas[[#This Row],[Valor Total R$]],2) = ROUND(BD_Receitas[[#This Row],[Valor Total R$]],2), "Ok","Verificar Cobrança"), IF(ROUND(BD_Receitas[[#This Row],[Valor Contrato]],2) = ROUND(BD_Receitas[[#This Row],[Valor Movimentado]],2), "OK","Verificar cobrança") )))))
A11: 16 | B11: 45658 | C11: BRASILIA | D11: MG RJ ES | E11: MINAS CENTRAL | F11: 1 | G11: Betim | H11: Rede Sol | I11: Avanço Horário | J11: 0 | K11: 0 | P11: =IF(BD_Receitas[[#This Row],[TIPO DE COBRANÇA]]="Operação Normal", _xlfn.XLOOKUP(BD_Receitas[[#This Row],[ID]],TabCondicoesComerciais[ID],TabCondicoesComerciais[Volume mínimo (m3)],0),"") | Q11: =_xlfn.XLOOKUP(BD_Receitas[[#This Row],[ID]],TabCondicoesComerciais[ID],TabCondicoesComerciais[Vol. 1ºGiro],0) -> 100 | R11: =IF(BD_Receitas[[#This Row],[TIPO DE COBRANÇA]]="Avanço Espaço", _xlfn.XLOOKUP(BD_Receitas[[#This Row],[ID]],TabCondicoesComerciais[ID],TabCondicoesComerciais[Avanço Espaço],0), IF(BD_Receitas[[#This Row],[TIPO DE COBRANÇA]]="Avanço Horário", _xlfn.XLOOKUP(BD_Receitas[[#This Row],[ID]],TabCondicoesComerciais[ID],TabCondicoesComerciais[Avanço Horário],0), IF(BD_Receitas[[#This Row],[TIPO DE COBRANÇA]]="Operação Normal", _xlfn.XLOOKUP(BD_Receitas[[#This Row],[ID]],TabCondicoesComerciais[ID],TabCondicoesComerciais[Tarifa 1º Giro],0),0))) -> 0 | S11: =IF(BD_Receitas[[#This Row],[TIPO DE COBRANÇA]]="Operação Normal", _xlfn.XLOOKUP(BD_Receitas[[#This Row],[ID]],TabCondicoesComerciais[ID],TabCondicoesComerciais[Tarifa 2º Giro],0),0) -> 0 | T11: =IFERROR(IF(BD_Receitas[[#This Row],[TIPO DE COBRANÇA]]<>"Operação Normal","",BD_Receitas[[#This Row],[Valor Total R$]]/ MAX(BD_Receitas[[#This Row],[Vol. Movimentado M³]], BD_Receitas[[#This Row],[Volume Mínimo ]]) ),0) | U11: =IFERROR(IF(BD_Receitas[[#This Row],[TIPO DE COBRANÇA]]<>"Operação Normal","", SUMIFS(BD_Receitas[Valor Total R$],BD_Receitas[CONGENERE],BD_Receitas[[#This Row],[CONGENERE]],BD_Receitas[FILIAL],BD_Receitas[[#This Row],[FILIAL]],BD_Receitas[DATA CONTABIL],BD_Receitas[[#This Row],[DATA CONTABIL]]) /BD_Receitas[[#This Row],[Vol. Movimentado M³]] ),0) | V11: =IF(BD_Receitas[[#This Row],[TIPO DE COBRANÇA]]<>"Operação Normal","",(BD_Receitas[[#This Row],[Volume 1º Giro]]*BD_Receitas[[#This Row],[Tarifa 1º Giro]])+(BD_Receitas[[#This Row],[Volume Mínimo ]]-BD_Receitas[[#This Row],[Volume 1º Giro]])*BD_Receitas[[#This Row],[Tarifa 2º Giro]]) | W11: =IF(BD_Receitas[[#This Row],[TIPO DE COBRANÇA]]<>"OPERAÇÃO NORMAL","", IF(BD_Receitas[[#This Row],[Vol. Movimentado M³]]<BD_Receitas[[#This Row],[Volume 1º Giro]],BD_Receitas[[#This Row],[Vol. Movimentado M³]]* BD_Receitas[[#This Row],[Tarifa 1º Giro]], (BD_Receitas[[#This Row],[Volume 1º Giro]]*BD_Receitas[[#This Row],[Tarifa 1º Giro]])+(BD_Receitas[[#This Row],[Vol. Movimentado M³]]-BD_Receitas[[#This Row],[Volume 1º Giro]])*BD_Receitas[[#This Row],[Tarifa 2º Giro]]) ) | X11: =IF(BD_Receitas[[#This Row],[TIPO DE COBRANÇA]] <> "OPERAÇÃO NORMAL","", IF(BD_Receitas[[#This Row],[Vol. Movimentado M³]]= BD_Receitas[[#This Row],[Volume Mínimo ]], "Vol. Movimentado igual ao Vol. Mínimo", IF(ROUND(BD_Receitas[[#This Row],[Tarifa 1º Giro]],3) <> ROUND(BD_Receitas[[#This Row],[Tarifa Cobrada]],3), "Conferir tarifa cobrada", IF(BD_Receitas[[#This Row],[Volume Mínimo ]]=0,"Ok", IF(BD_Receitas[[#This Row],[Vol. Movimentado M³]]<= BD_Receitas[[#This Row],[Volume Mínimo ]], IF(ROUND(BD_Receitas[[#This Row],[Valor Total R$]],2) = ROUND(BD_Receitas[[#This Row],[Valor Total R$]],2), "Ok","Verificar Cobrança"), IF(ROUND(BD_Receitas[[#This Row],[Valor Contrato]],2) = ROUND(BD_Receitas[[#This Row],[Valor Movimentado]],2), "OK","Verificar cobrança") )))))
A12: 16 | B12: 45658 | C12: BRASILIA | D12: MG RJ ES | E12: MINAS CENTRAL | F12: 1 | G12: Betim | H12: Rede Sol | I12: Operação Normal | J12: 9355.5094 | K12: 300 | P12: =IF(BD_Receitas[[#This Row],[TIPO DE COBRANÇA]]="Operação Normal", _xlfn.XLOOKUP(BD_Receitas[[#This Row],[ID]],TabCondicoesComerciais[ID],TabCondicoesComerciais[Volume mínimo (m3)],0),"") -> 300 | Q12: =_xlfn.XLOOKUP(BD_Receitas[[#This Row],[ID]],TabCondicoesComerciais[ID],TabCondicoesComerciais[Vol. 1ºGiro],0) -> 100 | R12: =IF(BD_Receitas[[#This Row],[TIPO DE COBRANÇA]]="Avanço Espaço", _xlfn.XLOOKUP(BD_Receitas[[#This Row],[ID]],TabCondicoesComerciais[ID],TabCondicoesComerciais[Avanço Espaço],0), IF(BD_Receitas[[#This Row],[TIPO DE COBRANÇA]]="Avanço Horário", _xlfn.XLOOKUP(BD_Receitas[[#This Row],[ID]],TabCondicoesComerciais[ID],TabCondicoesComerciais[Avanço Horário],0), IF(BD_Receitas[[#This Row],[TIPO DE COBRANÇA]]="Operação Normal", _xlfn.XLOOKUP(BD_Receitas[[#This Row],[ID]],TabCondicoesComerciais[ID],TabCondicoesComerciais[Tarifa 1º Giro],0),0))) -> 30 | S12: =IF(BD_Receitas[[#This Row],[TIPO DE COBRANÇA]]="Operação Normal", _xlfn.XLOOKUP(BD_Receitas[[#This Row],[ID]],TabCondicoesComerciais[ID],TabCondicoesComerciais[Tarifa 2º Giro],0),0) -> 30 | T12: =IFERROR(IF(BD_Receitas[[#This Row],[TIPO DE COBRANÇA]]<>"Operação Normal","",BD_Receitas[[#This Row],[Valor Total R$]]/ MAX(BD_Receitas[[#This Row],[Vol. Movimentado M³]], BD_Receitas[[#This Row],[Volume Mínimo ]]) ),0) -> 0 | U12: =IFERROR(IF(BD_Receitas[[#This Row],[TIPO DE COBRANÇA]]<>"Operação Normal","", SUMIFS(BD_Receitas[Valor Total R$],BD_Receitas[CONGENERE],BD_Receitas[[#This Row],[CONGENERE]],BD_Receitas[FILIAL],BD_Receitas[[#This Row],[FILIAL]],BD_Receitas[DATA CONTABIL],BD_Receitas[[#This Row],[DATA CONTABIL]]) /BD_Receitas[[#This Row],[Vol. Movimentado M³]] ),0) -> 0 | V12: =IF(BD_Receitas[[#This Row],[TIPO DE COBRANÇA]]<>"Operação Normal","",(BD_Receitas[[#This Row],[Volume 1º Giro]]*BD_Receitas[[#This Row],[Tarifa 1º Giro]])+(BD_Receitas[[#This Row],[Volume Mínimo ]]-BD_Receitas[[#This Row],[Volume 1º Giro]])*BD_Receitas[[#This Row],[Tarifa 2º Giro]]) -> 9000 | W12: =IF(BD_Receitas[[#This Row],[TIPO DE COBRANÇA]]<>"OPERAÇÃO NORMAL","", IF(BD_Receitas[[#This Row],[Vol. Movimentado M³]]<BD_Receitas[[#This Row],[Volume 1º Giro]],BD_Receitas[[#This Row],[Vol. Movimentado M³]]* BD_Receitas[[#This Row],[Tarifa 1º Giro]], (BD_Receitas[[#This Row],[Volume 1º Giro]]*BD_Receitas[[#This Row],[Tarifa 1º Giro]])+(BD_Receitas[[#This Row],[Vol. Movimentado M³]]-BD_Receitas[[#This Row],[Volume 1º Giro]])*BD_Receitas[[#This Row],[Tarifa 2º Giro]]) ) -> 0 | X12: =IF(BD_Receitas[[#This Row],[TIPO DE COBRANÇA]] <> "OPERAÇÃO NORMAL","", IF(BD_Receitas[[#This Row],[Vol. Movimentado M³]]= BD_Receitas[[#This Row],[Volume Mínimo ]], "Vol. Movimentado igual ao Vol. Mínimo", IF(ROUND(BD_Receitas[[#This Row],[Tarifa 1º Giro]],3) <> ROUND(BD_Receitas[[#This Row],[Tarifa Cobrada]],3), "Conferir tarifa cobrada", IF(BD_Receitas[[#This Row],[Volume Mínimo ]]=0,"Ok", IF(BD_Receitas[[#This Row],[Vol. Movimentado M³]]<= BD_Receitas[[#This Row],[Volume Mínimo ]], IF(ROUND(BD_Receitas[[#This Row],[Valor Total R$]],2) = ROUND(BD_Receitas[[#This Row],[Valor Total R$]],2), "Ok","Verificar Cobrança"), IF(ROUND(BD_Receitas[[#This Row],[Valor Contrato]],2) = ROUND(BD_Receitas[[#This Row],[Valor Movimentado]],2), "OK","Verificar cobrança") ))))) -> Conferir tarifa cobrada
A13: 16 | B13: 45658 | C13: BRASILIA | D13: MG RJ ES | E13: MINAS CENTRAL | F13: 1 | G13: Betim | H13: Rede Sol | I13: Outras Receitas | J13: 0 | K13: 0 | P13: =IF(BD_Receitas[[#This Row],[TIPO DE COBRANÇA]]="Operação Normal", _xlfn.XLOOKUP(BD_Receitas[[#This Row],[ID]],TabCondicoesComerciais[ID],TabCondicoesComerciais[Volume mínimo (m3)],0),"") | Q13: =_xlfn.XLOOKUP(BD_Receitas[[#This Row],[ID]],TabCondicoesComerciais[ID],TabCondicoesComerciais[Vol. 1ºGiro],0) -> 100 | R13: =IF(BD_Receitas[[#This Row],[TIPO DE COBRANÇA]]="Avanço Espaço", _xlfn.XLOOKUP(BD_Receitas[[#This Row],[ID]],TabCondicoesComerciais[ID],TabCondicoesComerciais[Avanço Espaço],0), IF(BD_Receitas[[#This Row],[TIPO DE COBRANÇA]]="Avanço Horário", _xlfn.XLOOKUP(BD_Receitas[[#This Row],[ID]],TabCondicoesComerciais[ID],TabCondicoesComerciais[Avanço Horário],0), IF(BD_Receitas[[#This Row],[TIPO DE COBRANÇA]]="Operação Normal", _xlfn.XLOOKUP(BD_Receitas[[#This Row],[ID]],TabCondicoesComerciais[ID],TabCondicoesComerciais[Tarifa 1º Giro],0),0))) -> 0 | S13: =IF(BD_Receitas[[#This Row],[TIPO DE COBRANÇA]]="Operação Normal", _xlfn.XLOOKUP(BD_Receitas[[#This Row],[ID]],TabCondicoesComerciais[ID],TabCondicoesComerciais[Tarifa 2º Giro],0),0) -> 0 | T13: =IFERROR(IF(BD_Receitas[[#This Row],[TIPO DE COBRANÇA]]<>"Operação Normal","",BD_Receitas[[#This Row],[Valor Total R$]]/ MAX(BD_Receitas[[#This Row],[Vol. Movimentado M³]], BD_Receitas[[#This Row],[Volume Mínimo ]]) ),0) | U13: =IFERROR(IF(BD_Receitas[[#This Row],[TIPO DE COBRANÇA]]<>"Operação Normal","", SUMIFS(BD_Receitas[Valor Total R$],BD_Receitas[CONGENERE],BD_Receitas[[#This Row],[CONGENERE]],BD_Receitas[FILIAL],BD_Receitas[[#This Row],[FILIAL]],BD_Receitas[DATA CONTABIL],BD_Receitas[[#This Row],[DATA CONTABIL]]) /BD_Receitas[[#This Row],[Vol. Movimentado M³]] ),0) | V13: =IF(BD_Receitas[[#This Row],[TIPO DE COBRANÇA]]<>"Operação Normal","",(BD_Receitas[[#This Row],[Volume 1º Giro]]*BD_Receitas[[#This Row],[Tarifa 1º Giro]])+(BD_Receitas[[#This Row],[Volume Mínimo ]]-BD_Receitas[[#This Row],[Volume 1º Giro]])*BD_Receitas[[#This Row],[Tarifa 2º Giro]]) | W13: =IF(BD_Receitas[[#This Row],[TIPO DE COBRANÇA]]<>"OPERAÇÃO NORMAL","", IF(BD_Receitas[[#This Row],[Vol. Movimentado M³]]<BD_Receitas[[#This Row],[Volume 1º Giro]],BD_Receitas[[#This Row],[Vol. Movimentado M³]]* BD_Receitas[[#This Row],[Tarifa 1º Giro]], (BD_Receitas[[#This Row],[Volume 1º Giro]]*BD_Receitas[[#This Row],[Tarifa 1º Giro]])+(BD_Receitas[[#This Row],[Vol. Movimentado M³]]-BD_Receitas[[#This Row],[Volume 1º Giro]])*BD_Receitas[[#This Row],[Tarifa 2º Giro]]) ) | X13: =IF(BD_Receitas[[#This Row],[TIPO DE COBRANÇA]] <> "OPERAÇÃO NORMAL","", IF(BD_Receitas[[#This Row],[Vol. Movimentado M³]]= BD_Receitas[[#This Row],[Volume Mínimo ]], "Vol. Movimentado igual ao Vol. Mínimo", IF(ROUND(BD_Receitas[[#This Row],[Tarifa 1º Giro]],3) <> ROUND(BD_Receitas[[#This Row],[Tarifa Cobrada]],3), "Conferir tarifa cobrada", IF(BD_Receitas[[#This Row],[Volume Mínimo ]]=0,"Ok", IF(BD_Receitas[[#This Row],[Vol. Movimentado M³]]<= BD_Receitas[[#This Row],[Volume Mínimo ]], IF(ROUND(BD_Receitas[[#This Row],[Valor Total R$]],2) = ROUND(BD_Receitas[[#This Row],[Valor Total R$]],2), "Ok","Verificar Cobrança"), IF(ROUND(BD_Receitas[[#This Row],[Valor Contrato]],2) = ROUND(BD_Receitas[[#This Row],[Valor Movimentado]],2), "OK","Verificar cobrança") )))))
A14: 1401 | B14: 45658 | C14: BRASILIA | D14: MG RJ ES | E14: MINAS CENTRAL | F14: 1 | G14: Betim | H14: Tobras | I14: Avanço Espaço | J14: 0 | K14: 0 | P14: =IF(BD_Receitas[[#This Row],[TIPO DE COBRANÇA]]="Operação Normal", _xlfn.XLOOKUP(BD_Receitas[[#This Row],[ID]],TabCondicoesComerciais[ID],TabCondicoesComerciais[Volume mínimo (m3)],0),"") | Q14: =_xlfn.XLOOKUP(BD_Receitas[[#This Row],[ID]],TabCondicoesComerciais[ID],TabCondicoesComerciais[Vol. 1ºGiro],0) -> 750 | R14: =IF(BD_Receitas[[#This Row],[TIPO DE COBRANÇA]]="Avanço Espaço", _xlfn.XLOOKUP(BD_Receitas[[#This Row],[ID]],TabCondicoesComerciais[ID],TabCondicoesComerciais[Avanço Espaço],0), IF(BD_Receitas[[#This Row],[TIPO DE COBRANÇA]]="Avanço Horário", _xlfn.XLOOKUP(BD_Receitas[[#This Row],[ID]],TabCondicoesComerciais[ID],TabCondicoesComerciais[Avanço Horário],0), IF(BD_Receitas[[#This Row],[TIPO DE COBRANÇA]]="Operação Normal", _xlfn.XLOOKUP(BD_Receitas[[#This Row],[ID]],TabCondicoesComerciais[ID],TabCondicoesComerciais[Tarifa 1º Giro],0),0))) -> 12.968 | S14: =IF(BD_Receitas[[#This Row],[TIPO DE COBRANÇA]]="Operação Normal", _xlfn.XLOOKUP(BD_Receitas[[#This Row],[ID]],TabCondicoesComerciais[ID],TabCondicoesComerciais[Tarifa 2º Giro],0),0) -> 0 | T14: =IFERROR(IF(BD_Receitas[[#This Row],[TIPO DE COBRANÇA]]<>"Operação Normal","",BD_Receitas[[#This Row],[Valor Total R$]]/ MAX(BD_Receitas[[#This Row],[Vol. Movimentado M³]], BD_Receitas[[#This Row],[Volume Mínimo ]]) ),0) | U14: =IFERROR(IF(BD_Receitas[[#This Row],[TIPO DE COBRANÇA]]<>"Operação Normal","", SUMIFS(BD_Receitas[Valor Total R$],BD_Receitas[CONGENERE],BD_Receitas[[#This Row],[CONGENERE]],BD_Receitas[FILIAL],BD_Receitas[[#This Row],[FILIAL]],BD_Receitas[DATA CONTABIL],BD_Receitas[[#This Row],[DATA CONTABIL]]) /BD_Receitas[[#This Row],[Vol. Movimentado M³]] ),0) | V14: =IF(BD_Receitas[[#This Row],[TIPO DE COBRANÇA]]<>"Operação Normal","",(BD_Receitas[[#This Row],[Volume 1º Giro]]*BD_Receitas[[#This Row],[Tarifa 1º Giro]])+(BD_Receitas[[#This Row],[Volume Mínimo ]]-BD_Receitas[[#This Row],[Volume 1º Giro]])*BD_Receitas[[#This Row],[Tarifa 2º Giro]]) | W14: =IF(BD_Receitas[[#This Row],[TIPO DE COBRANÇA]]<>"OPERAÇÃO NORMAL","", IF(BD_Receitas[[#This Row],[Vol. Movimentado M³]]<BD_Receitas[[#This Row],[Volume 1º Giro]],BD_Receitas[[#This Row],[Vol. Movimentado M³]]* BD_Receitas[[#This Row],[Tarifa 1º Giro]], (BD_Receitas[[#This Row],[Volume 1º Giro]]*BD_Receitas[[#This Row],[Tarifa 1º Giro]])+(BD_Receitas[[#This Row],[Vol. Movimentado M³]]-BD_Receitas[[#This Row],[Volume 1º Giro]])*BD_Receitas[[#This Row],[Tarifa 2º Giro]]) ) | X14: =IF(BD_Receitas[[#This Row],[TIPO DE COBRANÇA]] <> "OPERAÇÃO NORMAL","", IF(BD_Receitas[[#This Row],[Vol. Movimentado M³]]= BD_Receitas[[#This Row],[Volume Mínimo ]], "Vol. Movimentado igual ao Vol. Mínimo", IF(ROUND(BD_Receitas[[#This Row],[Tarifa 1º Giro]],3) <> ROUND(BD_Receitas[[#This Row],[Tarifa Cobrada]],3), "Conferir tarifa cobrada", IF(BD_Receitas[[#This Row],[Volume Mínimo ]]=0,"Ok", IF(BD_Receitas[[#This Row],[Vol. Movimentado M³]]<= BD_Receitas[[#This Row],[Volume Mínimo ]], IF(ROUND(BD_Receitas[[#This Row],[Valor Total R$]],2) = ROUND(BD_Receitas[[#This Row],[Valor Total R$]],2), "Ok","Verificar Cobrança"), IF(ROUND(BD_Receitas[[#This Row],[Valor Contrato]],2) = ROUND(BD_Receitas[[#This Row],[Valor Movimentado]],2), "OK","Verificar cobrança") )))))
A15: 1401 | B15: 45658 | C15: BRASILIA | D15: MG RJ ES | E15: MINAS CENTRAL | F15: 1 | G15: Betim | H15: Tobras | I15: Avanço Horário | J15: 0 | K15: 0 | P15: =IF(BD_Receitas[[#This Row],[TIPO DE COBRANÇA]]="Operação Normal", _xlfn.XLOOKUP(BD_Receitas[[#This Row],[ID]],TabCondicoesComerciais[ID],TabCondicoesComerciais[Volume mínimo (m3)],0),"") | Q15: =_xlfn.XLOOKUP(BD_Receitas[[#This Row],[ID]],TabCondicoesComerciais[ID],TabCondicoesComerciais[Vol. 1ºGiro],0) -> 750 | R15: =IF(BD_Receitas[[#This Row],[TIPO DE COBRANÇA]]="Avanço Espaço", _xlfn.XLOOKUP(BD_Receitas[[#This Row],[ID]],TabCondicoesComerciais[ID],TabCondicoesComerciais[Avanço Espaço],0), IF(BD_Receitas[[#This Row],[TIPO DE COBRANÇA]]="Avanço Horário", _xlfn.XLOOKUP(BD_Receitas[[#This Row],[ID]],TabCondicoesComerciais[ID],TabCondicoesComerciais[Avanço Horário],0), IF(BD_Receitas[[#This Row],[TIPO DE COBRANÇA]]="Operação Normal", _xlfn.XLOOKUP(BD_Receitas[[#This Row],[ID]],TabCondicoesComerciais[ID],TabCondicoesComerciais[Tarifa 1º Giro],0),0))) -> 12.968 | S15: =IF(BD_Receitas[[#This Row],[TIPO DE COBRANÇA]]="Operação Normal", _xlfn.XLOOKUP(BD_Receitas[[#This Row],[ID]],TabCondicoesComerciais[ID],TabCondicoesComerciais[Tarifa 2º Giro],0),0) -> 0 | T15: =IFERROR(IF(BD_Receitas[[#This Row],[TIPO DE COBRANÇA]]<>"Operação Normal","",BD_Receitas[[#This Row],[Valor Total R$]]/ MAX(BD_Receitas[[#This Row],[Vol. Movimentado M³]], BD_Receitas[[#This Row],[Volume Mínimo ]]) ),0) | U15: =IFERROR(IF(BD_Receitas[[#This Row],[TIPO DE COBRANÇA]]<>"Operação Normal","", SUMIFS(BD_Receitas[Valor Total R$],BD_Receitas[CONGENERE],BD_Receitas[[#This Row],[CONGENERE]],BD_Receitas[FILIAL],BD_Receitas[[#This Row],[FILIAL]],BD_Receitas[DATA CONTABIL],BD_Receitas[[#This Row],[DATA CONTABIL]]) /BD_Receitas[[#This Row],[Vol. Movimentado M³]] ),0) | V15: =IF(BD_Receitas[[#This Row],[TIPO DE COBRANÇA]]<>"Operação Normal","",(BD_Receitas[[#This Row],[Volume 1º Giro]]*BD_Receitas[[#This Row],[Tarifa 1º Giro]])+(BD_Receitas[[#This Row],[Volume Mínimo ]]-BD_Receitas[[#This Row],[Volume 1º Giro]])*BD_Receitas[[#This Row],[Tarifa 2º Giro]]) | W15: =IF(BD_Receitas[[#This Row],[TIPO DE COBRANÇA]]<>"OPERAÇÃO NORMAL","", IF(BD_Receitas[[#This Row],[Vol. Movimentado M³]]<BD_Receitas[[#This Row],[Volume 1º Giro]],BD_Receitas[[#This Row],[Vol. Movimentado M³]]* BD_Receitas[[#This Row],[Tarifa 1º Giro]], (BD_Receitas[[#This Row],[Volume 1º Giro]]*BD_Receitas[[#This Row],[Tarifa 1º Giro]])+(BD_Receitas[[#This Row],[Vol. Movimentado M³]]-BD_Receitas[[#This Row],[Volume 1º Giro]])*BD_Receitas[[#This Row],[Tarifa 2º Giro]]) ) | X15: =IF(BD_Receitas[[#This Row],[TIPO DE COBRANÇA]] <> "OPERAÇÃO NORMAL","", IF(BD_Receitas[[#This Row],[Vol. Movimentado M³]]= BD_Receitas[[#This Row],[Volume Mínimo ]], "Vol. Movimentado igual ao Vol. Mínimo", IF(ROUND(BD_Receitas[[#This Row],[Tarifa 1º Giro]],3) <> ROUND(BD_Receitas[[#This Row],[Tarifa Cobrada]],3), "Conferir tarifa cobrada", IF(BD_Receitas[[#This Row],[Volume Mínimo ]]=0,"Ok", IF(BD_Receitas[[#This Row],[Vol. Movimentado M³]]<= BD_Receitas[[#This Row],[Volume Mínimo ]], IF(ROUND(BD_Receitas[[#This Row],[Valor Total R$]],2) = ROUND(BD_Receitas[[#This Row],[Valor Total R$]],2), "Ok","Verificar Cobrança"), IF(ROUND(BD_Receitas[[#This Row],[Valor Contrato]],2) = ROUND(BD_Receitas[[#This Row],[Valor Movimentado]],2), "OK","Verificar cobrança") )))))
A16: 1401 | B16: 45658 | C16: BRASILIA | D16: MG RJ ES | E16: MINAS CENTRAL | F16: 1 | G16: Betim | H16: Tobras | I16: Operação Normal | J16: 226720.95 | K16: 6500 | L16: 219054.05 | M16: 4263.215 | N16: 17618 | O16: COBRANÇA DE ARMAZENAGEM CONJUNTA REFERENTE A DEZ/2024 | P16: =IF(BD_Receitas[[#This Row],[TIPO DE COBRANÇA]]="Operação Normal", _xlfn.XLOOKUP(BD_Receitas[[#This Row],[ID]],TabCondicoesComerciais[ID],TabCondicoesComerciais[Volume mínimo (m3)],0),"") -> 6500 | Q16: =_xlfn.XLOOKUP(BD_Receitas[[#This Row],[ID]],TabCondicoesComerciais[ID],TabCondicoesComerciais[Vol. 1ºGiro],0) -> 750 | R16: =IF(BD_Receitas[[#This Row],[TIPO DE COBRANÇA]]="Avanço Espaço", _xlfn.XLOOKUP(BD_Receitas[[#This Row],[ID]],TabCondicoesComerciais[ID],TabCondicoesComerciais[Avanço Espaço],0), IF(BD_Receitas[[#This Row],[TIPO DE COBRANÇA]]="Avanço Horário", _xlfn.XLOOKUP(BD_Receitas[[#This Row],[ID]],TabCondicoesComerciais[ID],TabCondicoesComerciais[Avanço Horário],0), IF(BD_Receitas[[#This Row],[TIPO DE COBRANÇA]]="Operação Normal", _xlfn.XLOOKUP(BD_Receitas[[#This Row],[ID]],TabCondicoesComerciais[ID],TabCondicoesComerciais[Tarifa 1º Giro],0),0))) -> 32.42 | S16: =IF(BD_Receitas[[#This Row],[TIPO DE COBRANÇA]]="Operação Normal", _xlfn.XLOOKUP(BD_Receitas[[#This Row],[ID]],TabCondicoesComerciais[ID],TabCondicoesComerciais[Tarifa 2º Giro],0),0) -> 32.42 | T16: =IFERROR(IF(BD_Receitas[[#This Row],[TIPO DE COBRANÇA]]<>"Operação Normal","",BD_Receitas[[#This Row],[Valor Total R$]]/ MAX(BD_Receitas[[#This Row],[Vol. Movimentado M³]], BD_Receitas[[#This Row],[Volume Mínimo ]]) ),0) -> 33.700623 | U16: =IFERROR(IF(BD_Receitas[[#This Row],[TIPO DE COBRANÇA]]<>"Operação Normal","", SUMIFS(BD_Receitas[Valor Total R$],BD_Receitas[CONGENERE],BD_Receitas[[#This Row],[CONGENERE]],BD_Receitas[FILIAL],BD_Receitas[[#This Row],[FILIAL]],BD_Receitas[DATA CONTABIL],BD_Receitas[[#This Row],[DATA CONTABIL]]) /BD_Receitas[[#This Row],[Vol. Movimentado M³]] ),0) -> 51.38236 | V16: =IF(BD_Receitas[[#This Row],[TIPO DE COBRANÇA]]<>"Operação Normal","",(BD_Receitas[[#This Row],[Volume 1º Giro]]*BD_Receitas[[#This Row],[Tarifa 1º Giro]])+(BD_Receitas[[#This Row],[Volume Mínimo ]]-BD_Receitas[[#This Row],[Volume 1º Giro]])*BD_Receitas[[#This Row],[Tarifa 2º Giro]]) -> 210730 | W16: =IF(BD_Receitas[[#This Row],[TIPO DE COBRANÇA]]<>"OPERAÇÃO NORMAL","", IF(BD_Receitas[[#This Row],[Vol. Movimentado M³]]<BD_Receitas[[#This Row],[Volume 1º Giro]],BD_Receitas[[#This Row],[Vol. Movimentado M³]]* BD_Receitas[[#This Row],[Tarifa 1º Giro]], (BD_Receitas[[#This Row],[Volume 1º Giro]]*BD_Receitas[[#This Row],[Tarifa 1º Giro]])+(BD_Receitas[[#This Row],[Vol. Movimentado M³]]-BD_Receitas[[#This Row],[Volume 1º Giro]])*BD_Receitas[[#This Row],[Tarifa 2º Giro]]) ) -> 138213.43 | X16: =IF(BD_Receitas[[#This Row],[TIPO DE COBRANÇA]] <> "OPERAÇÃO NORMAL","", IF(BD_Receitas[[#This Row],[Vol. Movimentado M³]]= BD_Receitas[[#This Row],[Volume Mínimo ]], "Vol. Movimentado igual ao Vol. Mínimo", IF(ROUND(BD_Receitas[[#This Row],[Tarifa 1º Giro]],3) <> ROUND(BD_Receitas[[#This Row],[Tarifa Cobrada]],3), "Conferir tarifa cobrada", IF(BD_Receitas[[#This Row],[Volume Mínimo ]]=0,"Ok", IF(BD_Receitas[[#This Row],[Vol. Movimentado M³]]<= BD_Receitas[[#This Row],[Volume Mínimo ]], IF(ROUND(BD_Receitas[[#This Row],[Valor Total R$]],2) = ROUND(BD_Receitas[[#This Row],[Valor Total R$]],2), "Ok","Verificar Cobrança"), IF(ROUND(BD_Receitas[[#This Row],[Valor Contrato]],2) = ROUND(BD_Receitas[[#This Row],[Valor Movimentado]],2), "OK","Verificar cobrança") ))))) -> Conferir tarifa cobrada
A17: 1401 | B17: 45658 | C17: BRASILIA | D17: MG RJ ES | E17: MINAS CENTRAL | F17: 1 | G17: Betim | H17: Tobras | I17: Outras Receitas | J17: 0 | K17: 0 | P17: =IF(BD_Receitas[[#This Row],[TIPO DE COBRANÇA]]="Operação Normal", _xlfn.XLOOKUP(BD_Receitas[[#This Row],[ID]],TabCondicoesComerciais[ID],TabCondicoesComerciais[Volume mínimo (m3)],0),"") | Q17: =_xlfn.XLOOKUP(BD_Receitas[[#This Row],[ID]],TabCondicoesComerciais[ID],TabCondicoesComerciais[Vol. 1ºGiro],0) -> 750 | R17: =IF(BD_Receitas[[#This Row],[TIPO DE COBRANÇA]]="Avanço Espaço", _xlfn.XLOOKUP(BD_Receitas[[#This Row],[ID]],TabCondicoesComerciais[ID],TabCondicoesComerciais[Avanço Espaço],0), IF(BD_Receitas[[#This Row],[TIPO DE COBRANÇA]]="Avanço Horário", _xlfn.XLOOKUP(BD_Receitas[[#This Row],[ID]],TabCondicoesComerciais[ID],TabCondicoesComerciais[Avanço Horário],0), IF(BD_Receitas[[#This Row],[TIPO DE COBRANÇA]]="Operação Normal", _xlfn.XLOOKUP(BD_Receitas[[#This Row],[ID]],TabCondicoesComerciais[ID],TabCondicoesComerciais[Tarifa 1º Giro],0),0))) -> 0 | S17: =IF(BD_Receitas[[#This Row],[TIPO DE COBRANÇA]]="Operação Normal", _xlfn.XLOOKUP(BD_Receitas[[#This Row],[ID]],TabCondicoesComerciais[ID],TabCondicoesComerciais[Tarifa 2º Giro],0),0) -> 0 | T17: =IFERROR(IF(BD_Receitas[[#This Row],[TIPO DE COBRANÇA]]<>"Operação Normal","",BD_Receitas[[#This Row],[Valor Total R$]]/ MAX(BD_Receitas[[#This Row],[Vol. Movimentado M³]], BD_Receitas[[#This Row],[Volume Mínimo ]]) ),0) | U17: =IFERROR(IF(BD_Receitas[[#This Row],[TIPO DE COBRANÇA]]<>"Operação Normal","", SUMIFS(BD_Receitas[Valor Total R$],BD_Receitas[CONGENERE],BD_Receitas[[#This Row],[CONGENERE]],BD_Receitas[FILIAL],BD_Receitas[[#This Row],[FILIAL]],BD_Receitas[DATA CONTABIL],BD_Receitas[[#This Row],[DATA CONTABIL]]) /BD_Receitas[[#This Row],[Vol. Movimentado M³]] ),0) | V17: =IF(BD_Receitas[[#This Row],[TIPO DE COBRANÇA]]<>"Operação Normal","",(BD_Receitas[[#This Row],[Volume 1º Giro]]*BD_Receitas[[#This Row],[Tarifa 1º Giro]])+(BD_Receitas[[#This Row],[Volume Mínimo ]]-BD_Receitas[[#This Row],[Volume 1º Giro]])*BD_Receitas[[#This Row],[Tarifa 2º Giro]]) | W17: =IF(BD_Receitas[[#This Row],[TIPO DE COBRANÇA]]<>"OPERAÇÃO NORMAL","", IF(BD_Receitas[[#This Row],[Vol. Movimentado M³]]<BD_Receitas[[#This Row],[Volume 1º Giro]],BD_Receitas[[#This Row],[Vol. Movimentado M³]]* BD_Receitas[[#This Row],[Tarifa 1º Giro]], (BD_Receitas[[#This Row],[Volume 1º Giro]]*BD_Receitas[[#This Row],[Tarifa 1º Giro]])+(BD_Receitas[[#This Row],[Vol. Movimentado M³]]-BD_Receitas[[#This Row],[Volume 1º Giro]])*BD_Receitas[[#This Row],[Tarifa 2º Giro]]) ) | X17: =IF(BD_Receitas[[#This Row],[TIPO DE COBRANÇA]] <> "OPERAÇÃO NORMAL","", IF(BD_Receitas[[#This Row],[Vol. Movimentado M³]]= BD_Receitas[[#This Row],[Volume Mínimo ]], "Vol. Movimentado igual ao Vol. Mínimo", IF(ROUND(BD_Receitas[[#This Row],[Tarifa 1º Giro]],3) <> ROUND(BD_Receitas[[#This Row],[Tarifa Cobrada]],3), "Conferir tarifa cobrada", IF(BD_Receitas[[#This Row],[Volume Mínimo ]]=0,"Ok", IF(BD_Receitas[[#This Row],[Vol. Movimentado M³]]<= BD_Receitas[[#This Row],[Volume Mínimo ]], IF(ROUND(BD_Receitas[[#This Row],[Valor Total R$]],2) = ROUND(BD_Receitas[[#This Row],[Valor Total R$]],2), "Ok","Verificar Cobrança"), IF(ROUND(BD_Receitas[[#This Row],[Valor Contrato]],2) = ROUND(BD_Receitas[[#This Row],[Valor Movimentado]],2), "OK","Verificar cobrança") )))))
A18: 115 | B18: 45658 | C18: BRASILIA | D18: MG RJ ES | E18: RJ e ES | F18: 11 | G18: Duque de Caxias | H18: Rede Sol | I18: Avanço Espaço | J18: 0 | K18: 0 | P18: =IF(BD_Receitas[[#This Row],[TIPO DE COBRANÇA]]="Operação Normal", _xlfn.XLOOKUP(BD_Receitas[[#This Row],[ID]],TabCondicoesComerciais[ID],TabCondicoesComerciais[Volume mínimo (m3)],0),"") | Q18: =_xlfn.XLOOKUP(BD_Receitas[[#This Row],[ID]],TabCondicoesComerciais[ID],TabCondicoesComerciais[Vol. 1ºGiro],0) -> 580 | R18: =IF(BD_Receitas[[#This Row],[TIPO DE COBRANÇA]]="Avanço Espaço", _xlfn.XLOOKUP(BD_Receitas[[#This Row],[ID]],TabCondicoesComerciais[ID],TabCondicoesComerciais[Avanço Espaço],0), IF(BD_Receitas[[#This Row],[TIPO DE COBRANÇA]]="Avanço Horário", _xlfn.XLOOKUP(BD_Receitas[[#This Row],[ID]],TabCondicoesComerciais[ID],TabCondicoesComerciais[Avanço Horário],0), IF(BD_Receitas[[#This Row],[TIPO DE COBRANÇA]]="Operação Normal", _xlfn.XLOOKUP(BD_Receitas[[#This Row],[ID]],TabCondicoesComerciais[ID],TabCondicoesComerciais[Tarifa 1º Giro],0),0))) -> 0 | S18: =IF(BD_Receitas[[#This Row],[TIPO DE COBRANÇA]]="Operação Normal", _xlfn.XLOOKUP(BD_Receitas[[#This Row],[ID]],TabCondicoesComerciais[ID],TabCondicoesComerciais[Tarifa 2º Giro],0),0) -> 0 | T18: =IFERROR(IF(BD_Receitas[[#This Row],[TIPO DE COBRANÇA]]<>"Operação Normal","",BD_Receitas[[#This Row],[Valor Total R$]]/ MAX(BD_Receitas[[#This Row],[Vol. Movimentado M³]], BD_Receitas[[#This Row],[Volume Mínimo ]]) ),0) | U18: =IFERROR(IF(BD_Receitas[[#This Row],[TIPO DE COBRANÇA]]<>"Operação Normal","", SUMIFS(BD_Receitas[Valor Total R$],BD_Receitas[CONGENERE],BD_Receitas[[#This Row],[CONGENERE]],BD_Receitas[FILIAL],BD_Receitas[[#This Row],[FILIAL]],BD_Receitas[DATA CONTABIL],BD_Receitas[[#This Row],[DATA CONTABIL]]) /BD_Receitas[[#This Row],[Vol. Movimentado M³]] ),0) | V18: =IF(BD_Receitas[[#This Row],[TIPO DE COBRANÇA]]<>"Operação Normal","",(BD_Receitas[[#This Row],[Volume 1º Giro]]*BD_Receitas[[#This Row],[Tarifa 1º Giro]])+(BD_Receitas[[#This Row],[Volume Mínimo ]]-BD_Receitas[[#This Row],[Volume 1º Giro]])*BD_Receitas[[#This Row],[Tarifa 2º Giro]]) | W18: =IF(BD_Receitas[[#This Row],[TIPO DE COBRANÇA]]<>"OPERAÇÃO NORMAL","", IF(BD_Receitas[[#This Row],[Vol. Movimentado M³]]<BD_Receitas[[#This Row],[Volume 1º Giro]],BD_Receitas[[#This Row],[Vol. Movimentado M³]]* BD_Receitas[[#This Row],[Tarifa 1º Giro]], (BD_Receitas[[#This Row],[Volume 1º Giro]]*BD_Receitas[[#This Row],[Tarifa 1º Giro]])+(BD_Receitas[[#This Row],[Vol. Movimentado M³]]-BD_Receitas[[#This Row],[Volume 1º Giro]])*BD_Receitas[[#This Row],[Tarifa 2º Giro]]) ) | X18: =IF(BD_Receitas[[#This Row],[TIPO DE COBRANÇA]] <> "OPERAÇÃO NORMAL","", IF(BD_Receitas[[#This Row],[Vol. Movimentado M³]]= BD_Receitas[[#This Row],[Volume Mínimo ]], "Vol. Movimentado igual ao Vol. Mínimo", IF(ROUND(BD_Receitas[[#This Row],[Tarifa 1º Giro]],3) <> ROUND(BD_Receitas[[#This Row],[Tarifa Cobrada]],3), "Conferir tarifa cobrada", IF(BD_Receitas[[#This Row],[Volume Mínimo ]]=0,"Ok", IF(BD_Receitas[[#This Row],[Vol. Movimentado M³]]<= BD_Receitas[[#This Row],[Volume Mínimo ]], IF(ROUND(BD_Receitas[[#This Row],[Valor Total R$]],2) = ROUND(BD_Receitas[[#This Row],[Valor Total R$]],2), "Ok","Verificar Cobrança"), IF(ROUND(BD_Receitas[[#This Row],[Valor Contrato]],2) = ROUND(BD_Receitas[[#This Row],[Valor Movimentado]],2), "OK","Verificar cobrança") )))))
A19: 115 | B19: 45658 | C19: BRASILIA | D19: MG RJ ES | E19: RJ e ES | F19: 11 | G19: Duque de Caxias | H19: Rede Sol | I19: Avanço Horário | J19: 0 | K19: 0 | P19: =IF(BD_Receitas[[#This Row],[TIPO DE COBRANÇA]]="Operação Normal", _xlfn.XLOOKUP(BD_Receitas[[#This Row],[ID]],TabCondicoesComerciais[ID],TabCondicoesComerciais[Volume mínimo (m3)],0),"") | Q19: =_xlfn.XLOOKUP(BD_Receitas[[#This Row],[ID]],TabCondicoesComerciais[ID],TabCondicoesComerciais[Vol. 1ºGiro],0) -> 580 | R19: =IF(BD_Receitas[[#This Row],[TIPO DE COBRANÇA]]="Avanço Espaço", _xlfn.XLOOKUP(BD_Receitas[[#This Row],[ID]],TabCondicoesComerciais[ID],TabCondicoesComerciais[Avanço Espaço],0), IF(BD_Receitas[[#This Row],[TIPO DE COBRANÇA]]="Avanço Horário", _xlfn.XLOOKUP(BD_Receitas[[#This Row],[ID]],TabCondicoesComerciais[ID],TabCondicoesComerciais[Avanço Horário],0), IF(BD_Receitas[[#This Row],[TIPO DE COBRANÇA]]="Operação Normal", _xlfn.XLOOKUP(BD_Receitas[[#This Row],[ID]],TabCondicoesComerciais[ID],TabCondicoesComerciais[Tarifa 1º Giro],0),0))) -> 0 | S19: =IF(BD_Receitas[[#This Row],[TIPO DE COBRANÇA]]="Operação Normal", _xlfn.XLOOKUP(BD_Receitas[[#This Row],[ID]],TabCondicoesComerciais[ID],TabCondicoesComerciais[Tarifa 2º Giro],0),0) -> 0 | T19: =IFERROR(IF(BD_Receitas[[#This Row],[TIPO DE COBRANÇA]]<>"Operação Normal","",BD_Receitas[[#This Row],[Valor Total R$]]/ MAX(BD_Receitas[[#This Row],[Vol. Movimentado M³]], BD_Receitas[[#This Row],[Volume Mínimo ]]) ),0) | U19: =IFERROR(IF(BD_Receitas[[#This Row],[TIPO DE COBRANÇA]]<>"Operação Normal","", SUMIFS(BD_Receitas[Valor Total R$],BD_Receitas[CONGENERE],BD_Receitas[[#This Row],[CONGENERE]],BD_Receitas[FILIAL],BD_Receitas[[#This Row],[FILIAL]],BD_Receitas[DATA CONTABIL],BD_Receitas[[#This Row],[DATA CONTABIL]]) /BD_Receitas[[#This Row],[Vol. Movimentado M³]] ),0) | V19: =IF(BD_Receitas[[#This Row],[TIPO DE COBRANÇA]]<>"Operação Normal","",(BD_Receitas[[#This Row],[Volume 1º Giro]]*BD_Receitas[[#This Row],[Tarifa 1º Giro]])+(BD_Receitas[[#This Row],[Volume Mínimo ]]-BD_Receitas[[#This Row],[Volume 1º Giro]])*BD_Receitas[[#This Row],[Tarifa 2º Giro]]) | W19: =IF(BD_Receitas[[#This Row],[TIPO DE COBRANÇA]]<>"OPERAÇÃO NORMAL","", IF(BD_Receitas[[#This Row],[Vol. Movimentado M³]]<BD_Receitas[[#This Row],[Volume 1º Giro]],BD_Receitas[[#This Row],[Vol. Movimentado M³]]* BD_Receitas[[#This Row],[Tarifa 1º Giro]], (BD_Receitas[[#This Row],[Volume 1º Giro]]*BD_Receitas[[#This Row],[Tarifa 1º Giro]])+(BD_Receitas[[#This Row],[Vol. Movimentado M³]]-BD_Receitas[[#This Row],[Volume 1º Giro]])*BD_Receitas[[#This Row],[Tarifa 2º Giro]]) ) | X19: =IF(BD_Receitas[[#This Row],[TIPO DE COBRANÇA]] <> "OPERAÇÃO NORMAL","", IF(BD_Receitas[[#This Row],[Vol. Movimentado M³]]= BD_Receitas[[#This Row],[Volume Mínimo ]], "Vol. Movimentado igual ao Vol. Mínimo", IF(ROUND(BD_Receitas[[#This Row],[Tarifa 1º Giro]],3) <> ROUND(BD_Receitas[[#This Row],[Tarifa Cobrada]],3), "Conferir tarifa cobrada", IF(BD_Receitas[[#This Row],[Volume Mínimo ]]=0,"Ok", IF(BD_Receitas[[#This Row],[Vol. Movimentado M³]]<= BD_Receitas[[#This Row],[Volume Mínimo ]], IF(ROUND(BD_Receitas[[#This Row],[Valor Total R$]],2) = ROUND(BD_Receitas[[#This Row],[Valor Total R$]],2), "Ok","Verificar Cobrança"), IF(ROUND(BD_Receitas[[#This Row],[Valor Contrato]],2) = ROUND(BD_Receitas[[#This Row],[Valor Movimentado]],2), "OK","Verificar cobrança") )))))
A20: 115 | B20: 45658 | C20: BRASILIA | D20: MG RJ ES | E20: RJ e ES | F20: 11 | G20: Duque de Caxias | H20: Rede Sol | I20: Operação Normal | J20: 56842.105 | K20: 2000 | P20: =IF(BD_Receitas[[#This Row],[TIPO DE COBRANÇA]]="Operação Normal", _xlfn.XLOOKUP(BD_Receitas[[#This Row],[ID]],TabCondicoesComerciais[ID],TabCondicoesComerciais[Volume mínimo (m3)],0),"") -> 2000 | Q20: =_xlfn.XLOOKUP(BD_Receitas[[#This Row],[ID]],TabCondicoesComerciais[ID],TabCondicoesComerciais[Vol. 1ºGiro],0) -> 580 | R20: =IF(BD_Receitas[[#This Row],[TIPO DE COBRANÇA]]="Avanço Espaço", _xlfn.XLOOKUP(BD_Receitas[[#This Row],[ID]],TabCondicoesComerciais[ID],TabCondicoesComerciais[Avanço Espaço],0), IF(BD_Receitas[[#This Row],[TIPO DE COBRANÇA]]="Avanço Horário", _xlfn.XLOOKUP(BD_Receitas[[#This Row],[ID]],TabCondicoesComerciais[ID],TabCondicoesComerciais[Avanço Horário],0), IF(BD_Receitas[[#This Row],[TIPO DE COBRANÇA]]="Operação Normal", _xlfn.XLOOKUP(BD_Receitas[[#This Row],[ID]],TabCondicoesComerciais[ID],TabCondicoesComerciais[Tarifa 1º Giro],0),0))) -> 27 | S20: =IF(BD_Receitas[[#This Row],[TIPO DE COBRANÇA]]="Operação Normal", _xlfn.XLOOKUP(BD_Receitas[[#This Row],[ID]],TabCondicoesComerciais[ID],TabCondicoesComerciais[Tarifa 2º Giro],0),0) -> 27 | T20: =IFERROR(IF(BD_Receitas[[#This Row],[TIPO DE COBRANÇA]]<>"Operação Normal","",BD_Receitas[[#This Row],[Valor Total R$]]/ MAX(BD_Receitas[[#This Row],[Vol. Movimentado M³]], BD_Receitas[[#This Row],[Volume Mínimo ]]) ),0) -> 0 | U20: =IFERROR(IF(BD_Receitas[[#This Row],[TIPO DE COBRANÇA]]<>"Operação Normal","", SUMIFS(BD_Receitas[Valor Total R$],BD_Receitas[CONGENERE],BD_Receitas[[#This Row],[CONGENERE]],BD_Receitas[FILIAL],BD_Receitas[[#This Row],[FILIAL]],BD_Receitas[DATA CONTABIL],BD_Receitas[[#This Row],[DATA CONTABIL]]) /BD_Receitas[[#This Row],[Vol. Movimentado M³]] ),0) -> 0 | V20: =IF(BD_Receitas[[#This Row],[TIPO DE COBRANÇA]]<>"Operação Normal","",(BD_Receitas[[#This Row],[Volume 1º Giro]]*BD_Receitas[[#This Row],[Tarifa 1º Giro]])+(BD_Receitas[[#This Row],[Volume Mínimo ]]-BD_Receitas[[#This Row],[Volume 1º Giro]])*BD_Receitas[[#This Row],[Tarifa 2º Giro]]) -> 54000 | W20: =IF(BD_Receitas[[#This Row],[TIPO DE COBRANÇA]]<>"OPERAÇÃO NORMAL","", IF(BD_Receitas[[#This Row],[Vol. Movimentado M³]]<BD_Receitas[[#This Row],[Volume 1º Giro]],BD_Receitas[[#This Row],[Vol. Movimentado M³]]* BD_Receitas[[#This Row],[Tarifa 1º Giro]], (BD_Receitas[[#This Row],[Volume 1º Giro]]*BD_Receitas[[#This Row],[Tarifa 1º Giro]])+(BD_Receitas[[#This Row],[Vol. Movimentado M³]]-BD_Receitas[[#This Row],[Volume 1º Giro]])*BD_Receitas[[#This Row],[Tarifa 2º Giro]]) ) -> 0 | X20: =IF(BD_Receitas[[#This Row],[TIPO DE COBRANÇA]] <> "OPERAÇÃO NORMAL","", IF(BD_Receitas[[#This Row],[Vol. Movimentado M³]]= BD_Receitas[[#This Row],[Volume Mínimo ]], "Vol. Movimentado igual ao Vol. Mínimo", IF(ROUND(BD_Receitas[[#This Row],[Tarifa 1º Giro]],3) <> ROUND(BD_Receitas[[#This Row],[Tarifa Cobrada]],3), "Conferir tarifa cobrada", IF(BD_Receitas[[#This Row],[Volume Mínimo ]]=0,"Ok", IF(BD_Receitas[[#This Row],[Vol. Movimentado M³]]<= BD_Receitas[[#This Row],[Volume Mínimo ]], IF(ROUND(BD_Receitas[[#This Row],[Valor Total R$]],2) = ROUND(BD_Receitas[[#This Row],[Valor Total R$]],2), "Ok","Verificar Cobrança"), IF(ROUND(BD_Receitas[[#This Row],[Valor Contrato]],2) = ROUND(BD_Receitas[[#This Row],[Valor Movimentado]],2), "OK","Verificar cobrança") ))))) -> Conferir tarifa cobrada
A21: 115 | B21: 45658 | C21: BRASILIA | D21: MG RJ ES | E21: RJ e ES | F21: 11 | G21: Duque de Caxias | H21: Rede Sol | I21: Outras Receitas | J21: 0 | K21: 0 | P21: =IF(BD_Receitas[[#This Row],[TIPO DE COBRANÇA]]="Operação Normal", _xlfn.XLOOKUP(BD_Receitas[[#This Row],[ID]],TabCondicoesComerciais[ID],TabCondicoesComerciais[Volume mínimo (m3)],0),"") | Q21: =_xlfn.XLOOKUP(BD_Receitas[[#This Row],[ID]],TabCondicoesComerciais[ID],TabCondicoesComerciais[Vol. 1ºGiro],0) -> 580 | R21: =IF(BD_Receitas[[#This Row],[TIPO DE COBRANÇA]]="Avanço Espaço", _xlfn.XLOOKUP(BD_Receitas[[#This Row],[ID]],TabCondicoesComerciais[ID],TabCondicoesComerciais[Avanço Espaço],0), IF(BD_Receitas[[#This Row],[TIPO DE COBRANÇA]]="Avanço Horário", _xlfn.XLOOKUP(BD_Receitas[[#This Row],[ID]],TabCondicoesComerciais[ID],TabCondicoesComerciais[Avanço Horário],0), IF(BD_Receitas[[#This Row],[TIPO DE COBRANÇA]]="Operação Normal", _xlfn.XLOOKUP(BD_Receitas[[#This Row],[ID]],TabCondicoesComerciais[ID],TabCondicoesComerciais[Tarifa 1º Giro],0),0))) -> 0 | S21: =IF(BD_Receitas[[#This Row],[TIPO DE COBRANÇA]]="Operação Normal", _xlfn.XLOOKUP(BD_Receitas[[#This Row],[ID]],TabCondicoesComerciais[ID],TabCondicoesComerciais[Tarifa 2º Giro],0),0) -> 0 | T21: =IFERROR(IF(BD_Receitas[[#This Row],[TIPO DE COBRANÇA]]<>"Operação Normal","",BD_Receitas[[#This Row],[Valor Total R$]]/ MAX(BD_Receitas[[#This Row],[Vol. Movimentado M³]], BD_Receitas[[#This Row],[Volume Mínimo ]]) ),0) | U21: =IFERROR(IF(BD_Receitas[[#This Row],[TIPO DE COBRANÇA]]<>"Operação Normal","", SUMIFS(BD_Receitas[Valor Total R$],BD_Receitas[CONGENERE],BD_Receitas[[#This Row],[CONGENERE]],BD_Receitas[FILIAL],BD_Receitas[[#This Row],[FILIAL]],BD_Receitas[DATA CONTABIL],BD_Receitas[[#This Row],[DATA CONTABIL]]) /BD_Receitas[[#This Row],[Vol. Movimentado M³]] ),0) | V21: =IF(BD_Receitas[[#This Row],[TIPO DE COBRANÇA]]<>"Operação Normal","",(BD_Receitas[[#This Row],[Volume 1º Giro]]*BD_Receitas[[#This Row],[Tarifa 1º Giro]])+(BD_Receitas[[#This Row],[Volume Mínimo ]]-BD_Receitas[[#This Row],[Volume 1º Giro]])*BD_Receitas[[#This Row],[Tarifa 2º Giro]]) | W21: =IF(BD_Receitas[[#This Row],[TIPO DE COBRANÇA]]<>"OPERAÇÃO NORMAL","", IF(BD_Receitas[[#This Row],[Vol. Movimentado M³]]<BD_Receitas[[#This Row],[Volume 1º Giro]],BD_Receitas[[#This Row],[Vol. Movimentado M³]]* BD_Receitas[[#This Row],[Tarifa 1º Giro]], (BD_Receitas[[#This Row],[Volume 1º Giro]]*BD_Receitas[[#This Row],[Tarifa 1º Giro]])+(BD_Receitas[[#This Row],[Vol. Movimentado M³]]-BD_Receitas[[#This Row],[Volume 1º Giro]])*BD_Receitas[[#This Row],[Tarifa 2º Giro]]) ) | X21: =IF(BD_Receitas[[#This Row],[TIPO DE COBRANÇA]] <> "OPERAÇÃO NORMAL","", IF(BD_Receitas[[#This Row],[Vol. Movimentado M³]]= BD_Receitas[[#This Row],[Volume Mínimo ]], "Vol. Movimentado igual ao Vol. Mínimo", IF(ROUND(BD_Receitas[[#This Row],[Tarifa 1º Giro]],3) <> ROUND(BD_Receitas[[#This Row],[Tarifa Cobrada]],3), "Conferir tarifa cobrada", IF(BD_Receitas[[#This Row],[Volume Mínimo ]]=0,"Ok", IF(BD_Receitas[[#This Row],[Vol. Movimentado M³]]<= BD_Receitas[[#This Row],[Volume Mínimo ]], IF(ROUND(BD_Receitas[[#This Row],[Valor Total R$]],2) = ROUND(BD_Receitas[[#This Row],[Valor Total R$]],2), "Ok","Verificar Cobrança"), IF(ROUND(BD_Receitas[[#This Row],[Valor Contrato]],2) = ROUND(BD_Receitas[[#This Row],[Valor Movimentado]],2), "OK","Verificar cobrança") )))))
A22: 11104 | B22: 45658 | C22: BRASILIA | D22: MG RJ ES | E22: RJ e ES | F22: 11 | G22: Duque de Caxias | H22: Ruff | I22: Avanço Espaço | J22: 0 | K22: 0 | P22: =IF(BD_Receitas[[#This Row],[TIPO DE COBRANÇA]]="Operação Normal", _xlfn.XLOOKUP(BD_Receitas[[#This Row],[ID]],TabCondicoesComerciais[ID],TabCondicoesComerciais[Volume mínimo (m3)],0),"") | Q22: =_xlfn.XLOOKUP(BD_Receitas[[#This Row],[ID]],TabCondicoesComerciais[ID],TabCondicoesComerciais[Vol. 1ºGiro],0) -> 750 | R22: =IF(BD_Receitas[[#This Row],[TIPO DE COBRANÇA]]="Avanço Espaço", _xlfn.XLOOKUP(BD_Receitas[[#This Row],[ID]],TabCondicoesComerciais[ID],TabCondicoesComerciais[Avanço Espaço],0), IF(BD_Receitas[[#This Row],[TIPO DE COBRANÇA]]="Avanço Horário", _xlfn.XLOOKUP(BD_Receitas[[#This Row],[ID]],TabCondicoesComerciais[ID],TabCondicoesComerciais[Avanço Horário],0), IF(BD_Receitas[[#This Row],[TIPO DE COBRANÇA]]="Operação Normal", _xlfn.XLOOKUP(BD_Receitas[[#This Row],[ID]],TabCondicoesComerciais[ID],TabCondicoesComerciais[Tarifa 1º Giro],0),0))) -> 8.88 | S22: =IF(BD_Receitas[[#This Row],[TIPO DE COBRANÇA]]="Operação Normal", _xlfn.XLOOKUP(BD_Receitas[[#This Row],[ID]],TabCondicoesComerciais[ID],TabCondicoesComerciais[Tarifa 2º Giro],0),0) -> 0 | T22: =IFERROR(IF(BD_Receitas[[#This Row],[TIPO DE COBRANÇA]]<>"Operação Normal","",BD_Receitas[[#This Row],[Valor Total R$]]/ MAX(BD_Receitas[[#This Row],[Vol. Movimentado M³]], BD_Receitas[[#This Row],[Volume Mínimo ]]) ),0) | U22: =IFERROR(IF(BD_Receitas[[#This Row],[TIPO DE COBRANÇA]]<>"Operação Normal","", SUMIFS(BD_Receitas[Valor Total R$],BD_Receitas[CONGENERE],BD_Receitas[[#This Row],[CONGENERE]],BD_Receitas[FILIAL],BD_Receitas[[#This Row],[FILIAL]],BD_Receitas[DATA CONTABIL],BD_Receitas[[#This Row],[DATA CONTABIL]]) /BD_Receitas[[#This Row],[Vol. Movimentado M³]] ),0) | V22: =IF(BD_Receitas[[#This Row],[TIPO DE COBRANÇA]]<>"Operação Normal","",(BD_Receitas[[#This Row],[Volume 1º Giro]]*BD_Receitas[[#This Row],[Tarifa 1º Giro]])+(BD_Receitas[[#This Row],[Volume Mínimo ]]-BD_Receitas[[#This Row],[Volume 1º Giro]])*BD_Receitas[[#This Row],[Tarifa 2º Giro]]) | W22: =IF(BD_Receitas[[#This Row],[TIPO DE COBRANÇA]]<>"OPERAÇÃO NORMAL","", IF(BD_Receitas[[#This Row],[Vol. Movimentado M³]]<BD_Receitas[[#This Row],[Volume 1º Giro]],BD_Receitas[[#This Row],[Vol. Movimentado M³]]* BD_Receitas[[#This Row],[Tarifa 1º Giro]], (BD_Receitas[[#This Row],[Volume 1º Giro]]*BD_Receitas[[#This Row],[Tarifa 1º Giro]])+(BD_Receitas[[#This Row],[Vol. Movimentado M³]]-BD_Receitas[[#This Row],[Volume 1º Giro]])*BD_Receitas[[#This Row],[Tarifa 2º Giro]]) ) | X22: =IF(BD_Receitas[[#This Row],[TIPO DE COBRANÇA]] <> "OPERAÇÃO NORMAL","", IF(BD_Receitas[[#This Row],[Vol. Movimentado M³]]= BD_Receitas[[#This Row],[Volume Mínimo ]], "Vol. Movimentado igual ao Vol. Mínimo", IF(ROUND(BD_Receitas[[#This Row],[Tarifa 1º Giro]],3) <> ROUND(BD_Receitas[[#This Row],[Tarifa Cobrada]],3), "Conferir tarifa cobrada", IF(BD_Receitas[[#This Row],[Volume Mínimo ]]=0,"Ok", IF(BD_Receitas[[#This Row],[Vol. Movimentado M³]]<= BD_Receitas[[#This Row],[Volume Mínimo ]], IF(ROUND(BD_Receitas[[#This Row],[Valor Total R$]],2) = ROUND(BD_Receitas[[#This Row],[Valor Total R$]],2), "Ok","Verificar Cobrança"), IF(ROUND(BD_Receitas[[#This Row],[Valor Contrato]],2) = ROUND(BD_Receitas[[#This Row],[Valor Movimentado]],2), "OK","Verificar cobrança") )))))
A23: 11104 | B23: 45658 | C23: BRASILIA | D23: MG RJ ES | E23: RJ e ES | F23: 11 | G23: Duque de Caxias | H23: Ruff | I23: Avanço Horário | J23: 0 | K23: 0 | P23: =IF(BD_Receitas[[#This Row],[TIPO DE COBRANÇA]]="Operação Normal", _xlfn.XLOOKUP(BD_Receitas[[#This Row],[ID]],TabCondicoesComerciais[ID],TabCondicoesComerciais[Volume mínimo (m3)],0),"") | Q23: =_xlfn.XLOOKUP(BD_Receitas[[#This Row],[ID]],TabCondicoesComerciais[ID],TabCondicoesComerciais[Vol. 1ºGiro],0) -> 750 | R23: =IF(BD_Receitas[[#This Row],[TIPO DE COBRANÇA]]="Avanço Espaço", _xlfn.XLOOKUP(BD_Receitas[[#This Row],[ID]],TabCondicoesComerciais[ID],TabCondicoesComerciais[Avanço Espaço],0), IF(BD_Receitas[[#This Row],[TIPO DE COBRANÇA]]="Avanço Horário", _xlfn.XLOOKUP(BD_Receitas[[#This Row],[ID]],TabCondicoesComerciais[ID],TabCondicoesComerciais[Avanço Horário],0), IF(BD_Receitas[[#This Row],[TIPO DE COBRANÇA]]="Operação Normal", _xlfn.XLOOKUP(BD_Receitas[[#This Row],[ID]],TabCondicoesComerciais[ID],TabCondicoesComerciais[Tarifa 1º Giro],0),0))) -> 8.88 | S23: =IF(BD_Receitas[[#This Row],[TIPO DE COBRANÇA]]="Operação Normal", _xlfn.XLOOKUP(BD_Receitas[[#This Row],[ID]],TabCondicoesComerciais[ID],TabCondicoesComerciais[Tarifa 2º Giro],0),0) -> 0 | T23: =IFERROR(IF(BD_Receitas[[#This Row],[TIPO DE COBRANÇA]]<>"Operação Normal","",BD_Receitas[[#This Row],[Valor Total R$]]/ MAX(BD_Receitas[[#This Row],[Vol. Movimentado M³]], BD_Receitas[[#This Row],[Volume Mínimo ]]) ),0) | U23: =IFERROR(IF(BD_Receitas[[#This Row],[TIPO DE COBRANÇA]]<>"Operação Normal","", SUMIFS(BD_Receitas[Valor Total R$],BD_Receitas[CONGENERE],BD_Receitas[[#This Row],[CONGENERE]],BD_Receitas[FILIAL],BD_Receitas[[#This Row],[FILIAL]],BD_Receitas[DATA CONTABIL],BD_Receitas[[#This Row],[DATA CONTABIL]]) /BD_Receitas[[#This Row],[Vol. Movimentado M³]] ),0) | V23: =IF(BD_Receitas[[#This Row],[TIPO DE COBRANÇA]]<>"Operação Normal","",(BD_Receitas[[#This Row],[Volume 1º Giro]]*BD_Receitas[[#This Row],[Tarifa 1º Giro]])+(BD_Receitas[[#This Row],[Volume Mínimo ]]-BD_Receitas[[#This Row],[Volume 1º Giro]])*BD_Receitas[[#This Row],[Tarifa 2º Giro]]) | W23: =IF(BD_Receitas[[#This Row],[TIPO DE COBRANÇA]]<>"OPERAÇÃO NORMAL","", IF(BD_Receitas[[#This Row],[Vol. Movimentado M³]]<BD_Receitas[[#This Row],[Volume 1º Giro]],BD_Receitas[[#This Row],[Vol. Movimentado M³]]* BD_Receitas[[#This Row],[Tarifa 1º Giro]], (BD_Receitas[[#This Row],[Volume 1º Giro]]*BD_Receitas[[#This Row],[Tarifa 1º Giro]])+(BD_Receitas[[#This Row],[Vol. Movimentado M³]]-BD_Receitas[[#This Row],[Volume 1º Giro]])*BD_Receitas[[#This Row],[Tarifa 2º Giro]]) ) | X23: =IF(BD_Receitas[[#This Row],[TIPO DE COBRANÇA]] <> "OPERAÇÃO NORMAL","", IF(BD_Receitas[[#This Row],[Vol. Movimentado M³]]= BD_Receitas[[#This Row],[Volume Mínimo ]], "Vol. Movimentado igual ao Vol. Mínimo", IF(ROUND(BD_Receitas[[#This Row],[Tarifa 1º Giro]],3) <> ROUND(BD_Receitas[[#This Row],[Tarifa Cobrada]],3), "Conferir tarifa cobrada", IF(BD_Receitas[[#This Row],[Volume Mínimo ]]=0,"Ok", IF(BD_Receitas[[#This Row],[Vol. Movimentado M³]]<= BD_Receitas[[#This Row],[Volume Mínimo ]], IF(ROUND(BD_Receitas[[#This Row],[Valor Total R$]],2) = ROUND(BD_Receitas[[#This Row],[Valor Total R$]],2), "Ok","Verificar Cobrança"), IF(ROUND(BD_Receitas[[#This Row],[Valor Contrato]],2) = ROUND(BD_Receitas[[#This Row],[Valor Movimentado]],2), "OK","Verificar cobrança") )))))
A24: 11104 | B24: 45658 | C24: BRASILIA | D24: MG RJ ES | E24: RJ e ES | F24: 11 | G24: Duque de Caxias | H24: Ruff | I24: Operação Normal | J24: 0 | K24: 0 | P24: =IF(BD_Receitas[[#This Row],[TIPO DE COBRANÇA]]="Operação Normal", _xlfn.XLOOKUP(BD_Receitas[[#This Row],[ID]],TabCondicoesComerciais[ID],TabCondicoesComerciais[Volume mínimo (m3)],0),"") -> 0 | Q24: =_xlfn.XLOOKUP(BD_Receitas[[#This Row],[ID]],TabCondicoesComerciais[ID],TabCondicoesComerciais[Vol. 1ºGiro],0) -> 750 | R24: =IF(BD_Receitas[[#This Row],[TIPO DE COBRANÇA]]="Avanço Espaço", _xlfn.XLOOKUP(BD_Receitas[[#This Row],[ID]],TabCondicoesComerciais[ID],TabCondicoesComerciais[Avanço Espaço],0), IF(BD_Receitas[[#This Row],[TIPO DE COBRANÇA]]="Avanço Horário", _xlfn.XLOOKUP(BD_Receitas[[#This Row],[ID]],TabCondicoesComerciais[ID],TabCondicoesComerciais[Avanço Horário],0), IF(BD_Receitas[[#This Row],[TIPO DE COBRANÇA]]="Operação Normal", _xlfn.XLOOKUP(BD_Receitas[[#This Row],[ID]],TabCondicoesComerciais[ID],TabCondicoesComerciais[Tarifa 1º Giro],0),0))) -> 22.2 | S24: =IF(BD_Receitas[[#This Row],[TIPO DE COBRANÇA]]="Operação Normal", _xlfn.XLOOKUP(BD_Receitas[[#This Row],[ID]],TabCondicoesComerciais[ID],TabCondicoesComerciais[Tarifa 2º Giro],0),0) -> 22.2 | T24: =IFERROR(IF(BD_Receitas[[#This Row],[TIPO DE COBRANÇA]]<>"Operação Normal","",BD_Receitas[[#This Row],[Valor Total R$]]/ MAX(BD_Receitas[[#This Row],[Vol. Movimentado M³]], BD_Receitas[[#This Row],[Volume Mínimo ]]) ),0) -> 0 | U24: =IFERROR(IF(BD_Receitas[[#This Row],[TIPO DE COBRANÇA]]<>"Operação Normal","", SUMIFS(BD_Receitas[Valor Total R$],BD_Receitas[CONGENERE],BD_Receitas[[#This Row],[CONGENERE]],BD_Receitas[FILIAL],BD_Receitas[[#This Row],[FILIAL]],BD_Receitas[DATA CONTABIL],BD_Receitas[[#This Row],[DATA CONTABIL]]) /BD_Receitas[[#This Row],[Vol. Movimentado M³]] ),0) -> 0 | V24: =IF(BD_Receitas[[#This Row],[TIPO DE COBRANÇA]]<>"Operação Normal","",(BD_Receitas[[#This Row],[Volume 1º Giro]]*BD_Receitas[[#This Row],[Tarifa 1º Giro]])+(BD_Receitas[[#This Row],[Volume Mínimo ]]-BD_Receitas[[#This Row],[Volume 1º Giro]])*BD_Receitas[[#This Row],[Tarifa 2º Giro]]) -> 0 | W24: =IF(BD_Receitas[[#This Row],[TIPO DE COBRANÇA]]<>"OPERAÇÃO NORMAL","", IF(BD_Receitas[[#This Row],[Vol. Movimentado M³]]<BD_Receitas[[#This Row],[Volume 1º Giro]],BD_Receitas[[#This Row],[Vol. Movimentado M³]]* BD_Receitas[[#This Row],[Tarifa 1º Giro]], (BD_Receitas[[#This Row],[Volume 1º Giro]]*BD_Receitas[[#This Row],[Tarifa 1º Giro]])+(BD_Receitas[[#This Row],[Vol. Movimentado M³]]-BD_Receitas[[#This Row],[Volume 1º Giro]])*BD_Receitas[[#This Row],[Tarifa 2º Giro]]) ) -> 0 | X24: =IF(BD_Receitas[[#This Row],[TIPO DE COBRANÇA]] <> "OPERAÇÃO NORMAL","", IF(BD_Receitas[[#This Row],[Vol. Movimentado M³]]= BD_Receitas[[#This Row],[Volume Mínimo ]], "Vol. Movimentado igual ao Vol. Mínimo", IF(ROUND(BD_Receitas[[#This Row],[Tarifa 1º Giro]],3) <> ROUND(BD_Receitas[[#This Row],[Tarifa Cobrada]],3), "Conferir tarifa cobrada", IF(BD_Receitas[[#This Row],[Volume Mínimo ]]=0,"Ok", IF(BD_Receitas[[#This Row],[Vol. Movimentado M³]]<= BD_Receitas[[#This Row],[Volume Mínimo ]], IF(ROUND(BD_Receitas[[#This Row],[Valor Total R$]],2) = ROUND(BD_Receitas[[#This Row],[Valor Total R$]],2), "Ok","Verificar Cobrança"), IF(ROUND(BD_Receitas[[#This Row],[Valor Contrato]],2) = ROUND(BD_Receitas[[#This Row],[Valor Movimentado]],2), "OK","Verificar cobrança") ))))) -> Vol. Movimentado igual ao Vol. Mínimo
A25: 11104 | B25: 45658 | C25: BRASILIA | D25: MG RJ ES | E25: RJ e ES | F25: 11 | G25: Duque de Caxias | H25: Ruff | I25: Outras Receitas | J25: 0 | K25: 0 | P25: =IF(BD_Receitas[[#This Row],[TIPO DE COBRANÇA]]="Operação Normal", _xlfn.XLOOKUP(BD_Receitas[[#This Row],[ID]],TabCondicoesComerciais[ID],TabCondicoesComerciais[Volume mínimo (m3)],0),"") | Q25: =_xlfn.XLOOKUP(BD_Receitas[[#This Row],[ID]],TabCondicoesComerciais[ID],TabCondicoesComerciais[Vol. 1ºGiro],0) -> 750 | R25: =IF(BD_Receitas[[#This Row],[TIPO DE COBRANÇA]]="Avanço Espaço", _xlfn.XLOOKUP(BD_Receitas[[#This Row],[ID]],TabCondicoesComerciais[ID],TabCondicoesComerciais[Avanço Espaço],0), IF(BD_Receitas[[#This Row],[TIPO DE COBRANÇA]]="Avanço Horário", _xlfn.XLOOKUP(BD_Receitas[[#This Row],[ID]],TabCondicoesComerciais[ID],TabCondicoesComerciais[Avanço Horário],0), IF(BD_Receitas[[#This Row],[TIPO DE COBRANÇA]]="Operação Normal", _xlfn.XLOOKUP(BD_Receitas[[#This Row],[ID]],TabCondicoesComerciais[ID],TabCondicoesComerciais[Tarifa 1º Giro],0),0))) -> 0 | S25: =IF(BD_Receitas[[#This Row],[TIPO DE COBRANÇA]]="Operação Normal", _xlfn.XLOOKUP(BD_Receitas[[#This Row],[ID]],TabCondicoesComerciais[ID],TabCondicoesComerciais[Tarifa 2º Giro],0),0) -> 0 | T25: =IFERROR(IF(BD_Receitas[[#This Row],[TIPO DE COBRANÇA]]<>"Operação Normal","",BD_Receitas[[#This Row],[Valor Total R$]]/ MAX(BD_Receitas[[#This Row],[Vol. Movimentado M³]], BD_Receitas[[#This Row],[Volume Mínimo ]]) ),0) | U25: =IFERROR(IF(BD_Receitas[[#This Row],[TIPO DE COBRANÇA]]<>"Operação Normal","", SUMIFS(BD_Receitas[Valor Total R$],BD_Receitas[CONGENERE],BD_Receitas[[#This Row],[CONGENERE]],BD_Receitas[FILIAL],BD_Receitas[[#This Row],[FILIAL]],BD_Receitas[DATA CONTABIL],BD_Receitas[[#This Row],[DATA CONTABIL]]) /BD_Receitas[[#This Row],[Vol. Movimentado M³]] ),0) | V25: =IF(BD_Receitas[[#This Row],[TIPO DE COBRANÇA]]<>"Operação Normal","",(BD_Receitas[[#This Row],[Volume 1º Giro]]*BD_Receitas[[#This Row],[Tarifa 1º Giro]])+(BD_Receitas[[#This Row],[Volume Mínimo ]]-BD_Receitas[[#This Row],[Volume 1º Giro]])*BD_Receitas[[#This Row],[Tarifa 2º Giro]]) | W25: =IF(BD_Receitas[[#This Row],[TIPO DE COBRANÇA]]<>"OPERAÇÃO NORMAL","", IF(BD_Receitas[[#This Row],[Vol. Movimentado M³]]<BD_Receitas[[#This Row],[Volume 1º Giro]],BD_Receitas[[#This Row],[Vol. Movimentado M³]]* BD_Receitas[[#This Row],[Tarifa 1º Giro]], (BD_Receitas[[#This Row],[Volume 1º Giro]]*BD_Receitas[[#This Row],[Tarifa 1º Giro]])+(BD_Receitas[[#This Row],[Vol. Movimentado M³]]-BD_Receitas[[#This Row],[Volume 1º Giro]])*BD_Receitas[[#This Row],[Tarifa 2º Giro]]) ) | X25: =IF(BD_Receitas[[#This Row],[TIPO DE COBRANÇA]] <> "OPERAÇÃO NORMAL","", IF(BD_Receitas[[#This Row],[Vol. Movimentado M³]]= BD_Receitas[[#This Row],[Volume Mínimo ]], "Vol. Movimentado igual ao Vol. Mínimo", IF(ROUND(BD_Receitas[[#This Row],[Tarifa 1º Giro]],3) <> ROUND(BD_Receitas[[#This Row],[Tarifa Cobrada]],3), "Conferir tarifa cobrada", IF(BD_Receitas[[#This Row],[Volume Mínimo ]]=0,"Ok", IF(BD_Receitas[[#This Row],[Vol. Movimentado M³]]<= BD_Receitas[[#This Row],[Volume Mínimo ]], IF(ROUND(BD_Receitas[[#This Row],[Valor Total R$]],2) = ROUND(BD_Receitas[[#This Row],[Valor Total R$]],2), "Ok","Verificar Cobrança"), IF(ROUND(BD_Receitas[[#This Row],[Valor Contrato]],2) = ROUND(BD_Receitas[[#This Row],[Valor Movimentado]],2), "OK","Verificar cobrança") )))))
A26: 13300 | B26: 45658 | C26: BRASILIA | D26: GOIANIA | E26: GO E TRIANGULO MINEIRO | F26: 13 | G26: Goiânia | H26: Petrobahia | I26: Avanço Espaço | J26: 0 | K26: 0 | P26: =IF(BD_Receitas[[#This Row],[TIPO DE COBRANÇA]]="Operação Normal", _xlfn.XLOOKUP(BD_Receitas[[#This Row],[ID]],TabCondicoesComerciais[ID],TabCondicoesComerciais[Volume mínimo (m3)],0),"") | Q26: =_xlfn.XLOOKUP(BD_Receitas[[#This Row],[ID]],TabCondicoesComerciais[ID],TabCondicoesComerciais[Vol. 1ºGiro],0) -> 750 | R26: =IF(BD_Receitas[[#This Row],[TIPO DE COBRANÇA]]="Avanço Espaço", _xlfn.XLOOKUP(BD_Receitas[[#This Row],[ID]],TabCondicoesComerciais[ID],TabCondicoesComerciais[Avanço Espaço],0), IF(BD_Receitas[[#This Row],[TIPO DE COBRANÇA]]="Avanço Horário", _xlfn.XLOOKUP(BD_Receitas[[#This Row],[ID]],TabCondicoesComerciais[ID],TabCondicoesComerciais[Avanço Horário],0), IF(BD_Receitas[[#This Row],[TIPO DE COBRANÇA]]="Operação Normal", _xlfn.XLOOKUP(BD_Receitas[[#This Row],[ID]],TabCondicoesComerciais[ID],TabCondicoesComerciais[Tarifa 1º Giro],0),0))) -> 9.75 | S26: =IF(BD_Receitas[[#This Row],[TIPO DE COBRANÇA]]="Operação Normal", _xlfn.XLOOKUP(BD_Receitas[[#This Row],[ID]],TabCondicoesComerciais[ID],TabCondicoesComerciais[Tarifa 2º Giro],0),0) -> 0 | T26: =IFERROR(IF(BD_Receitas[[#This Row],[TIPO DE COBRANÇA]]<>"Operação Normal","",BD_Receitas[[#This Row],[Valor Total R$]]/ MAX(BD_Receitas[[#This Row],[Vol. Movimentado M³]], BD_Receitas[[#This Row],[Volume Mínimo ]]) ),0) | U26: =IFERROR(IF(BD_Receitas[[#This Row],[TIPO DE COBRANÇA]]<>"Operação Normal","", SUMIFS(BD_Receitas[Valor Total R$],BD_Receitas[CONGENERE],BD_Receitas[[#This Row],[CONGENERE]],BD_Receitas[FILIAL],BD_Receitas[[#This Row],[FILIAL]],BD_Receitas[DATA CONTABIL],BD_Receitas[[#This Row],[DATA CONTABIL]]) /BD_Receitas[[#This Row],[Vol. Movimentado M³]] ),0) | V26: =IF(BD_Receitas[[#This Row],[TIPO DE COBRANÇA]]<>"Operação Normal","",(BD_Receitas[[#This Row],[Volume 1º Giro]]*BD_Receitas[[#This Row],[Tarifa 1º Giro]])+(BD_Receitas[[#This Row],[Volume Mínimo ]]-BD_Receitas[[#This Row],[Volume 1º Giro]])*BD_Receitas[[#This Row],[Tarifa 2º Giro]]) | W26: =IF(BD_Receitas[[#This Row],[TIPO DE COBRANÇA]]<>"OPERAÇÃO NORMAL","", IF(BD_Receitas[[#This Row],[Vol. Movimentado M³]]<BD_Receitas[[#This Row],[Volume 1º Giro]],BD_Receitas[[#This Row],[Vol. Movimentado M³]]* BD_Receitas[[#This Row],[Tarifa 1º Giro]], (BD_Receitas[[#This Row],[Volume 1º Giro]]*BD_Receitas[[#This Row],[Tarifa 1º Giro]])+(BD_Receitas[[#This Row],[Vol. Movimentado M³]]-BD_Receitas[[#This Row],[Volume 1º Giro]])*BD_Receitas[[#This Row],[Tarifa 2º Giro]]) ) | X26: =IF(BD_Receitas[[#This Row],[TIPO DE COBRANÇA]] <> "OPERAÇÃO NORMAL","", IF(BD_Receitas[[#This Row],[Vol. Movimentado M³]]= BD_Receitas[[#This Row],[Volume Mínimo ]], "Vol. Movimentado igual ao Vol. Mínimo", IF(ROUND(BD_Receitas[[#This Row],[Tarifa 1º Giro]],3) <> ROUND(BD_Receitas[[#This Row],[Tarifa Cobrada]],3), "Conferir tarifa cobrada", IF(BD_Receitas[[#This Row],[Volume Mínimo ]]=0,"Ok", IF(BD_Receitas[[#This Row],[Vol. Movimentado M³]]<= BD_Receitas[[#This Row],[Volume Mínimo ]], IF(ROUND(BD_Receitas[[#This Row],[Valor Total R$]],2) = ROUND(BD_Receitas[[#This Row],[Valor Total R$]],2), "Ok","Verificar Cobrança"), IF(ROUND(BD_Receitas[[#This Row],[Valor Contrato]],2) = ROUND(BD_Receitas[[#This Row],[Valor Movimentado]],2), "OK","Verificar cobrança") )))))
A27: 13300 | B27: 45658 | C27: BRASILIA | D27: GOIANIA | E27: GO E TRIANGULO MINEIRO | F27: 13 | G27: Goiânia | H27: Petrobahia | I27: Avanço Horário | J27: 0 | K27: 0 | P27: =IF(BD_Receitas[[#This Row],[TIPO DE COBRANÇA]]="Operação Normal", _xlfn.XLOOKUP(BD_Receitas[[#This Row],[ID]],TabCondicoesComerciais[ID],TabCondicoesComerciais[Volume mínimo (m3)],0),"") | Q27: =_xlfn.XLOOKUP(BD_Receitas[[#This Row],[ID]],TabCondicoesComerciais[ID],TabCondicoesComerciais[Vol. 1ºGiro],0) -> 750 | R27: =IF(BD_Receitas[[#This Row],[TIPO DE COBRANÇA]]="Avanço Espaço", _xlfn.XLOOKUP(BD_Receitas[[#This Row],[ID]],TabCondicoesComerciais[ID],TabCondicoesComerciais[Avanço Espaço],0), IF(BD_Receitas[[#This Row],[TIPO DE COBRANÇA]]="Avanço Horário", _xlfn.XLOOKUP(BD_Receitas[[#This Row],[ID]],TabCondicoesComerciais[ID],TabCondicoesComerciais[Avanço Horário],0), IF(BD_Receitas[[#This Row],[TIPO DE COBRANÇA]]="Operação Normal", _xlfn.XLOOKUP(BD_Receitas[[#This Row],[ID]],TabCondicoesComerciais[ID],TabCondicoesComerciais[Tarifa 1º Giro],0),0))) -> 9.75 | S27: =IF(BD_Receitas[[#This Row],[TIPO DE COBRANÇA]]="Operação Normal", _xlfn.XLOOKUP(BD_Receitas[[#This Row],[ID]],TabCondicoesComerciais[ID],TabCondicoesComerciais[Tarifa 2º Giro],0),0) -> 0 | T27: =IFERROR(IF(BD_Receitas[[#This Row],[TIPO DE COBRANÇA]]<>"Operação Normal","",BD_Receitas[[#This Row],[Valor Total R$]]/ MAX(BD_Receitas[[#This Row],[Vol. Movimentado M³]], BD_Receitas[[#This Row],[Volume Mínimo ]]) ),0) | U27: =IFERROR(IF(BD_Receitas[[#This Row],[TIPO DE COBRANÇA]]<>"Operação Normal","", SUMIFS(BD_Receitas[Valor Total R$],BD_Receitas[CONGENERE],BD_Receitas[[#This Row],[CONGENERE]],BD_Receitas[FILIAL],BD_Receitas[[#This Row],[FILIAL]],BD_Receitas[DATA CONTABIL],BD_Receitas[[#This Row],[DATA CONTABIL]]) /BD_Receitas[[#This Row],[Vol. Movimentado M³]] ),0) | V27: =IF(BD_Receitas[[#This Row],[TIPO DE COBRANÇA]]<>"Operação Normal","",(BD_Receitas[[#This Row],[Volume 1º Giro]]*BD_Receitas[[#This Row],[Tarifa 1º Giro]])+(BD_Receitas[[#This Row],[Volume Mínimo ]]-BD_Receitas[[#This Row],[Volume 1º Giro]])*BD_Receitas[[#This Row],[Tarifa 2º Giro]]) | W27: =IF(BD_Receitas[[#This Row],[TIPO DE COBRANÇA]]<>"OPERAÇÃO NORMAL","", IF(BD_Receitas[[#This Row],[Vol. Movimentado M³]]<BD_Receitas[[#This Row],[Volume 1º Giro]],BD_Receitas[[#This Row],[Vol. Movimentado M³]]* BD_Receitas[[#This Row],[Tarifa 1º Giro]], (BD_Receitas[[#This Row],[Volume 1º Giro]]*BD_Receitas[[#This Row],[Tarifa 1º Giro]])+(BD_Receitas[[#This Row],[Vol. Movimentado M³]]-BD_Receitas[[#This Row],[Volume 1º Giro]])*BD_Receitas[[#This Row],[Tarifa 2º Giro]]) ) | X27: =IF(BD_Receitas[[#This Row],[TIPO DE COBRANÇA]] <> "OPERAÇÃO NORMAL","", IF(BD_Receitas[[#This Row],[Vol. Movimentado M³]]= BD_Receitas[[#This Row],[Volume Mínimo ]], "Vol. Movimentado igual ao Vol. Mínimo", IF(ROUND(BD_Receitas[[#This Row],[Tarifa 1º Giro]],3) <> ROUND(BD_Receitas[[#This Row],[Tarifa Cobrada]],3), "Conferir tarifa cobrada", IF(BD_Receitas[[#This Row],[Volume Mínimo ]]=0,"Ok", IF(BD_Receitas[[#This Row],[Vol. Movimentado M³]]<= BD_Receitas[[#This Row],[Volume Mínimo ]], IF(ROUND(BD_Receitas[[#This Row],[Valor Total R$]],2) = ROUND(BD_Receitas[[#This Row],[Valor Total R$]],2), "Ok","Verificar Cobrança"), IF(ROUND(BD_Receitas[[#This Row],[Valor Contrato]],2) = ROUND(BD_Receitas[[#This Row],[Valor Movimentado]],2), "OK","Verificar cobrança") )))))
A28: 13300 | B28: 45658 | C28: BRASILIA | D28: GOIANIA | E28: GO E TRIANGULO MINEIRO | F28: 13 | G28: Goiânia | H28: Petrobahia | I28: Operação Normal | J28: 86210.526 | K28: 4200 | P28: =IF(BD_Receitas[[#This Row],[TIPO DE COBRANÇA]]="Operação Normal", _xlfn.XLOOKUP(BD_Receitas[[#This Row],[ID]],TabCondicoesComerciais[ID],TabCondicoesComerciais[Volume mínimo (m3)],0),"") -> 3000 | Q28: =_xlfn.XLOOKUP(BD_Receitas[[#This Row],[ID]],TabCondicoesComerciais[ID],TabCondicoesComerciais[Vol. 1ºGiro],0) -> 750 | R28: =IF(BD_Receitas[[#This Row],[TIPO DE COBRANÇA]]="Avanço Espaço", _xlfn.XLOOKUP(BD_Receitas[[#This Row],[ID]],TabCondicoesComerciais[ID],TabCondicoesComerciais[Avanço Espaço],0), IF(BD_Receitas[[#This Row],[TIPO DE COBRANÇA]]="Avanço Horário", _xlfn.XLOOKUP(BD_Receitas[[#This Row],[ID]],TabCondicoesComerciais[ID],TabCondicoesComerciais[Avanço Horário],0), IF(BD_Receitas[[#This Row],[TIPO DE COBRANÇA]]="Operação Normal", _xlfn.XLOOKUP(BD_Receitas[[#This Row],[ID]],TabCondicoesComerciais[ID],TabCondicoesComerciais[Tarifa 1º Giro],0),0))) -> 19.5 | S28: =IF(BD_Receitas[[#This Row],[TIPO DE COBRANÇA]]="Operação Normal", _xlfn.XLOOKUP(BD_Receitas[[#This Row],[ID]],TabCondicoesComerciais[ID],TabCondicoesComerciais[Tarifa 2º Giro],0),0) -> 19.5 | T28: =IFERROR(IF(BD_Receitas[[#This Row],[TIPO DE COBRANÇA]]<>"Operação Normal","",BD_Receitas[[#This Row],[Valor Total R$]]/ MAX(BD_Receitas[[#This Row],[Vol. Movimentado M³]], BD_Receitas[[#This Row],[Volume Mínimo ]]) ),0) -> 0 | U28: =IFERROR(IF(BD_Receitas[[#This Row],[TIPO DE COBRANÇA]]<>"Operação Normal","", SUMIFS(BD_Receitas[Valor Total R$],BD_Receitas[CONGENERE],BD_Receitas[[#This Row],[CONGENERE]],BD_Receitas[FILIAL],BD_Receitas[[#This Row],[FILIAL]],BD_Receitas[DATA CONTABIL],BD_Receitas[[#This Row],[DATA CONTABIL]]) /BD_Receitas[[#This Row],[Vol. Movimentado M³]] ),0) -> 0 | V28: =IF(BD_Receitas[[#This Row],[TIPO DE COBRANÇA]]<>"Operação Normal","",(BD_Receitas[[#This Row],[Volume 1º Giro]]*BD_Receitas[[#This Row],[Tarifa 1º Giro]])+(BD_Receitas[[#This Row],[Volume Mínimo ]]-BD_Receitas[[#This Row],[Volume 1º Giro]])*BD_Receitas[[#This Row],[Tarifa 2º Giro]]) -> 58500 | W28: =IF(BD_Receitas[[#This Row],[TIPO DE COBRANÇA]]<>"OPERAÇÃO NORMAL","", IF(BD_Receitas[[#This Row],[Vol. Movimentado M³]]<BD_Receitas[[#This Row],[Volume 1º Giro]],BD_Receitas[[#This Row],[Vol. Movimentado M³]]* BD_Receitas[[#This Row],[Tarifa 1º Giro]], (BD_Receitas[[#This Row],[Volume 1º Giro]]*BD_Receitas[[#This Row],[Tarifa 1º Giro]])+(BD_Receitas[[#This Row],[Vol. Movimentado M³]]-BD_Receitas[[#This Row],[Volume 1º Giro]])*BD_Receitas[[#This Row],[Tarifa 2º Giro]]) ) -> 0 | X28: =IF(BD_Receitas[[#This Row],[TIPO DE COBRANÇA]] <> "OPERAÇÃO NORMAL","", IF(BD_Receitas[[#This Row],[Vol. Movimentado M³]]= BD_Receitas[[#This Row],[Volume Mínimo ]], "Vol. Movimentado igual ao Vol. Mínimo", IF(ROUND(BD_Receitas[[#This Row],[Tarifa 1º Giro]],3) <> ROUND(BD_Receitas[[#This Row],[Tarifa Cobrada]],3), "Conferir tarifa cobrada", IF(BD_Receitas[[#This Row],[Volume Mínimo ]]=0,"Ok", IF(BD_Receitas[[#This Row],[Vol. Movimentado M³]]<= BD_Receitas[[#This Row],[Volume Mínimo ]], IF(ROUND(BD_Receitas[[#This Row],[Valor Total R$]],2) = ROUND(BD_Receitas[[#This Row],[Valor Total R$]],2), "Ok","Verificar Cobrança"), IF(ROUND(BD_Receitas[[#This Row],[Valor Contrato]],2) = ROUND(BD_Receitas[[#This Row],[Valor Movimentado]],2), "OK","Verificar cobrança") ))))) -> Conferir tarifa cobrada
A29: 13300 | B29: 45658 | C29: BRASILIA | D29: GOIANIA | E29: GO E TRIANGULO MINEIRO | F29: 13 | G29: Goiânia | H29: Petrobahia | I29: Outras Receitas | J29: 0 | K29: 0 | P29: =IF(BD_Receitas[[#This Row],[TIPO DE COBRANÇA]]="Operação Normal", _xlfn.XLOOKUP(BD_Receitas[[#This Row],[ID]],TabCondicoesComerciais[ID],TabCondicoesComerciais[Volume mínimo (m3)],0),"") | Q29: =_xlfn.XLOOKUP(BD_Receitas[[#This Row],[ID]],TabCondicoesComerciais[ID],TabCondicoesComerciais[Vol. 1ºGiro],0) -> 750 | R29: =IF(BD_Receitas[[#This Row],[TIPO DE COBRANÇA]]="Avanço Espaço", _xlfn.XLOOKUP(BD_Receitas[[#This Row],[ID]],TabCondicoesComerciais[ID],TabCondicoesComerciais[Avanço Espaço],0), IF(BD_Receitas[[#This Row],[TIPO DE COBRANÇA]]="Avanço Horário", _xlfn.XLOOKUP(BD_Receitas[[#This Row],[ID]],TabCondicoesComerciais[ID],TabCondicoesComerciais[Avanço Horário],0), IF(BD_Receitas[[#This Row],[TIPO DE COBRANÇA]]="Operação Normal", _xlfn.XLOOKUP(BD_Receitas[[#This Row],[ID]],TabCondicoesComerciais[ID],TabCondicoesComerciais[Tarifa 1º Giro],0),0))) -> 0 | S29: =IF(BD_Receitas[[#This Row],[TIPO DE COBRANÇA]]="Operação Normal", _xlfn.XLOOKUP(BD_Receitas[[#This Row],[ID]],TabCondicoesComerciais[ID],TabCondicoesComerciais[Tarifa 2º Giro],0),0) -> 0 | T29: =IFERROR(IF(BD_Receitas[[#This Row],[TIPO DE COBRANÇA]]<>"Operação Normal","",BD_Receitas[[#This Row],[Valor Total R$]]/ MAX(BD_Receitas[[#This Row],[Vol. Movimentado M³]], BD_Receitas[[#This Row],[Volume Mínimo ]]) ),0) | U29: =IFERROR(IF(BD_Receitas[[#This Row],[TIPO DE COBRANÇA]]<>"Operação Normal","", SUMIFS(BD_Receitas[Valor Total R$],BD_Receitas[CONGENERE],BD_Receitas[[#This Row],[CONGENERE]],BD_Receitas[FILIAL],BD_Receitas[[#This Row],[FILIAL]],BD_Receitas[DATA CONTABIL],BD_Receitas[[#This Row],[DATA CONTABIL]]) /BD_Receitas[[#This Row],[Vol. Movimentado M³]] ),0) | V29: =IF(BD_Receitas[[#This Row],[TIPO DE COBRANÇA]]<>"Operação Normal","",(BD_Receitas[[#This Row],[Volume 1º Giro]]*BD_Receitas[[#This Row],[Tarifa 1º Giro]])+(BD_Receitas[[#This Row],[Volume Mínimo ]]-BD_Receitas[[#This Row],[Volume 1º Giro]])*BD_Receitas[[#This Row],[Tarifa 2º Giro]]) | W29: =IF(BD_Receitas[[#This Row],[TIPO DE COBRANÇA]]<>"OPERAÇÃO NORMAL","", IF(BD_Receitas[[#This Row],[Vol. Movimentado M³]]<BD_Receitas[[#This Row],[Volume 1º Giro]],BD_Receitas[[#This Row],[Vol. Movimentado M³]]* BD_Receitas[[#This Row],[Tarifa 1º Giro]], (BD_Receitas[[#This Row],[Volume 1º Giro]]*BD_Receitas[[#This Row],[Tarifa 1º Giro]])+(BD_Receitas[[#This Row],[Vol. Movimentado M³]]-BD_Receitas[[#This Row],[Volume 1º Giro]])*BD_Receitas[[#This Row],[Tarifa 2º Giro]]) ) | X29: =IF(BD_Receitas[[#This Row],[TIPO DE COBRANÇA]] <> "OPERAÇÃO NORMAL","", IF(BD_Receitas[[#This Row],[Vol. Movimentado M³]]= BD_Receitas[[#This Row],[Volume Mínimo ]], "Vol. Movimentado igual ao Vol. Mínimo", IF(ROUND(BD_Receitas[[#This Row],[Tarifa 1º Giro]],3) <> ROUND(BD_Receitas[[#This Row],[Tarifa Cobrada]],3), "Conferir tarifa cobrada", IF(BD_Receitas[[#This Row],[Volume Mínimo ]]=0,"Ok", IF(BD_Receitas[[#This Row],[Vol. Movimentado M³]]<= BD_Receitas[[#This Row],[Volume Mínimo ]], IF(ROUND(BD_Receitas[[#This Row],[Valor Total R$]],2) = ROUND(BD_Receitas[[#This Row],[Valor Total R$]],2), "Ok","Verificar Cobrança"), IF(ROUND(BD_Receitas[[#This Row],[Valor Contrato]],2) = ROUND(BD_Receitas[[#This Row],[Valor Movimentado]],2), "OK","Verificar cobrança") )))))
A30: 38203 | B30: 45658 | C30: BRASILIA | D30: GUAMARE | E30: NORDESTE | F30: 38 | G30: Guamaré | H30: Raízen | I30: Avanço Espaço | J30: 0 | K30: 0 | L30: 2410.53 | M30: 334.796 | N30: 99 | P30: =IF(BD_Receitas[[#This Row],[TIPO DE COBRANÇA]]="Operação Normal", _xlfn.XLOOKUP(BD_Receitas[[#This Row],[ID]],TabCondicoesComerciais[ID],TabCondicoesComerciais[Volume mínimo (m3)],0),"") | Q30: =_xlfn.XLOOKUP(BD_Receitas[[#This Row],[ID]],TabCondicoesComerciais[ID],TabCondicoesComerciais[Vol. 1ºGiro],0) -> 1070 | R30: =IF(BD_Receitas[[#This Row],[TIPO DE COBRANÇA]]="Avanço Espaço", _xlfn.XLOOKUP(BD_Receitas[[#This Row],[ID]],TabCondicoesComerciais[ID],TabCondicoesComerciais[Avanço Espaço],0), IF(BD_Receitas[[#This Row],[TIPO DE COBRANÇA]]="Avanço Horário", _xlfn.XLOOKUP(BD_Receitas[[#This Row],[ID]],TabCondicoesComerciais[ID],TabCondicoesComerciais[Avanço Horário],0), IF(BD_Receitas[[#This Row],[TIPO DE COBRANÇA]]="Operação Normal", _xlfn.XLOOKUP(BD_Receitas[[#This Row],[ID]],TabCondicoesComerciais[ID],TabCondicoesComerciais[Tarifa 1º Giro],0),0))) -> 12 | S30: =IF(BD_Receitas[[#This Row],[TIPO DE COBRANÇA]]="Operação Normal", _xlfn.XLOOKUP(BD_Receitas[[#This Row],[ID]],TabCondicoesComerciais[ID],TabCondicoesComerciais[Tarifa 2º Giro],0),0) -> 0 | T30: =IFERROR(IF(BD_Receitas[[#This Row],[TIPO DE COBRANÇA]]<>"Operação Normal","",BD_Receitas[[#This Row],[Valor Total R$]]/ MAX(BD_Receitas[[#This Row],[Vol. Movimentado M³]], BD_Receitas[[#This Row],[Volume Mínimo ]]) ),0) | U30: =IFERROR(IF(BD_Receitas[[#This Row],[TIPO DE COBRANÇA]]<>"Operação Normal","", SUMIFS(BD_Receitas[Valor Total R$],BD_Receitas[CONGENERE],BD_Receitas[[#This Row],[CONGENERE]],BD_Receitas[FILIAL],BD_Receitas[[#This Row],[FILIAL]],BD_Receitas[DATA CONTABIL],BD_Receitas[[#This Row],[DATA CONTABIL]]) /BD_Receitas[[#This Row],[Vol. Movimentado M³]] ),0) | V30: =IF(BD_Receitas[[#This Row],[TIPO DE COBRANÇA]]<>"Operação Normal","",(BD_Receitas[[#This Row],[Volume 1º Giro]]*BD_Receitas[[#This Row],[Tarifa 1º Giro]])+(BD_Receitas[[#This Row],[Volume Mínimo ]]-BD_Receitas[[#This Row],[Volume 1º Giro]])*BD_Receitas[[#This Row],[Tarifa 2º Giro]]) | W30: =IF(BD_Receitas[[#This Row],[TIPO DE COBRANÇA]]<>"OPERAÇÃO NORMAL","", IF(BD_Receitas[[#This Row],[Vol. Movimentado M³]]<BD_Receitas[[#This Row],[Volume 1º Giro]],BD_Receitas[[#This Row],[Vol. Movimentado M³]]* BD_Receitas[[#This Row],[Tarifa 1º Giro]], (BD_Receitas[[#This Row],[Volume 1º Giro]]*BD_Receitas[[#This Row],[Tarifa 1º Giro]])+(BD_Receitas[[#This Row],[Vol. Movimentado M³]]-BD_Receitas[[#This Row],[Volume 1º Giro]])*BD_Receitas[[#This Row],[Tarifa 2º Giro]]) ) | X30: =IF(BD_Receitas[[#This Row],[TIPO DE COBRANÇA]] <> "OPERAÇÃO NORMAL","", IF(BD_Receitas[[#This Row],[Vol. Movimentado M³]]= BD_Receitas[[#This Row],[Volume Mínimo ]], "Vol. Movimentado igual ao Vol. Mínimo", IF(ROUND(BD_Receitas[[#This Row],[Tarifa 1º Giro]],3) <> ROUND(BD_Receitas[[#This Row],[Tarifa Cobrada]],3), "Conferir tarifa cobrada", IF(BD_Receitas[[#This Row],[Volume Mínimo ]]=0,"Ok", IF(BD_Receitas[[#This Row],[Vol. Movimentado M³]]<= BD_Receitas[[#This Row],[Volume Mínimo ]], IF(ROUND(BD_Receitas[[#This Row],[Valor Total R$]],2) = ROUND(BD_Receitas[[#This Row],[Valor Total R$]],2), "Ok","Verificar Cobrança"), IF(ROUND(BD_Receitas[[#This Row],[Valor Contrato]],2) = ROUND(BD_Receitas[[#This Row],[Valor Movimentado]],2), "OK","Verificar cobrança") )))))
A31: 38203 | B31: 45658 | C31: BRASILIA | D31: GUAMARE | E31: NORDESTE | F31: 38 | G31: Guamaré | H31: Raízen | I31: Avanço Horário | J31: 0 | K31: 0 | L31: 1799.064 | M31: 249.87 | N31: 99 | P31: =IF(BD_Receitas[[#This Row],[TIPO DE COBRANÇA]]="Operação Normal", _xlfn.XLOOKUP(BD_Receitas[[#This Row],[ID]],TabCondicoesComerciais[ID],TabCondicoesComerciais[Volume mínimo (m3)],0),"") | Q31: =_xlfn.XLOOKUP(BD_Receitas[[#This Row],[ID]],TabCondicoesComerciais[ID],TabCondicoesComerciais[Vol. 1ºGiro],0) -> 1070 | R31: =IF(BD_Receitas[[#This Row],[TIPO DE COBRANÇA]]="Avanço Espaço", _xlfn.XLOOKUP(BD_Receitas[[#This Row],[ID]],TabCondicoesComerciais[ID],TabCondicoesComerciais[Avanço Espaço],0), IF(BD_Receitas[[#This Row],[TIPO DE COBRANÇA]]="Avanço Horário", _xlfn.XLOOKUP(BD_Receitas[[#This Row],[ID]],TabCondicoesComerciais[ID],TabCondicoesComerciais[Avanço Horário],0), IF(BD_Receitas[[#This Row],[TIPO DE COBRANÇA]]="Operação Normal", _xlfn.XLOOKUP(BD_Receitas[[#This Row],[ID]],TabCondicoesComerciais[ID],TabCondicoesComerciais[Tarifa 1º Giro],0),0))) -> 12 | S31: =IF(BD_Receitas[[#This Row],[TIPO DE COBRANÇA]]="Operação Normal", _xlfn.XLOOKUP(BD_Receitas[[#This Row],[ID]],TabCondicoesComerciais[ID],TabCondicoesComerciais[Tarifa 2º Giro],0),0) -> 0 | T31: =IFERROR(IF(BD_Receitas[[#This Row],[TIPO DE COBRANÇA]]<>"Operação Normal","",BD_Receitas[[#This Row],[Valor Total R$]]/ MAX(BD_Receitas[[#This Row],[Vol. Movimentado M³]], BD_Receitas[[#This Row],[Volume Mínimo ]]) ),0) | U31: =IFERROR(IF(BD_Receitas[[#This Row],[TIPO DE COBRANÇA]]<>"Operação Normal","", SUMIFS(BD_Receitas[Valor Total R$],BD_Receitas[CONGENERE],BD_Receitas[[#This Row],[CONGENERE]],BD_Receitas[FILIAL],BD_Receitas[[#This Row],[FILIAL]],BD_Receitas[DATA CONTABIL],BD_Receitas[[#This Row],[DATA CONTABIL]]) /BD_Receitas[[#This Row],[Vol. Movimentado M³]] ),0) | V31: =IF(BD_Receitas[[#This Row],[TIPO DE COBRANÇA]]<>"Operação Normal","",(BD_Receitas[[#This Row],[Volume 1º Giro]]*BD_Receitas[[#This Row],[Tarifa 1º Giro]])+(BD_Receitas[[#This Row],[Volume Mínimo ]]-BD_Receitas[[#This Row],[Volume 1º Giro]])*BD_Receitas[[#This Row],[Tarifa 2º Giro]]) | W31: =IF(BD_Receitas[[#This Row],[TIPO DE COBRANÇA]]<>"OPERAÇÃO NORMAL","", IF(BD_Receitas[[#This Row],[Vol. Movimentado M³]]<BD_Receitas[[#This Row],[Volume 1º Giro]],BD_Receitas[[#This Row],[Vol. Movimentado M³]]* BD_Receitas[[#This Row],[Tarifa 1º Giro]], (BD_Receitas[[#This Row],[Volume 1º Giro]]*BD_Receitas[[#This Row],[Tarifa 1º Giro]])+(BD_Receitas[[#This Row],[Vol. Movimentado M³]]-BD_Receitas[[#This Row],[Volume 1º Giro]])*BD_Receitas[[#This Row],[Tarifa 2º Giro]]) ) | X31: =IF(BD_Receitas[[#This Row],[TIPO DE COBRANÇA]] <> "OPERAÇÃO NORMAL","", IF(BD_Receitas[[#This Row],[Vol. Movimentado M³]]= BD_Receitas[[#This Row],[Volume Mínimo ]], "Vol. Movimentado igual ao Vol. Mínimo", IF(ROUND(BD_Receitas[[#This Row],[Tarifa 1º Giro]],3) <> ROUND(BD_Receitas[[#This Row],[Tarifa Cobrada]],3), "Conferir tarifa cobrada", IF(BD_Receitas[[#This Row],[Volume Mínimo ]]=0,"Ok", IF(BD_Receitas[[#This Row],[Vol. Movimentado M³]]<= BD_Receitas[[#This Row],[Volume Mínimo ]], IF(ROUND(BD_Receitas[[#This Row],[Valor Total R$]],2) = ROUND(BD_Receitas[[#This Row],[Valor Total R$]],2), "Ok","Verificar Cobrança"), IF(ROUND(BD_Receitas[[#This Row],[Valor Contrato]],2) = ROUND(BD_Receitas[[#This Row],[Valor Movimentado]],2), "OK","Verificar cobrança") )))))
A32: 38203 | B32: 45658 | C32: BRASILIA | D32: GUAMARE | E32: NORDESTE | F32: 38 | G32: Guamaré | H32: Raízen | I32: Operação Normal | J32: 137499.16 | K32: 4200 | L32: 57780 | M32: 2343.207 | N32: 99 | P32: =IF(BD_Receitas[[#This Row],[TIPO DE COBRANÇA]]="Operação Normal", _xlfn.XLOOKUP(BD_Receitas[[#This Row],[ID]],TabCondicoesComerciais[ID],TabCondicoesComerciais[Volume mínimo (m3)],0),"") -> 3210 | Q32: =_xlfn.XLOOKUP(BD_Receitas[[#This Row],[ID]],TabCondicoesComerciais[ID],TabCondicoesComerciais[Vol. 1ºGiro],0) -> 1070 | R32: =IF(BD_Receitas[[#This Row],[TIPO DE COBRANÇA]]="Avanço Espaço", _xlfn.XLOOKUP(BD_Receitas[[#This Row],[ID]],TabCondicoesComerciais[ID],TabCondicoesComerciais[Avanço Espaço],0), IF(BD_Receitas[[#This Row],[TIPO DE COBRANÇA]]="Avanço Horário", _xlfn.XLOOKUP(BD_Receitas[[#This Row],[ID]],TabCondicoesComerciais[ID],TabCondicoesComerciais[Avanço Horário],0), IF(BD_Receitas[[#This Row],[TIPO DE COBRANÇA]]="Operação Normal", _xlfn.XLOOKUP(BD_Receitas[[#This Row],[ID]],TabCondicoesComerciais[ID],TabCondicoesComerciais[Tarifa 1º Giro],0),0))) -> 30 | S32: =IF(BD_Receitas[[#This Row],[TIPO DE COBRANÇA]]="Operação Normal", _xlfn.XLOOKUP(BD_Receitas[[#This Row],[ID]],TabCondicoesComerciais[ID],TabCondicoesComerciais[Tarifa 2º Giro],0),0) -> 30 | T32: =IFERROR(IF(BD_Receitas[[#This Row],[TIPO DE COBRANÇA]]<>"Operação Normal","",BD_Receitas[[#This Row],[Valor Total R$]]/ MAX(BD_Receitas[[#This Row],[Vol. Movimentado M³]], BD_Receitas[[#This Row],[Volume Mínimo ]]) ),0) -> 18 | U32: =IFERROR(IF(BD_Receitas[[#This Row],[TIPO DE COBRANÇA]]<>"Operação Normal","", SUMIFS(BD_Receitas[Valor Total R$],BD_Receitas[CONGENERE],BD_Receitas[[#This Row],[CONGENERE]],BD_Receitas[FILIAL],BD_Receitas[[#This Row],[FILIAL]],BD_Receitas[DATA CONTABIL],BD_Receitas[[#This Row],[DATA CONTABIL]]) /BD_Receitas[[#This Row],[Vol. Movimentado M³]] ),0) -> 29.036101 | V32: =IF(BD_Receitas[[#This Row],[TIPO DE COBRANÇA]]<>"Operação Normal","",(BD_Receitas[[#This Row],[Volume 1º Giro]]*BD_Receitas[[#This Row],[Tarifa 1º Giro]])+(BD_Receitas[[#This Row],[Volume Mínimo ]]-BD_Receitas[[#This Row],[Volume 1º Giro]])*BD_Receitas[[#This Row],[Tarifa 2º Giro]]) -> 96300 | W32: =IF(BD_Receitas[[#This Row],[TIPO DE COBRANÇA]]<>"OPERAÇÃO NORMAL","", IF(BD_Receitas[[#This Row],[Vol. Movimentado M³]]<BD_Receitas[[#This Row],[Volume 1º Giro]],BD_Receitas[[#This Row],[Vol. Movimentado M³]]* BD_Receitas[[#This Row],[Tarifa 1º Giro]], (BD_Receitas[[#This Row],[Volume 1º Giro]]*BD_Receitas[[#This Row],[Tarifa 1º Giro]])+(BD_Receitas[[#This Row],[Vol. Movimentado M³]]-BD_Receitas[[#This Row],[Volume 1º Giro]])*BD_Receitas[[#This Row],[Tarifa 2º Giro]]) ) -> 70296.21 | X32: =IF(BD_Receitas[[#This Row],[TIPO DE COBRANÇA]] <> "OPERAÇÃO NORMAL","", IF(BD_Receitas[[#This Row],[Vol. Movimentado M³]]= BD_Receitas[[#This Row],[Volume Mínimo ]], "Vol. Movimentado igual ao Vol. Mínimo", IF(ROUND(BD_Receitas[[#This Row],[Tarifa 1º Giro]],3) <> ROUND(BD_Receitas[[#This Row],[Tarifa Cobrada]],3), "Conferir tarifa cobrada", IF(BD_Receitas[[#This Row],[Volume Mínimo ]]=0,"Ok", IF(BD_Receitas[[#This Row],[Vol. Movimentado M³]]<= BD_Receitas[[#This Row],[Volume Mínimo ]], IF(ROUND(BD_Receitas[[#This Row],[Valor Total R$]],2) = ROUND(BD_Receitas[[#This Row],[Valor Total R$]],2), "Ok","Verificar Cobrança"), IF(ROUND(BD_Receitas[[#This Row],[Valor Contrato]],2) = ROUND(BD_Receitas[[#This Row],[Valor Movimentado]],2), "OK","Verificar cobrança") ))))) -> Conferir tarifa cobrada
A33: 38203 | B33: 45658 | C33: BRASILIA | D33: GUAMARE | E33: NORDESTE | F33: 38 | G33: Guamaré | H33: Raízen | I33: Outras Receitas | J33: 0 | K33: 0 | L33: 6048 | M33: 0 | N33: 99 | P33: =IF(BD_Receitas[[#This Row],[TIPO DE COBRANÇA]]="Operação Normal", _xlfn.XLOOKUP(BD_Receitas[[#This Row],[ID]],TabCondicoesComerciais[ID],TabCondicoesComerciais[Volume mínimo (m3)],0),"") | Q33: =_xlfn.XLOOKUP(BD_Receitas[[#This Row],[ID]],TabCondicoesComerciais[ID],TabCondicoesComerciais[Vol. 1ºGiro],0) -> 1070 | R33: =IF(BD_Receitas[[#This Row],[TIPO DE COBRANÇA]]="Avanço Espaço", _xlfn.XLOOKUP(BD_Receitas[[#This Row],[ID]],TabCondicoesComerciais[ID],TabCondicoesComerciais[Avanço Espaço],0), IF(BD_Receitas[[#This Row],[TIPO DE COBRANÇA]]="Avanço Horário", _xlfn.XLOOKUP(BD_Receitas[[#This Row],[ID]],TabCondicoesComerciais[ID],TabCondicoesComerciais[Avanço Horário],0), IF(BD_Receitas[[#This Row],[TIPO DE COBRANÇA]]="Operação Normal", _xlfn.XLOOKUP(BD_Receitas[[#This Row],[ID]],TabCondicoesComerciais[ID],TabCondicoesComerciais[Tarifa 1º Giro],0),0))) -> 0 | S33: =IF(BD_Receitas[[#This Row],[TIPO DE COBRANÇA]]="Operação Normal", _xlfn.XLOOKUP(BD_Receitas[[#This Row],[ID]],TabCondicoesComerciais[ID],TabCondicoesComerciais[Tarifa 2º Giro],0),0) -> 0 | T33: =IFERROR(IF(BD_Receitas[[#This Row],[TIPO DE COBRANÇA]]<>"Operação Normal","",BD_Receitas[[#This Row],[Valor Total R$]]/ MAX(BD_Receitas[[#This Row],[Vol. Movimentado M³]], BD_Receitas[[#This Row],[Volume Mínimo ]]) ),0) | U33: =IFERROR(IF(BD_Receitas[[#This Row],[TIPO DE COBRANÇA]]<>"Operação Normal","", SUMIFS(BD_Receitas[Valor Total R$],BD_Receitas[CONGENERE],BD_Receitas[[#This Row],[CONGENERE]],BD_Receitas[FILIAL],BD_Receitas[[#This Row],[FILIAL]],BD_Receitas[DATA CONTABIL],BD_Receitas[[#This Row],[DATA CONTABIL]]) /BD_Receitas[[#This Row],[Vol. Movimentado M³]] ),0) | V33: =IF(BD_Receitas[[#This Row],[TIPO DE COBRANÇA]]<>"Operação Normal","",(BD_Receitas[[#This Row],[Volume 1º Giro]]*BD_Receitas[[#This Row],[Tarifa 1º Giro]])+(BD_Receitas[[#This Row],[Volume Mínimo ]]-BD_Receitas[[#This Row],[Volume 1º Giro]])*BD_Receitas[[#This Row],[Tarifa 2º Giro]]) | W33: =IF(BD_Receitas[[#This Row],[TIPO DE COBRANÇA]]<>"OPERAÇÃO NORMAL","", IF(BD_Receitas[[#This Row],[Vol. Movimentado M³]]<BD_Receitas[[#This Row],[Volume 1º Giro]],BD_Receitas[[#This Row],[Vol. Movimentado M³]]* BD_Receitas[[#This Row],[Tarifa 1º Giro]], (BD_Receitas[[#This Row],[Volume 1º Giro]]*BD_Receitas[[#This Row],[Tarifa 1º Giro]])+(BD_Receitas[[#This Row],[Vol. Movimentado M³]]-BD_Receitas[[#This Row],[Volume 1º Giro]])*BD_Receitas[[#This Row],[Tarifa 2º Giro]]) ) | X33: =IF(BD_Receitas[[#This Row],[TIPO DE COBRANÇA]] <> "OPERAÇÃO NORMAL","", IF(BD_Receitas[[#This Row],[Vol. Movimentado M³]]= BD_Receitas[[#This Row],[Volume Mínimo ]], "Vol. Movimentado igual ao Vol. Mínimo", IF(ROUND(BD_Receitas[[#This Row],[Tarifa 1º Giro]],3) <> ROUND(BD_Receitas[[#This Row],[Tarifa Cobrada]],3), "Conferir tarifa cobrada", IF(BD_Receitas[[#This Row],[Volume Mínimo ]]=0,"Ok", IF(BD_Receitas[[#This Row],[Vol. Movimentado M³]]<= BD_Receitas[[#This Row],[Volume Mínimo ]], IF(ROUND(BD_Receitas[[#This Row],[Valor Total R$]],2) = ROUND(BD_Receitas[[#This Row],[Valor Total R$]],2), "Ok","Verificar Cobrança"), IF(ROUND(BD_Receitas[[#This Row],[Valor Contrato]],2) = ROUND(BD_Receitas[[#This Row],[Valor Movimentado]],2), "OK","Verificar cobrança") )))))
A34: 1607 | B34: 45658 | C34: BRASILIA | D34: SAO PAULO | E34: PAULISTA | F34: 16 | G34: Guarulhos | H34: Ipiranga | I34: Avanço Espaço | J34: 0 | K34: 0 | P34: =IF(BD_Receitas[[#This Row],[TIPO DE COBRANÇA]]="Operação Normal", _xlfn.XLOOKUP(BD_Receitas[[#This Row],[ID]],TabCondicoesComerciais[ID],TabCondicoesComerciais[Volume mínimo (m3)],0),"") | Q34: =_xlfn.XLOOKUP(BD_Receitas[[#This Row],[ID]],TabCondicoesComerciais[ID],TabCondicoesComerciais[Vol. 1ºGiro],0) -> 2000 | R34: =IF(BD_Receitas[[#This Row],[TIPO DE COBRANÇA]]="Avanço Espaço", _xlfn.XLOOKUP(BD_Receitas[[#This Row],[ID]],TabCondicoesComerciais[ID],TabCondicoesComerciais[Avanço Espaço],0), IF(BD_Receitas[[#This Row],[TIPO DE COBRANÇA]]="Avanço Horário", _xlfn.XLOOKUP(BD_Receitas[[#This Row],[ID]],TabCondicoesComerciais[ID],TabCondicoesComerciais[Avanço Horário],0), IF(BD_Receitas[[#This Row],[TIPO DE COBRANÇA]]="Operação Normal", _xlfn.XLOOKUP(BD_Receitas[[#This Row],[ID]],TabCondicoesComerciais[ID],TabCondicoesComerciais[Tarifa 1º Giro],0),0))) -> 28 | S34: =IF(BD_Receitas[[#This Row],[TIPO DE COBRANÇA]]="Operação Normal", _xlfn.XLOOKUP(BD_Receitas[[#This Row],[ID]],TabCondicoesComerciais[ID],TabCondicoesComerciais[Tarifa 2º Giro],0),0) -> 0 | T34: =IFERROR(IF(BD_Receitas[[#This Row],[TIPO DE COBRANÇA]]<>"Operação Normal","",BD_Receitas[[#This Row],[Valor Total R$]]/ MAX(BD_Receitas[[#This Row],[Vol. Movimentado M³]], BD_Receitas[[#This Row],[Volume Mínimo ]]) ),0) | U34: =IFERROR(IF(BD_Receitas[[#This Row],[TIPO DE COBRANÇA]]<>"Operação Normal","", SUMIFS(BD_Receitas[Valor Total R$],BD_Receitas[CONGENERE],BD_Receitas[[#This Row],[CONGENERE]],BD_Receitas[FILIAL],BD_Receitas[[#This Row],[FILIAL]],BD_Receitas[DATA CONTABIL],BD_Receitas[[#This Row],[DATA CONTABIL]]) /BD_Receitas[[#This Row],[Vol. Movimentado M³]] ),0) | V34: =IF(BD_Receitas[[#This Row],[TIPO DE COBRANÇA]]<>"Operação Normal","",(BD_Receitas[[#This Row],[Volume 1º Giro]]*BD_Receitas[[#This Row],[Tarifa 1º Giro]])+(BD_Receitas[[#This Row],[Volume Mínimo ]]-BD_Receitas[[#This Row],[Volume 1º Giro]])*BD_Receitas[[#This Row],[Tarifa 2º Giro]]) | W34: =IF(BD_Receitas[[#This Row],[TIPO DE COBRANÇA]]<>"OPERAÇÃO NORMAL","", IF(BD_Receitas[[#This Row],[Vol. Movimentado M³]]<BD_Receitas[[#This Row],[Volume 1º Giro]],BD_Receitas[[#This Row],[Vol. Movimentado M³]]* BD_Receitas[[#This Row],[Tarifa 1º Giro]], (BD_Receitas[[#This Row],[Volume 1º Giro]]*BD_Receitas[[#This Row],[Tarifa 1º Giro]])+(BD_Receitas[[#This Row],[Vol. Movimentado M³]]-BD_Receitas[[#This Row],[Volume 1º Giro]])*BD_Receitas[[#This Row],[Tarifa 2º Giro]]) ) | X34: =IF(BD_Receitas[[#This Row],[TIPO DE COBRANÇA]] <> "OPERAÇÃO NORMAL","", IF(BD_Receitas[[#This Row],[Vol. Movimentado M³]]= BD_Receitas[[#This Row],[Volume Mínimo ]], "Vol. Movimentado igual ao Vol. Mínimo", IF(ROUND(BD_Receitas[[#This Row],[Tarifa 1º Giro]],3) <> ROUND(BD_Receitas[[#This Row],[Tarifa Cobrada]],3), "Conferir tarifa cobrada", IF(BD_Receitas[[#This Row],[Volume Mínimo ]]=0,"Ok", IF(BD_Receitas[[#This Row],[Vol. Movimentado M³]]<= BD_Receitas[[#This Row],[Volume Mínimo ]], IF(ROUND(BD_Receitas[[#This Row],[Valor Total R$]],2) = ROUND(BD_Receitas[[#This Row],[Valor Total R$]],2), "Ok","Verificar Cobrança"), IF(ROUND(BD_Receitas[[#This Row],[Valor Contrato]],2) = ROUND(BD_Receitas[[#This Row],[Valor Movimentado]],2), "OK","Verificar cobrança") )))))
A35: 1607 | B35: 45658 | C35: BRASILIA | D35: SAO PAULO | E35: PAULISTA | F35: 16 | G35: Guarulhos | H35: Ipiranga | I35: Avanço Horário | J35: 0 | K35: 0 | P35: =IF(BD_Receitas[[#This Row],[TIPO DE COBRANÇA]]="Operação Normal", _xlfn.XLOOKUP(BD_Receitas[[#This Row],[ID]],TabCondicoesComerciais[ID],TabCondicoesComerciais[Volume mínimo (m3)],0),"") | Q35: =_xlfn.XLOOKUP(BD_Receitas[[#This Row],[ID]],TabCondicoesComerciais[ID],TabCondicoesComerciais[Vol. 1ºGiro],0) -> 2000 | R35: =IF(BD_Receitas[[#This Row],[TIPO DE COBRANÇA]]="Avanço Espaço", _xlfn.XLOOKUP(BD_Receitas[[#This Row],[ID]],TabCondicoesComerciais[ID],TabCondicoesComerciais[Avanço Espaço],0), IF(BD_Receitas[[#This Row],[TIPO DE COBRANÇA]]="Avanço Horário", _xlfn.XLOOKUP(BD_Receitas[[#This Row],[ID]],TabCondicoesComerciais[ID],TabCondicoesComerciais[Avanço Horário],0), IF(BD_Receitas[[#This Row],[TIPO DE COBRANÇA]]="Operação Normal", _xlfn.XLOOKUP(BD_Receitas[[#This Row],[ID]],TabCondicoesComerciais[ID],TabCondicoesComerciais[Tarifa 1º Giro],0),0))) -> 28 | S35: =IF(BD_Receitas[[#This Row],[TIPO DE COBRANÇA]]="Operação Normal", _xlfn.XLOOKUP(BD_Receitas[[#This Row],[ID]],TabCondicoesComerciais[ID],TabCondicoesComerciais[Tarifa 2º Giro],0),0) -> 0 | T35: =IFERROR(IF(BD_Receitas[[#This Row],[TIPO DE COBRANÇA]]<>"Operação Normal","",BD_Receitas[[#This Row],[Valor Total R$]]/ MAX(BD_Receitas[[#This Row],[Vol. Movimentado M³]], BD_Receitas[[#This Row],[Volume Mínimo ]]) ),0) | U35: =IFERROR(IF(BD_Receitas[[#This Row],[TIPO DE COBRANÇA]]<>"Operação Normal","", SUMIFS(BD_Receitas[Valor Total R$],BD_Receitas[CONGENERE],BD_Receitas[[#This Row],[CONGENERE]],BD_Receitas[FILIAL],BD_Receitas[[#This Row],[FILIAL]],BD_Receitas[DATA CONTABIL],BD_Receitas[[#This Row],[DATA CONTABIL]]) /BD_Receitas[[#This Row],[Vol. Movimentado M³]] ),0) | V35: =IF(BD_Receitas[[#This Row],[TIPO DE COBRANÇA]]<>"Operação Normal","",(BD_Receitas[[#This Row],[Volume 1º Giro]]*BD_Receitas[[#This Row],[Tarifa 1º Giro]])+(BD_Receitas[[#This Row],[Volume Mínimo ]]-BD_Receitas[[#This Row],[Volume 1º Giro]])*BD_Receitas[[#This Row],[Tarifa 2º Giro]]) | W35: =IF(BD_Receitas[[#This Row],[TIPO DE COBRANÇA]]<>"OPERAÇÃO NORMAL","", IF(BD_Receitas[[#This Row],[Vol. Movimentado M³]]<BD_Receitas[[#This Row],[Volume 1º Giro]],BD_Receitas[[#This Row],[Vol. Movimentado M³]]* BD_Receitas[[#This Row],[Tarifa 1º Giro]], (BD_Receitas[[#This Row],[Volume 1º Giro]]*BD_Receitas[[#This Row],[Tarifa 1º Giro]])+(BD_Receitas[[#This Row],[Vol. Movimentado M³]]-BD_Receitas[[#This Row],[Volume 1º Giro]])*BD_Receitas[[#This Row],[Tarifa 2º Giro]]) ) | X35: =IF(BD_Receitas[[#This Row],[TIPO DE COBRANÇA]] <> "OPERAÇÃO NORMAL","", IF(BD_Receitas[[#This Row],[Vol. Movimentado M³]]= BD_Receitas[[#This Row],[Volume Mínimo ]], "Vol. Movimentado igual ao Vol. Mínimo", IF(ROUND(BD_Receitas[[#This Row],[Tarifa 1º Giro]],3) <> ROUND(BD_Receitas[[#This Row],[Tarifa Cobrada]],3), "Conferir tarifa cobrada", IF(BD_Receitas[[#This Row],[Volume Mínimo ]]=0,"Ok", IF(BD_Receitas[[#This Row],[Vol. Movimentado M³]]<= BD_Receitas[[#This Row],[Volume Mínimo ]], IF(ROUND(BD_Receitas[[#This Row],[Valor Total R$]],2) = ROUND(BD_Receitas[[#This Row],[Valor Total R$]],2), "Ok","Verificar Cobrança"), IF(ROUND(BD_Receitas[[#This Row],[Valor Contrato]],2) = ROUND(BD_Receitas[[#This Row],[Valor Movimentado]],2), "OK","Verificar cobrança") )))))
A36: 1607 | B36: 45658 | C36: BRASILIA | D36: SAO PAULO | E36: PAULISTA | F36: 16 | G36: Guarulhos | H36: Ipiranga | I36: Operação Normal | J36: 0 | K36: 0 | P36: =IF(BD_Receitas[[#This Row],[TIPO DE COBRANÇA]]="Operação Normal", _xlfn.XLOOKUP(BD_Receitas[[#This Row],[ID]],TabCondicoesComerciais[ID],TabCondicoesComerciais[Volume mínimo (m3)],0),"") -> 8000 | Q36: =_xlfn.XLOOKUP(BD_Receitas[[#This Row],[ID]],TabCondicoesComerciais[ID],TabCondicoesComerciais[Vol. 1ºGiro],0) -> 2000 | R36: =IF(BD_Receitas[[#This Row],[TIPO DE COBRANÇA]]="Avanço Espaço", _xlfn.XLOOKUP(BD_Receitas[[#This Row],[ID]],TabCondicoesComerciais[ID],TabCondicoesComerciais[Avanço Espaço],0), IF(BD_Receitas[[#This Row],[TIPO DE COBRANÇA]]="Avanço Horário", _xlfn.XLOOKUP(BD_Receitas[[#This Row],[ID]],TabCondicoesComerciais[ID],TabCondicoesComerciais[Avanço Horário],0), IF(BD_Receitas[[#This Row],[TIPO DE COBRANÇA]]="Operação Normal", _xlfn.XLOOKUP(BD_Receitas[[#This Row],[ID]],TabCondicoesComerciais[ID],TabCondicoesComerciais[Tarifa 1º Giro],0),0))) -> 20 | S36: =IF(BD_Receitas[[#This Row],[TIPO DE COBRANÇA]]="Operação Normal", _xlfn.XLOOKUP(BD_Receitas[[#This Row],[ID]],TabCondicoesComerciais[ID],TabCondicoesComerciais[Tarifa 2º Giro],0),0) -> 20 | T36: =IFERROR(IF(BD_Receitas[[#This Row],[TIPO DE COBRANÇA]]<>"Operação Normal","",BD_Receitas[[#This Row],[Valor Total R$]]/ MAX(BD_Receitas[[#This Row],[Vol. Movimentado M³]], BD_Receitas[[#This Row],[Volume Mínimo ]]) ),0) -> 0 | U36: =IFERROR(IF(BD_Receitas[[#This Row],[TIPO DE COBRANÇA]]<>"Operação Normal","", SUMIFS(BD_Receitas[Valor Total R$],BD_Receitas[CONGENERE],BD_Receitas[[#This Row],[CONGENERE]],BD_Receitas[FILIAL],BD_Receitas[[#This Row],[FILIAL]],BD_Receitas[DATA CONTABIL],BD_Receitas[[#This Row],[DATA CONTABIL]]) /BD_Receitas[[#This Row],[Vol. Movimentado M³]] ),0) -> 0 | V36: =IF(BD_Receitas[[#This Row],[TIPO DE COBRANÇA]]<>"Operação Normal","",(BD_Receitas[[#This Row],[Volume 1º Giro]]*BD_Receitas[[#This Row],[Tarifa 1º Giro]])+(BD_Receitas[[#This Row],[Volume Mínimo ]]-BD_Receitas[[#This Row],[Volume 1º Giro]])*BD_Receitas[[#This Row],[Tarifa 2º Giro]]) -> 160000 | W36: =IF(BD_Receitas[[#This Row],[TIPO DE COBRANÇA]]<>"OPERAÇÃO NORMAL","", IF(BD_Receitas[[#This Row],[Vol. Movimentado M³]]<BD_Receitas[[#This Row],[Volume 1º Giro]],BD_Receitas[[#This Row],[Vol. Movimentado M³]]* BD_Receitas[[#This Row],[Tarifa 1º Giro]], (BD_Receitas[[#This Row],[Volume 1º Giro]]*BD_Receitas[[#This Row],[Tarifa 1º Giro]])+(BD_Receitas[[#This Row],[Vol. Movimentado M³]]-BD_Receitas[[#This Row],[Volume 1º Giro]])*BD_Receitas[[#This Row],[Tarifa 2º Giro]]) ) -> 0 | X36: =IF(BD_Receitas[[#This Row],[TIPO DE COBRANÇA]] <> "OPERAÇÃO NORMAL","", IF(BD_Receitas[[#This Row],[Vol. Movimentado M³]]= BD_Receitas[[#This Row],[Volume Mínimo ]], "Vol. Movimentado igual ao Vol. Mínimo", IF(ROUND(BD_Receitas[[#This Row],[Tarifa 1º Giro]],3) <> ROUND(BD_Receitas[[#This Row],[Tarifa Cobrada]],3), "Conferir tarifa cobrada", IF(BD_Receitas[[#This Row],[Volume Mínimo ]]=0,"Ok", IF(BD_Receitas[[#This Row],[Vol. Movimentado M³]]<= BD_Receitas[[#This Row],[Volume Mínimo ]], IF(ROUND(BD_Receitas[[#This Row],[Valor Total R$]],2) = ROUND(BD_Receitas[[#This Row],[Valor Total R$]],2), "Ok","Verificar Cobrança"), IF(ROUND(BD_Receitas[[#This Row],[Valor Contrato]],2) = ROUND(BD_Receitas[[#This Row],[Valor Movimentado]],2), "OK","Verificar cobrança") ))))) -> Conferir tarifa cobrada
A37: 1607 | B37: 45658 | C37: BRASILIA | D37: SAO PAULO | E37: PAULISTA | F37: 16 | G37: Guarulhos | H37: Ipiranga | I37: Outras Receitas | J37: 0 | K37: 0 | P37: =IF(BD_Receitas[[#This Row],[TIPO DE COBRANÇA]]="Operação Normal", _xlfn.XLOOKUP(BD_Receitas[[#This Row],[ID]],TabCondicoesComerciais[ID],TabCondicoesComerciais[Volume mínimo (m3)],0),"") | Q37: =_xlfn.XLOOKUP(BD_Receitas[[#This Row],[ID]],TabCondicoesComerciais[ID],TabCondicoesComerciais[Vol. 1ºGiro],0) -> 2000 | R37: =IF(BD_Receitas[[#This Row],[TIPO DE COBRANÇA]]="Avanço Espaço", _xlfn.XLOOKUP(BD_Receitas[[#This Row],[ID]],TabCondicoesComerciais[ID],TabCondicoesComerciais[Avanço Espaço],0), IF(BD_Receitas[[#This Row],[TIPO DE COBRANÇA]]="Avanço Horário", _xlfn.XLOOKUP(BD_Receitas[[#This Row],[ID]],TabCondicoesComerciais[ID],TabCondicoesComerciais[Avanço Horário],0), IF(BD_Receitas[[#This Row],[TIPO DE COBRANÇA]]="Operação Normal", _xlfn.XLOOKUP(BD_Receitas[[#This Row],[ID]],TabCondicoesComerciais[ID],TabCondicoesComerciais[Tarifa 1º Giro],0),0))) -> 0 | S37: =IF(BD_Receitas[[#This Row],[TIPO DE COBRANÇA]]="Operação Normal", _xlfn.XLOOKUP(BD_Receitas[[#This Row],[ID]],TabCondicoesComerciais[ID],TabCondicoesComerciais[Tarifa 2º Giro],0),0) -> 0 | T37: =IFERROR(IF(BD_Receitas[[#This Row],[TIPO DE COBRANÇA]]<>"Operação Normal","",BD_Receitas[[#This Row],[Valor Total R$]]/ MAX(BD_Receitas[[#This Row],[Vol. Movimentado M³]], BD_Receitas[[#This Row],[Volume Mínimo ]]) ),0) | U37: =IFERROR(IF(BD_Receitas[[#This Row],[TIPO DE COBRANÇA]]<>"Operação Normal","", SUMIFS(BD_Receitas[Valor Total R$],BD_Receitas[CONGENERE],BD_Receitas[[#This Row],[CONGENERE]],BD_Receitas[FILIAL],BD_Receitas[[#This Row],[FILIAL]],BD_Receitas[DATA CONTABIL],BD_Receitas[[#This Row],[DATA CONTABIL]]) /BD_Receitas[[#This Row],[Vol. Movimentado M³]] ),0) | V37: =IF(BD_Receitas[[#This Row],[TIPO DE COBRANÇA]]<>"Operação Normal","",(BD_Receitas[[#This Row],[Volume 1º Giro]]*BD_Receitas[[#This Row],[Tarifa 1º Giro]])+(BD_Receitas[[#This Row],[Volume Mínimo ]]-BD_Receitas[[#This Row],[Volume 1º Giro]])*BD_Receitas[[#This Row],[Tarifa 2º Giro]]) | W37: =IF(BD_Receitas[[#This Row],[TIPO DE COBRANÇA]]<>"OPERAÇÃO NORMAL","", IF(BD_Receitas[[#This Row],[Vol. Movimentado M³]]<BD_Receitas[[#This Row],[Volume 1º Giro]],BD_Receitas[[#This Row],[Vol. Movimentado M³]]* BD_Receitas[[#This Row],[Tarifa 1º Giro]], (BD_Receitas[[#This Row],[Volume 1º Giro]]*BD_Receitas[[#This Row],[Tarifa 1º Giro]])+(BD_Receitas[[#This Row],[Vol. Movimentado M³]]-BD_Receitas[[#This Row],[Volume 1º Giro]])*BD_Receitas[[#This Row],[Tarifa 2º Giro]]) ) | X37: =IF(BD_Receitas[[#This Row],[TIPO DE COBRANÇA]] <> "OPERAÇÃO NORMAL","", IF(BD_Receitas[[#This Row],[Vol. Movimentado M³]]= BD_Receitas[[#This Row],[Volume Mínimo ]], "Vol. Movimentado igual ao Vol. Mínimo", IF(ROUND(BD_Receitas[[#This Row],[Tarifa 1º Giro]],3) <> ROUND(BD_Receitas[[#This Row],[Tarifa Cobrada]],3), "Conferir tarifa cobrada", IF(BD_Receitas[[#This Row],[Volume Mínimo ]]=0,"Ok", IF(BD_Receitas[[#This Row],[Vol. Movimentado M³]]<= BD_Receitas[[#This Row],[Volume Mínimo ]], IF(ROUND(BD_Receitas[[#This Row],[Valor Total R$]],2) = ROUND(BD_Receitas[[#This Row],[Valor Total R$]],2), "Ok","Verificar Cobrança"), IF(ROUND(BD_Receitas[[#This Row],[Valor Contrato]],2) = ROUND(BD_Receitas[[#This Row],[Valor Movimentado]],2), "OK","Verificar cobrança") )))))
A38: 16203 | B38: 45658 | C38: BRASILIA | D38: SAO PAULO | E38: PAULISTA | F38: 16 | G38: Guarulhos | H38: Raízen | I38: Avanço Espaço | J38: 0 | K38: 0 | L38: 2876.193 | M38: 319.6 | N38: 364 | O38: Avanço de espaço | P38: =IF(BD_Receitas[[#This Row],[TIPO DE COBRANÇA]]="Operação Normal", _xlfn.XLOOKUP(BD_Receitas[[#This Row],[ID]],TabCondicoesComerciais[ID],TabCondicoesComerciais[Volume mínimo (m3)],0),"") | Q38: =_xlfn.XLOOKUP(BD_Receitas[[#This Row],[ID]],TabCondicoesComerciais[ID],TabCondicoesComerciais[Vol. 1ºGiro],0) -> 1175 | R38: =IF(BD_Receitas[[#This Row],[TIPO DE COBRANÇA]]="Avanço Espaço", _xlfn.XLOOKUP(BD_Receitas[[#This Row],[ID]],TabCondicoesComerciais[ID],TabCondicoesComerciais[Avanço Espaço],0), IF(BD_Receitas[[#This Row],[TIPO DE COBRANÇA]]="Avanço Horário", _xlfn.XLOOKUP(BD_Receitas[[#This Row],[ID]],TabCondicoesComerciais[ID],TabCondicoesComerciais[Avanço Horário],0), IF(BD_Receitas[[#This Row],[TIPO DE COBRANÇA]]="Operação Normal", _xlfn.XLOOKUP(BD_Receitas[[#This Row],[ID]],TabCondicoesComerciais[ID],TabCondicoesComerciais[Tarifa 1º Giro],0),0))) -> 9.948 | S38: =IF(BD_Receitas[[#This Row],[TIPO DE COBRANÇA]]="Operação Normal", _xlfn.XLOOKUP(BD_Receitas[[#This Row],[ID]],TabCondicoesComerciais[ID],TabCondicoesComerciais[Tarifa 2º Giro],0),0) -> 0 | T38: =IFERROR(IF(BD_Receitas[[#This Row],[TIPO DE COBRANÇA]]<>"Operação Normal","",BD_Receitas[[#This Row],[Valor Total R$]]/ MAX(BD_Receitas[[#This Row],[Vol. Movimentado M³]], BD_Receitas[[#This Row],[Volume Mínimo ]]) ),0) | U38: =IFERROR(IF(BD_Receitas[[#This Row],[TIPO DE COBRANÇA]]<>"Operação Normal","", SUMIFS(BD_Receitas[Valor Total R$],BD_Receitas[CONGENERE],BD_Receitas[[#This Row],[CONGENERE]],BD_Receitas[FILIAL],BD_Receitas[[#This Row],[FILIAL]],BD_Receitas[DATA CONTABIL],BD_Receitas[[#This Row],[DATA CONTABIL]]) /BD_Receitas[[#This Row],[Vol. Movimentado M³]] ),0) | V38: =IF(BD_Receitas[[#This Row],[TIPO DE COBRANÇA]]<>"Operação Normal","",(BD_Receitas[[#This Row],[Volume 1º Giro]]*BD_Receitas[[#This Row],[Tarifa 1º Giro]])+(BD_Receitas[[#This Row],[Volume Mínimo ]]-BD_Receitas[[#This Row],[Volume 1º Giro]])*BD_Receitas[[#This Row],[Tarifa 2º Giro]]) | W38: =IF(BD_Receitas[[#This Row],[TIPO DE COBRANÇA]]<>"OPERAÇÃO NORMAL","", IF(BD_Receitas[[#This Row],[Vol. Movimentado M³]]<BD_Receitas[[#This Row],[Volume 1º Giro]],BD_Receitas[[#This Row],[Vol. Movimentado M³]]* BD_Receitas[[#This Row],[Tarifa 1º Giro]], (BD_Receitas[[#This Row],[Volume 1º Giro]]*BD_Receitas[[#This Row],[Tarifa 1º Giro]])+(BD_Receitas[[#This Row],[Vol. Movimentado M³]]-BD_Receitas[[#This Row],[Volume 1º Giro]])*BD_Receitas[[#This Row],[Tarifa 2º Giro]]) ) | X38: =IF(BD_Receitas[[#This Row],[TIPO DE COBRANÇA]] <> "OPERAÇÃO NORMAL","", IF(BD_Receitas[[#This Row],[Vol. Movimentado M³]]= BD_Receitas[[#This Row],[Volume Mínimo ]], "Vol. Movimentado igual ao Vol. Mínimo", IF(ROUND(BD_Receitas[[#This Row],[Tarifa 1º Giro]],3) <> ROUND(BD_Receitas[[#This Row],[Tarifa Cobrada]],3), "Conferir tarifa cobrada", IF(BD_Receitas[[#This Row],[Volume Mínimo ]]=0,"Ok", IF(BD_Receitas[[#This Row],[Vol. Movimentado M³]]<= BD_Receitas[[#This Row],[Volume Mínimo ]], IF(ROUND(BD_Receitas[[#This Row],[Valor Total R$]],2) = ROUND(BD_Receitas[[#This Row],[Valor Total R$]],2), "Ok","Verificar Cobrança"), IF(ROUND(BD_Receitas[[#This Row],[Valor Contrato]],2) = ROUND(BD_Receitas[[#This Row],[Valor Movimentado]],2), "OK","Verificar cobrança") )))))
A39: 16203 | B39: 45658 | C39: BRASILIA | D39: SAO PAULO | E39: PAULISTA | F39: 16 | G39: Guarulhos | H39: Raízen | I39: Avanço Horário | J39: 0 | K39: 0 | P39: =IF(BD_Receitas[[#This Row],[TIPO DE COBRANÇA]]="Operação Normal", _xlfn.XLOOKUP(BD_Receitas[[#This Row],[ID]],TabCondicoesComerciais[ID],TabCondicoesComerciais[Volume mínimo (m3)],0),"") | Q39: =_xlfn.XLOOKUP(BD_Receitas[[#This Row],[ID]],TabCondicoesComerciais[ID],TabCondicoesComerciais[Vol. 1ºGiro],0) -> 1175 | R39: =IF(BD_Receitas[[#This Row],[TIPO DE COBRANÇA]]="Avanço Espaço", _xlfn.XLOOKUP(BD_Receitas[[#This Row],[ID]],TabCondicoesComerciais[ID],TabCondicoesComerciais[Avanço Espaço],0), IF(BD_Receitas[[#This Row],[TIPO DE COBRANÇA]]="Avanço Horário", _xlfn.XLOOKUP(BD_Receitas[[#This Row],[ID]],TabCondicoesComerciais[ID],TabCondicoesComerciais[Avanço Horário],0), IF(BD_Receitas[[#This Row],[TIPO DE COBRANÇA]]="Operação Normal", _xlfn.XLOOKUP(BD_Receitas[[#This Row],[ID]],TabCondicoesComerciais[ID],TabCondicoesComerciais[Tarifa 1º Giro],0),0))) -> 9 | S39: =IF(BD_Receitas[[#This Row],[TIPO DE COBRANÇA]]="Operação Normal", _xlfn.XLOOKUP(BD_Receitas[[#This Row],[ID]],TabCondicoesComerciais[ID],TabCondicoesComerciais[Tarifa 2º Giro],0),0) -> 0 | T39: =IFERROR(IF(BD_Receitas[[#This Row],[TIPO DE COBRANÇA]]<>"Operação Normal","",BD_Receitas[[#This Row],[Valor Total R$]]/ MAX(BD_Receitas[[#This Row],[Vol. Movimentado M³]], BD_Receitas[[#This Row],[Volume Mínimo ]]) ),0) | U39: =IFERROR(IF(BD_Receitas[[#This Row],[TIPO DE COBRANÇA]]<>"Operação Normal","", SUMIFS(BD_Receitas[Valor Total R$],BD_Receitas[CONGENERE],BD_Receitas[[#This Row],[CONGENERE]],BD_Receitas[FILIAL],BD_Receitas[[#This Row],[FILIAL]],BD_Receitas[DATA CONTABIL],BD_Receitas[[#This Row],[DATA CONTABIL]]) /BD_Receitas[[#This Row],[Vol. Movimentado M³]] ),0) | V39: =IF(BD_Receitas[[#This Row],[TIPO DE COBRANÇA]]<>"Operação Normal","",(BD_Receitas[[#This Row],[Volume 1º Giro]]*BD_Receitas[[#This Row],[Tarifa 1º Giro]])+(BD_Receitas[[#This Row],[Volume Mínimo ]]-BD_Receitas[[#This Row],[Volume 1º Giro]])*BD_Receitas[[#This Row],[Tarifa 2º Giro]]) | W39: =IF(BD_Receitas[[#This Row],[TIPO DE COBRANÇA]]<>"OPERAÇÃO NORMAL","", IF(BD_Receitas[[#This Row],[Vol. Movimentado M³]]<BD_Receitas[[#This Row],[Volume 1º Giro]],BD_Receitas[[#This Row],[Vol. Movimentado M³]]* BD_Receitas[[#This Row],[Tarifa 1º Giro]], (BD_Receitas[[#This Row],[Volume 1º Giro]]*BD_Receitas[[#This Row],[Tarifa 1º Giro]])+(BD_Receitas[[#This Row],[Vol. Movimentado M³]]-BD_Receitas[[#This Row],[Volume 1º Giro]])*BD_Receitas[[#This Row],[Tarifa 2º Giro]]) ) | X39: =IF(BD_Receitas[[#This Row],[TIPO DE COBRANÇA]] <> "OPERAÇÃO NORMAL","", IF(BD_Receitas[[#This Row],[Vol. Movimentado M³]]= BD_Receitas[[#This Row],[Volume Mínimo ]], "Vol. Movimentado igual ao Vol. Mínimo", IF(ROUND(BD_Receitas[[#This Row],[Tarifa 1º Giro]],3) <> ROUND(BD_Receitas[[#This Row],[Tarifa Cobrada]],3), "Conferir tarifa cobrada", IF(BD_Receitas[[#This Row],[Volume Mínimo ]]=0,"Ok", IF(BD_Receitas[[#This Row],[Vol. Movimentado M³]]<= BD_Receitas[[#This Row],[Volume Mínimo ]], IF(ROUND(BD_Receitas[[#This Row],[Valor Total R$]],2) = ROUND(BD_Receitas[[#This Row],[Valor Total R$]],2), "Ok","Verificar Cobrança"), IF(ROUND(BD_Receitas[[#This Row],[Valor Contrato]],2) = ROUND(BD_Receitas[[#This Row],[Valor Movimentado]],2), "OK","Verificar cobrança") )))))
A40: 16203 | B40: 45658 | C40: BRASILIA | D40: SAO PAULO | E40: PAULISTA | F40: 16 | G40: Guarulhos | H40: Raízen | I40: Operação Normal | J40: 164947.61 | K40: 6100 | L40: 152744 | M40: 4189 | N40: 364 | O40: Receita com armazenagem | P40: =IF(BD_Receitas[[#This Row],[TIPO DE COBRANÇA]]="Operação Normal", _xlfn.XLOOKUP(BD_Receitas[[#This Row],[ID]],TabCondicoesComerciais[ID],TabCondicoesComerciais[Volume mínimo (m3)],0),"") -> 6100 | Q40: =_xlfn.XLOOKUP(BD_Receitas[[#This Row],[ID]],TabCondicoesComerciais[ID],TabCondicoesComerciais[Vol. 1ºGiro],0) -> 1175 | R40: =IF(BD_Receitas[[#This Row],[TIPO DE COBRANÇA]]="Avanço Espaço", _xlfn.XLOOKUP(BD_Receitas[[#This Row],[ID]],TabCondicoesComerciais[ID],TabCondicoesComerciais[Avanço Espaço],0), IF(BD_Receitas[[#This Row],[TIPO DE COBRANÇA]]="Avanço Horário", _xlfn.XLOOKUP(BD_Receitas[[#This Row],[ID]],TabCondicoesComerciais[ID],TabCondicoesComerciais[Avanço Horário],0), IF(BD_Receitas[[#This Row],[TIPO DE COBRANÇA]]="Operação Normal", _xlfn.XLOOKUP(BD_Receitas[[#This Row],[ID]],TabCondicoesComerciais[ID],TabCondicoesComerciais[Tarifa 1º Giro],0),0))) -> 25.04 | S40: =IF(BD_Receitas[[#This Row],[TIPO DE COBRANÇA]]="Operação Normal", _xlfn.XLOOKUP(BD_Receitas[[#This Row],[ID]],TabCondicoesComerciais[ID],TabCondicoesComerciais[Tarifa 2º Giro],0),0) -> 25.04 | T40: =IFERROR(IF(BD_Receitas[[#This Row],[TIPO DE COBRANÇA]]<>"Operação Normal","",BD_Receitas[[#This Row],[Valor Total R$]]/ MAX(BD_Receitas[[#This Row],[Vol. Movimentado M³]], BD_Receitas[[#This Row],[Volume Mínimo ]]) ),0) -> 25.04 | U40: =IFERROR(IF(BD_Receitas[[#This Row],[TIPO DE COBRANÇA]]<>"Operação Normal","", SUMIFS(BD_Receitas[Valor Total R$],BD_Receitas[CONGENERE],BD_Receitas[[#This Row],[CONGENERE]],BD_Receitas[FILIAL],BD_Receitas[[#This Row],[FILIAL]],BD_Receitas[DATA CONTABIL],BD_Receitas[[#This Row],[DATA CONTABIL]]) /BD_Receitas[[#This Row],[Vol. Movimentado M³]] ),0) -> 37.149724 | V40: =IF(BD_Receitas[[#This Row],[TIPO DE COBRANÇA]]<>"Operação Normal","",(BD_Receitas[[#This Row],[Volume 1º Giro]]*BD_Receitas[[#This Row],[Tarifa 1º Giro]])+(BD_Receitas[[#This Row],[Volume Mínimo ]]-BD_Receitas[[#This Row],[Volume 1º Giro]])*BD_Receitas[[#This Row],[Tarifa 2º Giro]]) -> 152744 | W40: =IF(BD_Receitas[[#This Row],[TIPO DE COBRANÇA]]<>"OPERAÇÃO NORMAL","", IF(BD_Receitas[[#This Row],[Vol. Movimentado M³]]<BD_Receitas[[#This Row],[Volume 1º Giro]],BD_Receitas[[#This Row],[Vol. Movimentado M³]]* BD_Receitas[[#This Row],[Tarifa 1º Giro]], (BD_Receitas[[#This Row],[Volume 1º Giro]]*BD_Receitas[[#This Row],[Tarifa 1º Giro]])+(BD_Receitas[[#This Row],[Vol. Movimentado M³]]-BD_Receitas[[#This Row],[Volume 1º Giro]])*BD_Receitas[[#This Row],[Tarifa 2º Giro]]) ) -> 104892.56 | X40: =IF(BD_Receitas[[#This Row],[TIPO DE COBRANÇA]] <> "OPERAÇÃO NORMAL","", IF(BD_Receitas[[#This Row],[Vol. Movimentado M³]]= BD_Receitas[[#This Row],[Volume Mínimo ]], "Vol. Movimentado igual ao Vol. Mínimo", IF(ROUND(BD_Receitas[[#This Row],[Tarifa 1º Giro]],3) <> ROUND(BD_Receitas[[#This Row],[Tarifa Cobrada]],3), "Conferir tarifa cobrada", IF(BD_Receitas[[#This Row],[Volume Mínimo ]]=0,"Ok", IF(BD_Receitas[[#This Row],[Vol. Movimentado M³]]<= BD_Receitas[[#This Row],[Volume Mínimo ]], IF(ROUND(BD_Receitas[[#This Row],[Valor Total R$]],2) = ROUND(BD_Receitas[[#This Row],[Valor Total R$]],2), "Ok","Verificar Cobrança"), IF(ROUND(BD_Receitas[[#This Row],[Valor Contrato]],2) = ROUND(BD_Receitas[[#This Row],[Valor Movimentado]],2), "OK","Verificar cobrança") ))))) -> Ok
A41: 16203 | B41: 45658 | C41: BRASILIA | D41: SAO PAULO | E41: PAULISTA | F41: 16 | G41: Guarulhos | H41: Raízen | I41: Outras Receitas | J41: 0 | K41: 0 | P41: =IF(BD_Receitas[[#This Row],[TIPO DE COBRANÇA]]="Operação Normal", _xlfn.XLOOKUP(BD_Receitas[[#This Row],[ID]],TabCondicoesComerciais[ID],TabCondicoesComerciais[Volume mínimo (m3)],0),"") | Q41: =_xlfn.XLOOKUP(BD_Receitas[[#This Row],[ID]],TabCondicoesComerciais[ID],TabCondicoesComerciais[Vol. 1ºGiro],0) -> 1175 | R41: =IF(BD_Receitas[[#This Row],[TIPO DE COBRANÇA]]="Avanço Espaço", _xlfn.XLOOKUP(BD_Receitas[[#This Row],[ID]],TabCondicoesComerciais[ID],TabCondicoesComerciais[Avanço Espaço],0), IF(BD_Receitas[[#This Row],[TIPO DE COBRANÇA]]="Avanço Horário", _xlfn.XLOOKUP(BD_Receitas[[#This Row],[ID]],TabCondicoesComerciais[ID],TabCondicoesComerciais[Avanço Horário],0), IF(BD_Receitas[[#This Row],[TIPO DE COBRANÇA]]="Operação Normal", _xlfn.XLOOKUP(BD_Receitas[[#This Row],[ID]],TabCondicoesComerciais[ID],TabCondicoesComerciais[Tarifa 1º Giro],0),0))) -> 0 | S41: =IF(BD_Receitas[[#This Row],[TIPO DE COBRANÇA]]="Operação Normal", _xlfn.XLOOKUP(BD_Receitas[[#This Row],[ID]],TabCondicoesComerciais[ID],TabCondicoesComerciais[Tarifa 2º Giro],0),0) -> 0 | T41: =IFERROR(IF(BD_Receitas[[#This Row],[TIPO DE COBRANÇA]]<>"Operação Normal","",BD_Receitas[[#This Row],[Valor Total R$]]/ MAX(BD_Receitas[[#This Row],[Vol. Movimentado M³]], BD_Receitas[[#This Row],[Volume Mínimo ]]) ),0) | U41: =IFERROR(IF(BD_Receitas[[#This Row],[TIPO DE COBRANÇA]]<>"Operação Normal","", SUMIFS(BD_Receitas[Valor Total R$],BD_Receitas[CONGENERE],BD_Receitas[[#This Row],[CONGENERE]],BD_Receitas[FILIAL],BD_Receitas[[#This Row],[FILIAL]],BD_Receitas[DATA CONTABIL],BD_Receitas[[#This Row],[DATA CONTABIL]]) /BD_Receitas[[#This Row],[Vol. Movimentado M³]] ),0) | V41: =IF(BD_Receitas[[#This Row],[TIPO DE COBRANÇA]]<>"Operação Normal","",(BD_Receitas[[#This Row],[Volume 1º Giro]]*BD_Receitas[[#This Row],[Tarifa 1º Giro]])+(BD_Receitas[[#This Row],[Volume Mínimo ]]-BD_Receitas[[#This Row],[Volume 1º Giro]])*BD_Receitas[[#This Row],[Tarifa 2º Giro]]) | W41: =IF(BD_Receitas[[#This Row],[TIPO DE COBRANÇA]]<>"OPERAÇÃO NORMAL","", IF(BD_Receitas[[#This Row],[Vol. Movimentado M³]]<BD_Receitas[[#This Row],[Volume 1º Giro]],BD_Receitas[[#This Row],[Vol. Movimentado M³]]* BD_Receitas[[#This Row],[Tarifa 1º Giro]], (BD_Receitas[[#This Row],[Volume 1º Giro]]*BD_Receitas[[#This Row],[Tarifa 1º Giro]])+(BD_Receitas[[#This Row],[Vol. Movimentado M³]]-BD_Receitas[[#This Row],[Volume 1º Giro]])*BD_Receitas[[#This Row],[Tarifa 2º Giro]]) ) | X41: =IF(BD_Receitas[[#This Row],[TIPO DE COBRANÇA]] <> "OPERAÇÃO NORMAL","", IF(BD_Receitas[[#This Row],[Vol. Movimentado M³]]= BD_Receitas[[#This Row],[Volume Mínimo ]], "Vol. Movimentado igual ao Vol. Mínimo", IF(ROUND(BD_Receitas[[#This Row],[Tarifa 1º Giro]],3) <> ROUND(BD_Receitas[[#This Row],[Tarifa Cobrada]],3), "Conferir tarifa cobrada", IF(BD_Receitas[[#This Row],[Volume Mínimo ]]=0,"Ok", IF(BD_Receitas[[#This Row],[Vol. Movimentado M³]]<= BD_Receitas[[#This Row],[Volume Mínimo ]], IF(ROUND(BD_Receitas[[#This Row],[Valor Total R$]],2) = ROUND(BD_Receitas[[#This Row],[Valor Total R$]],2), "Ok","Verificar Cobrança"), IF(ROUND(BD_Receitas[[#This Row],[Valor Contrato]],2) = ROUND(BD_Receitas[[#This Row],[Valor Movimentado]],2), "OK","Verificar cobrança") )))))
A42: 49102 | B42: 45658 | C42: BRASILIA | D42: GUAMARE | E42: BAIANO | F42: 49 | G42: Luis Eduardo Magalhães | H42: Ipiranga | I42: Avanço Espaço | J42: 0 | K42: 0 | P42: =IF(BD_Receitas[[#This Row],[TIPO DE COBRANÇA]]="Operação Normal", _xlfn.XLOOKUP(BD_Receitas[[#This Row],[ID]],TabCondicoesComerciais[ID],TabCondicoesComerciais[Volume mínimo (m3)],0),"") | Q42: =_xlfn.XLOOKUP(BD_Receitas[[#This Row],[ID]],TabCondicoesComerciais[ID],TabCondicoesComerciais[Vol. 1ºGiro],0) -> 310 | R42: =IF(BD_Receitas[[#This Row],[TIPO DE COBRANÇA]]="Avanço Espaço", _xlfn.XLOOKUP(BD_Receitas[[#This Row],[ID]],TabCondicoesComerciais[ID],TabCondicoesComerciais[Avanço Espaço],0), IF(BD_Receitas[[#This Row],[TIPO DE COBRANÇA]]="Avanço Horário", _xlfn.XLOOKUP(BD_Receitas[[#This Row],[ID]],TabCondicoesComerciais[ID],TabCondicoesComerciais[Avanço Horário],0), IF(BD_Receitas[[#This Row],[TIPO DE COBRANÇA]]="Operação Normal", _xlfn.XLOOKUP(BD_Receitas[[#This Row],[ID]],TabCondicoesComerciais[ID],TabCondicoesComerciais[Tarifa 1º Giro],0),0))) -> 0 | S42: =IF(BD_Receitas[[#This Row],[TIPO DE COBRANÇA]]="Operação Normal", _xlfn.XLOOKUP(BD_Receitas[[#This Row],[ID]],TabCondicoesComerciais[ID],TabCondicoesComerciais[Tarifa 2º Giro],0),0) -> 0 | T42: =IFERROR(IF(BD_Receitas[[#This Row],[TIPO DE COBRANÇA]]<>"Operação Normal","",BD_Receitas[[#This Row],[Valor Total R$]]/ MAX(BD_Receitas[[#This Row],[Vol. Movimentado M³]], BD_Receitas[[#This Row],[Volume Mínimo ]]) ),0) | U42: =IFERROR(IF(BD_Receitas[[#This Row],[TIPO DE COBRANÇA]]<>"Operação Normal","", SUMIFS(BD_Receitas[Valor Total R$],BD_Receitas[CONGENERE],BD_Receitas[[#This Row],[CONGENERE]],BD_Receitas[FILIAL],BD_Receitas[[#This Row],[FILIAL]],BD_Receitas[DATA CONTABIL],BD_Receitas[[#This Row],[DATA CONTABIL]]) /BD_Receitas[[#This Row],[Vol. Movimentado M³]] ),0) | V42: =IF(BD_Receitas[[#This Row],[TIPO DE COBRANÇA]]<>"Operação Normal","",(BD_Receitas[[#This Row],[Volume 1º Giro]]*BD_Receitas[[#This Row],[Tarifa 1º Giro]])+(BD_Receitas[[#This Row],[Volume Mínimo ]]-BD_Receitas[[#This Row],[Volume 1º Giro]])*BD_Receitas[[#This Row],[Tarifa 2º Giro]]) | W42: =IF(BD_Receitas[[#This Row],[TIPO DE COBRANÇA]]<>"OPERAÇÃO NORMAL","", IF(BD_Receitas[[#This Row],[Vol. Movimentado M³]]<BD_Receitas[[#This Row],[Volume 1º Giro]],BD_Receitas[[#This Row],[Vol. Movimentado M³]]* BD_Receitas[[#This Row],[Tarifa 1º Giro]], (BD_Receitas[[#This Row],[Volume 1º Giro]]*BD_Receitas[[#This Row],[Tarifa 1º Giro]])+(BD_Receitas[[#This Row],[Vol. Movimentado M³]]-BD_Receitas[[#This Row],[Volume 1º Giro]])*BD_Receitas[[#This Row],[Tarifa 2º Giro]]) ) | X42: =IF(BD_Receitas[[#This Row],[TIPO DE COBRANÇA]] <> "OPERAÇÃO NORMAL","", IF(BD_Receitas[[#This Row],[Vol. Movimentado M³]]= BD_Receitas[[#This Row],[Volume Mínimo ]], "Vol. Movimentado igual ao Vol. Mínimo", IF(ROUND(BD_Receitas[[#This Row],[Tarifa 1º Giro]],3) <> ROUND(BD_Receitas[[#This Row],[Tarifa Cobrada]],3), "Conferir tarifa cobrada", IF(BD_Receitas[[#This Row],[Volume Mínimo ]]=0,"Ok", IF(BD_Receitas[[#This Row],[Vol. Movimentado M³]]<= BD_Receitas[[#This Row],[Volume Mínimo ]], IF(ROUND(BD_Receitas[[#This Row],[Valor Total R$]],2) = ROUND(BD_Receitas[[#This Row],[Valor Total R$]],2), "Ok","Verificar Cobrança"), IF(ROUND(BD_Receitas[[#This Row],[Valor Contrato]],2) = ROUND(BD_Receitas[[#This Row],[Valor Movimentado]],2), "OK","Verificar cobrança") )))))
A43: 49102 | B43: 45658 | C43: BRASILIA | D43: GUAMARE | E43: BAIANO | F43: 49 | G43: Luis Eduardo Magalhães | H43: Ipiranga | I43: Avanço Horário | J43: 0 | K43: 0 | P43: =IF(BD_Receitas[[#This Row],[TIPO DE COBRANÇA]]="Operação Normal", _xlfn.XLOOKUP(BD_Receitas[[#This Row],[ID]],TabCondicoesComerciais[ID],TabCondicoesComerciais[Volume mínimo (m3)],0),"") | Q43: =_xlfn.XLOOKUP(BD_Receitas[[#This Row],[ID]],TabCondicoesComerciais[ID],TabCondicoesComerciais[Vol. 1ºGiro],0) -> 310 | R43: =IF(BD_Receitas[[#This Row],[TIPO DE COBRANÇA]]="Avanço Espaço", _xlfn.XLOOKUP(BD_Receitas[[#This Row],[ID]],TabCondicoesComerciais[ID],TabCondicoesComerciais[Avanço Espaço],0), IF(BD_Receitas[[#This Row],[TIPO DE COBRANÇA]]="Avanço Horário", _xlfn.XLOOKUP(BD_Receitas[[#This Row],[ID]],TabCondicoesComerciais[ID],TabCondicoesComerciais[Avanço Horário],0), IF(BD_Receitas[[#This Row],[TIPO DE COBRANÇA]]="Operação Normal", _xlfn.XLOOKUP(BD_Receitas[[#This Row],[ID]],TabCondicoesComerciais[ID],TabCondicoesComerciais[Tarifa 1º Giro],0),0))) -> 12.41 | S43: =IF(BD_Receitas[[#This Row],[TIPO DE COBRANÇA]]="Operação Normal", _xlfn.XLOOKUP(BD_Receitas[[#This Row],[ID]],TabCondicoesComerciais[ID],TabCondicoesComerciais[Tarifa 2º Giro],0),0) -> 0 | T43: =IFERROR(IF(BD_Receitas[[#This Row],[TIPO DE COBRANÇA]]<>"Operação Normal","",BD_Receitas[[#This Row],[Valor Total R$]]/ MAX(BD_Receitas[[#This Row],[Vol. Movimentado M³]], BD_Receitas[[#This Row],[Volume Mínimo ]]) ),0) | U43: =IFERROR(IF(BD_Receitas[[#This Row],[TIPO DE COBRANÇA]]<>"Operação Normal","", SUMIFS(BD_Receitas[Valor Total R$],BD_Receitas[CONGENERE],BD_Receitas[[#This Row],[CONGENERE]],BD_Receitas[FILIAL],BD_Receitas[[#This Row],[FILIAL]],BD_Receitas[DATA CONTABIL],BD_Receitas[[#This Row],[DATA CONTABIL]]) /BD_Receitas[[#This Row],[Vol. Movimentado M³]] ),0) | V43: =IF(BD_Receitas[[#This Row],[TIPO DE COBRANÇA]]<>"Operação Normal","",(BD_Receitas[[#This Row],[Volume 1º Giro]]*BD_Receitas[[#This Row],[Tarifa 1º Giro]])+(BD_Receitas[[#This Row],[Volume Mínimo ]]-BD_Receitas[[#This Row],[Volume 1º Giro]])*BD_Receitas[[#This Row],[Tarifa 2º Giro]]) | W43: =IF(BD_Receitas[[#This Row],[TIPO DE COBRANÇA]]<>"OPERAÇÃO NORMAL","", IF(BD_Receitas[[#This Row],[Vol. Movimentado M³]]<BD_Receitas[[#This Row],[Volume 1º Giro]],BD_Receitas[[#This Row],[Vol. Movimentado M³]]* BD_Receitas[[#This Row],[Tarifa 1º Giro]], (BD_Receitas[[#This Row],[Volume 1º Giro]]*BD_Receitas[[#This Row],[Tarifa 1º Giro]])+(BD_Receitas[[#This Row],[Vol. Movimentado M³]]-BD_Receitas[[#This Row],[Volume 1º Giro]])*BD_Receitas[[#This Row],[Tarifa 2º Giro]]) ) | X43: =IF(BD_Receitas[[#This Row],[TIPO DE COBRANÇA]] <> "OPERAÇÃO NORMAL","", IF(BD_Receitas[[#This Row],[Vol. Movimentado M³]]= BD_Receitas[[#This Row],[Volume Mínimo ]], "Vol. Movimentado igual ao Vol. Mínimo", IF(ROUND(BD_Receitas[[#This Row],[Tarifa 1º Giro]],3) <> ROUND(BD_Receitas[[#This Row],[Tarifa Cobrada]],3), "Conferir tarifa cobrada", IF(BD_Receitas[[#This Row],[Volume Mínimo ]]=0,"Ok", IF(BD_Receitas[[#This Row],[Vol. Movimentado M³]]<= BD_Receitas[[#This Row],[Volume Mínimo ]], IF(ROUND(BD_Receitas[[#This Row],[Valor Total R$]],2) = ROUND(BD_Receitas[[#This Row],[Valor Total R$]],2), "Ok","Verificar Cobrança"), IF(ROUND(BD_Receitas[[#This Row],[Valor Contrato]],2) = ROUND(BD_Receitas[[#This Row],[Valor Movimentado]],2), "OK","Verificar cobrança") )))))
A44: 49102 | B44: 45658 | C44: BRASILIA | D44: GUAMARE | E44: BAIANO | F44: 49 | G44: Luis Eduardo Magalhães | H44: Ipiranga | I44: Operação Normal | J44: 16703.077 | K44: 550 | L44: 32571 | M44: 921 | N44: 102 | P44: =IF(BD_Receitas[[#This Row],[TIPO DE COBRANÇA]]="Operação Normal", _xlfn.XLOOKUP(BD_Receitas[[#This Row],[ID]],TabCondicoesComerciais[ID],TabCondicoesComerciais[Volume mínimo (m3)],0),"") -> 1100 | Q44: =_xlfn.XLOOKUP(BD_Receitas[[#This Row],[ID]],TabCondicoesComerciais[ID],TabCondicoesComerciais[Vol. 1ºGiro],0) -> 310 | R44: =IF(BD_Receitas[[#This Row],[TIPO DE COBRANÇA]]="Avanço Espaço", _xlfn.XLOOKUP(BD_Receitas[[#This Row],[ID]],TabCondicoesComerciais[ID],TabCondicoesComerciais[Avanço Espaço],0), IF(BD_Receitas[[#This Row],[TIPO DE COBRANÇA]]="Avanço Horário", _xlfn.XLOOKUP(BD_Receitas[[#This Row],[ID]],TabCondicoesComerciais[ID],TabCondicoesComerciais[Avanço Horário],0), IF(BD_Receitas[[#This Row],[TIPO DE COBRANÇA]]="Operação Normal", _xlfn.XLOOKUP(BD_Receitas[[#This Row],[ID]],TabCondicoesComerciais[ID],TabCondicoesComerciais[Tarifa 1º Giro],0),0))) -> 31.04 | S44: =IF(BD_Receitas[[#This Row],[TIPO DE COBRANÇA]]="Operação Normal", _xlfn.XLOOKUP(BD_Receitas[[#This Row],[ID]],TabCondicoesComerciais[ID],TabCondicoesComerciais[Tarifa 2º Giro],0),0) -> 31.04 | T44: =IFERROR(IF(BD_Receitas[[#This Row],[TIPO DE COBRANÇA]]<>"Operação Normal","",BD_Receitas[[#This Row],[Valor Total R$]]/ MAX(BD_Receitas[[#This Row],[Vol. Movimentado M³]], BD_Receitas[[#This Row],[Volume Mínimo ]]) ),0) -> 29.61 | U44: =IFERROR(IF(BD_Receitas[[#This Row],[TIPO DE COBRANÇA]]<>"Operação Normal","", SUMIFS(BD_Receitas[Valor Total R$],BD_Receitas[CONGENERE],BD_Receitas[[#This Row],[CONGENERE]],BD_Receitas[FILIAL],BD_Receitas[[#This Row],[FILIAL]],BD_Receitas[DATA CONTABIL],BD_Receitas[[#This Row],[DATA CONTABIL]]) /BD_Receitas[[#This Row],[Vol. Movimentado M³]] ),0) -> 35.364821 | V44: =IF(BD_Receitas[[#This Row],[TIPO DE COBRANÇA]]<>"Operação Normal","",(BD_Receitas[[#This Row],[Volume 1º Giro]]*BD_Receitas[[#This Row],[Tarifa 1º Giro]])+(BD_Receitas[[#This Row],[Volume Mínimo ]]-BD_Receitas[[#This Row],[Volume 1º Giro]])*BD_Receitas[[#This Row],[Tarifa 2º Giro]]) -> 34144 | W44: =IF(BD_Receitas[[#This Row],[TIPO DE COBRANÇA]]<>"OPERAÇÃO NORMAL","", IF(BD_Receitas[[#This Row],[Vol. Movimentado M³]]<BD_Receitas[[#This Row],[Volume 1º Giro]],BD_Receitas[[#This Row],[Vol. Movimentado M³]]* BD_Receitas[[#This Row],[Tarifa 1º Giro]], (BD_Receitas[[#This Row],[Volume 1º Giro]]*BD_Receitas[[#This Row],[Tarifa 1º Giro]])+(BD_Receitas[[#This Row],[Vol. Movimentado M³]]-BD_Receitas[[#This Row],[Volume 1º Giro]])*BD_Receitas[[#This Row],[Tarifa 2º Giro]]) ) -> 28587.84 | X44: =IF(BD_Receitas[[#This Row],[TIPO DE COBRANÇA]] <> "OPERAÇÃO NORMAL","", IF(BD_Receitas[[#This Row],[Vol. Movimentado M³]]= BD_Receitas[[#This Row],[Volume Mínimo ]], "Vol. Movimentado igual ao Vol. Mínimo", IF(ROUND(BD_Receitas[[#This Row],[Tarifa 1º Giro]],3) <> ROUND(BD_Receitas[[#This Row],[Tarifa Cobrada]],3), "Conferir tarifa cobrada", IF(BD_Receitas[[#This Row],[Volume Mínimo ]]=0,"Ok", IF(BD_Receitas[[#This Row],[Vol. Movimentado M³]]<= BD_Receitas[[#This Row],[Volume Mínimo ]], IF(ROUND(BD_Receitas[[#This Row],[Valor Total R$]],2) = ROUND(BD_Receitas[[#This Row],[Valor Total R$]],2), "Ok","Verificar Cobrança"), IF(ROUND(BD_Receitas[[#This Row],[Valor Contrato]],2) = ROUND(BD_Receitas[[#This Row],[Valor Movimentado]],2), "OK","Verificar cobrança") ))))) -> Conferir tarifa cobrada
A45: 49102 | B45: 45658 | C45: BRASILIA | D45: GUAMARE | E45: BAIANO | F45: 49 | G45: Luis Eduardo Magalhães | H45: Ipiranga | I45: Outras Receitas | J45: 0 | K45: 0 | P45: =IF(BD_Receitas[[#This Row],[TIPO DE COBRANÇA]]="Operação Normal", _xlfn.XLOOKUP(BD_Receitas[[#This Row],[ID]],TabCondicoesComerciais[ID],TabCondicoesComerciais[Volume mínimo (m3)],0),"") | Q45: =_xlfn.XLOOKUP(BD_Receitas[[#This Row],[ID]],TabCondicoesComerciais[ID],TabCondicoesComerciais[Vol. 1ºGiro],0) -> 310 | R45: =IF(BD_Receitas[[#This Row],[TIPO DE COBRANÇA]]="Avanço Espaço", _xlfn.XLOOKUP(BD_Receitas[[#This Row],[ID]],TabCondicoesComerciais[ID],TabCondicoesComerciais[Avanço Espaço],0), IF(BD_Receitas[[#This Row],[TIPO DE COBRANÇA]]="Avanço Horário", _xlfn.XLOOKUP(BD_Receitas[[#This Row],[ID]],TabCondicoesComerciais[ID],TabCondicoesComerciais[Avanço Horário],0), IF(BD_Receitas[[#This Row],[TIPO DE COBRANÇA]]="Operação Normal", _xlfn.XLOOKUP(BD_Receitas[[#This Row],[ID]],TabCondicoesComerciais[ID],TabCondicoesComerciais[Tarifa 1º Giro],0),0))) -> 0 | S45: =IF(BD_Receitas[[#This Row],[TIPO DE COBRANÇA]]="Operação Normal", _xlfn.XLOOKUP(BD_Receitas[[#This Row],[ID]],TabCondicoesComerciais[ID],TabCondicoesComerciais[Tarifa 2º Giro],0),0) -> 0 | T45: =IFERROR(IF(BD_Receitas[[#This Row],[TIPO DE COBRANÇA]]<>"Operação Normal","",BD_Receitas[[#This Row],[Valor Total R$]]/ MAX(BD_Receitas[[#This Row],[Vol. Movimentado M³]], BD_Receitas[[#This Row],[Volume Mínimo ]]) ),0) | U45: =IFERROR(IF(BD_Receitas[[#This Row],[TIPO DE COBRANÇA]]<>"Operação Normal","", SUMIFS(BD_Receitas[Valor Total R$],BD_Receitas[CONGENERE],BD_Receitas[[#This Row],[CONGENERE]],BD_Receitas[FILIAL],BD_Receitas[[#This Row],[FILIAL]],BD_Receitas[DATA CONTABIL],BD_Receitas[[#This Row],[DATA CONTABIL]]) /BD_Receitas[[#This Row],[Vol. Movimentado M³]] ),0) | V45: =IF(BD_Receitas[[#This Row],[TIPO DE COBRANÇA]]<>"Operação Normal","",(BD_Receitas[[#This Row],[Volume 1º Giro]]*BD_Receitas[[#This Row],[Tarifa 1º Giro]])+(BD_Receitas[[#This Row],[Volume Mínimo ]]-BD_Receitas[[#This Row],[Volume 1º Giro]])*BD_Receitas[[#This Row],[Tarifa 2º Giro]]) | W45: =IF(BD_Receitas[[#This Row],[TIPO DE COBRANÇA]]<>"OPERAÇÃO NORMAL","", IF(BD_Receitas[[#This Row],[Vol. Movimentado M³]]<BD_Receitas[[#This Row],[Volume 1º Giro]],BD_Receitas[[#This Row],[Vol. Movimentado M³]]* BD_Receitas[[#This Row],[Tarifa 1º Giro]], (BD_Receitas[[#This Row],[Volume 1º Giro]]*BD_Receitas[[#This Row],[Tarifa 1º Giro]])+(BD_Receitas[[#This Row],[Vol. Movimentado M³]]-BD_Receitas[[#This Row],[Volume 1º Giro]])*BD_Receitas[[#This Row],[Tarifa 2º Giro]]) ) | X45: =IF(BD_Receitas[[#This Row],[TIPO DE COBRANÇA]] <> "OPERAÇÃO NORMAL","", IF(BD_Receitas[[#This Row],[Vol. Movimentado M³]]= BD_Receitas[[#This Row],[Volume Mínimo ]], "Vol. Movimentado igual ao Vol. Mínimo", IF(ROUND(BD_Receitas[[#This Row],[Tarifa 1º Giro]],3) <> ROUND(BD_Receitas[[#This Row],[Tarifa Cobrada]],3), "Conferir tarifa cobrada", IF(BD_Receitas[[#This Row],[Volume Mínimo ]]=0,"Ok", IF(BD_Receitas[[#This Row],[Vol. Movimentado M³]]<= BD_Receitas[[#This Row],[Volume Mínimo ]], IF(ROUND(BD_Receitas[[#This Row],[Valor Total R$]],2) = ROUND(BD_Receitas[[#This Row],[Valor Total R$]],2), "Ok","Verificar Cobrança"), IF(ROUND(BD_Receitas[[#This Row],[Valor Contrato]],2) = ROUND(BD_Receitas[[#This Row],[Valor Movimentado]],2), "OK","Verificar cobrança") )))))
A46: 49206 | B46: 45658 | C46: BRASILIA | D46: GUAMARE | E46: BAIANO | F46: 49 | G46: Luis Eduardo Magalhães | H46: Vibra | I46: Avanço Espaço | J46: 0 | K46: 0 | P46: =IF(BD_Receitas[[#This Row],[TIPO DE COBRANÇA]]="Operação Normal", _xlfn.XLOOKUP(BD_Receitas[[#This Row],[ID]],TabCondicoesComerciais[ID],TabCondicoesComerciais[Volume mínimo (m3)],0),"") | Q46: =_xlfn.XLOOKUP(BD_Receitas[[#This Row],[ID]],TabCondicoesComerciais[ID],TabCondicoesComerciais[Vol. 1ºGiro],0) -> 1070 | R46: =IF(BD_Receitas[[#This Row],[TIPO DE COBRANÇA]]="Avanço Espaço", _xlfn.XLOOKUP(BD_Receitas[[#This Row],[ID]],TabCondicoesComerciais[ID],TabCondicoesComerciais[Avanço Espaço],0), IF(BD_Receitas[[#This Row],[TIPO DE COBRANÇA]]="Avanço Horário", _xlfn.XLOOKUP(BD_Receitas[[#This Row],[ID]],TabCondicoesComerciais[ID],TabCondicoesComerciais[Avanço Horário],0), IF(BD_Receitas[[#This Row],[TIPO DE COBRANÇA]]="Operação Normal", _xlfn.XLOOKUP(BD_Receitas[[#This Row],[ID]],TabCondicoesComerciais[ID],TabCondicoesComerciais[Tarifa 1º Giro],0),0))) -> 0 | S46: =IF(BD_Receitas[[#This Row],[TIPO DE COBRANÇA]]="Operação Normal", _xlfn.XLOOKUP(BD_Receitas[[#This Row],[ID]],TabCondicoesComerciais[ID],TabCondicoesComerciais[Tarifa 2º Giro],0),0) -> 0 | T46: =IFERROR(IF(BD_Receitas[[#This Row],[TIPO DE COBRANÇA]]<>"Operação Normal","",BD_Receitas[[#This Row],[Valor Total R$]]/ MAX(BD_Receitas[[#This Row],[Vol. Movimentado M³]], BD_Receitas[[#This Row],[Volume Mínimo ]]) ),0) | U46: =IFERROR(IF(BD_Receitas[[#This Row],[TIPO DE COBRANÇA]]<>"Operação Normal","", SUMIFS(BD_Receitas[Valor Total R$],BD_Receitas[CONGENERE],BD_Receitas[[#This Row],[CONGENERE]],BD_Receitas[FILIAL],BD_Receitas[[#This Row],[FILIAL]],BD_Receitas[DATA CONTABIL],BD_Receitas[[#This Row],[DATA CONTABIL]]) /BD_Receitas[[#This Row],[Vol. Movimentado M³]] ),0) | V46: =IF(BD_Receitas[[#This Row],[TIPO DE COBRANÇA]]<>"Operação Normal","",(BD_Receitas[[#This Row],[Volume 1º Giro]]*BD_Receitas[[#This Row],[Tarifa 1º Giro]])+(BD_Receitas[[#This Row],[Volume Mínimo ]]-BD_Receitas[[#This Row],[Volume 1º Giro]])*BD_Receitas[[#This Row],[Tarifa 2º Giro]]) | W46: =IF(BD_Receitas[[#This Row],[TIPO DE COBRANÇA]]<>"OPERAÇÃO NORMAL","", IF(BD_Receitas[[#This Row],[Vol. Movimentado M³]]<BD_Receitas[[#This Row],[Volume 1º Giro]],BD_Receitas[[#This Row],[Vol. Movimentado M³]]* BD_Receitas[[#This Row],[Tarifa 1º Giro]], (BD_Receitas[[#This Row],[Volume 1º Giro]]*BD_Receitas[[#This Row],[Tarifa 1º Giro]])+(BD_Receitas[[#This Row],[Vol. Movimentado M³]]-BD_Receitas[[#This Row],[Volume 1º Giro]])*BD_Receitas[[#This Row],[Tarifa 2º Giro]]) ) | X46: =IF(BD_Receitas[[#This Row],[TIPO DE COBRANÇA]] <> "OPERAÇÃO NORMAL","", IF(BD_Receitas[[#This Row],[Vol. Movimentado M³]]= BD_Receitas[[#This Row],[Volume Mínimo ]], "Vol. Movimentado igual ao Vol. Mínimo", IF(ROUND(BD_Receitas[[#This Row],[Tarifa 1º Giro]],3) <> ROUND(BD_Receitas[[#This Row],[Tarifa Cobrada]],3), "Conferir tarifa cobrada", IF(BD_Receitas[[#This Row],[Volume Mínimo ]]=0,"Ok", IF(BD_Receitas[[#This Row],[Vol. Movimentado M³]]<= BD_Receitas[[#This Row],[Volume Mínimo ]], IF(ROUND(BD_Receitas[[#This Row],[Valor Total R$]],2) = ROUND(BD_Receitas[[#This Row],[Valor Total R$]],2), "Ok","Verificar Cobrança"), IF(ROUND(BD_Receitas[[#This Row],[Valor Contrato]],2) = ROUND(BD_Receitas[[#This Row],[Valor Movimentado]],2), "OK","Verificar cobrança") )))))
A47: 49206 | B47: 45658 | C47: BRASILIA | D47: GUAMARE | E47: BAIANO | F47: 49 | G47: Luis Eduardo Magalhães | H47: Vibra | I47: Avanço Horário | J47: 0 | K47: 0 | P47: =IF(BD_Receitas[[#This Row],[TIPO DE COBRANÇA]]="Operação Normal", _xlfn.XLOOKUP(BD_Receitas[[#This Row],[ID]],TabCondicoesComerciais[ID],TabCondicoesComerciais[Volume mínimo (m3)],0),"") | Q47: =_xlfn.XLOOKUP(BD_Receitas[[#This Row],[ID]],TabCondicoesComerciais[ID],TabCondicoesComerciais[Vol. 1ºGiro],0) -> 1070 | R47: =IF(BD_Receitas[[#This Row],[TIPO DE COBRANÇA]]="Avanço Espaço", _xlfn.XLOOKUP(BD_Receitas[[#This Row],[ID]],TabCondicoesComerciais[ID],TabCondicoesComerciais[Avanço Espaço],0), IF(BD_Receitas[[#This Row],[TIPO DE COBRANÇA]]="Avanço Horário", _xlfn.XLOOKUP(BD_Receitas[[#This Row],[ID]],TabCondicoesComerciais[ID],TabCondicoesComerciais[Avanço Horário],0), IF(BD_Receitas[[#This Row],[TIPO DE COBRANÇA]]="Operação Normal", _xlfn.XLOOKUP(BD_Receitas[[#This Row],[ID]],TabCondicoesComerciais[ID],TabCondicoesComerciais[Tarifa 1º Giro],0),0))) -> 0 | S47: =IF(BD_Receitas[[#This Row],[TIPO DE COBRANÇA]]="Operação Normal", _xlfn.XLOOKUP(BD_Receitas[[#This Row],[ID]],TabCondicoesComerciais[ID],TabCondicoesComerciais[Tarifa 2º Giro],0),0) -> 0 | T47: =IFERROR(IF(BD_Receitas[[#This Row],[TIPO DE COBRANÇA]]<>"Operação Normal","",BD_Receitas[[#This Row],[Valor Total R$]]/ MAX(BD_Receitas[[#This Row],[Vol. Movimentado M³]], BD_Receitas[[#This Row],[Volume Mínimo ]]) ),0) | U47: =IFERROR(IF(BD_Receitas[[#This Row],[TIPO DE COBRANÇA]]<>"Operação Normal","", SUMIFS(BD_Receitas[Valor Total R$],BD_Receitas[CONGENERE],BD_Receitas[[#This Row],[CONGENERE]],BD_Receitas[FILIAL],BD_Receitas[[#This Row],[FILIAL]],BD_Receitas[DATA CONTABIL],BD_Receitas[[#This Row],[DATA CONTABIL]]) /BD_Receitas[[#This Row],[Vol. Movimentado M³]] ),0) | V47: =IF(BD_Receitas[[#This Row],[TIPO DE COBRANÇA]]<>"Operação Normal","",(BD_Receitas[[#This Row],[Volume 1º Giro]]*BD_Receitas[[#This Row],[Tarifa 1º Giro]])+(BD_Receitas[[#This Row],[Volume Mínimo ]]-BD_Receitas[[#This Row],[Volume 1º Giro]])*BD_Receitas[[#This Row],[Tarifa 2º Giro]]) | W47: =IF(BD_Receitas[[#This Row],[TIPO DE COBRANÇA]]<>"OPERAÇÃO NORMAL","", IF(BD_Receitas[[#This Row],[Vol. Movimentado M³]]<BD_Receitas[[#This Row],[Volume 1º Giro]],BD_Receitas[[#This Row],[Vol. Movimentado M³]]* BD_Receitas[[#This Row],[Tarifa 1º Giro]], (BD_Receitas[[#This Row],[Volume 1º Giro]]*BD_Receitas[[#This Row],[Tarifa 1º Giro]])+(BD_Receitas[[#This Row],[Vol. Movimentado M³]]-BD_Receitas[[#This Row],[Volume 1º Giro]])*BD_Receitas[[#This Row],[Tarifa 2º Giro]]) ) | X47: =IF(BD_Receitas[[#This Row],[TIPO DE COBRANÇA]] <> "OPERAÇÃO NORMAL","", IF(BD_Receitas[[#This Row],[Vol. Movimentado M³]]= BD_Receitas[[#This Row],[Volume Mínimo ]], "Vol. Movimentado igual ao Vol. Mínimo", IF(ROUND(BD_Receitas[[#This Row],[Tarifa 1º Giro]],3) <> ROUND(BD_Receitas[[#This Row],[Tarifa Cobrada]],3), "Conferir tarifa cobrada", IF(BD_Receitas[[#This Row],[Volume Mínimo ]]=0,"Ok", IF(BD_Receitas[[#This Row],[Vol. Movimentado M³]]<= BD_Receitas[[#This Row],[Volume Mínimo ]], IF(ROUND(BD_Receitas[[#This Row],[Valor Total R$]],2) = ROUND(BD_Receitas[[#This Row],[Valor Total R$]],2), "Ok","Verificar Cobrança"), IF(ROUND(BD_Receitas[[#This Row],[Valor Contrato]],2) = ROUND(BD_Receitas[[#This Row],[Valor Movimentado]],2), "OK","Verificar cobrança") )))))
A48: 49206 | B48: 45658 | C48: BRASILIA | D48: GUAMARE | E48: BAIANO | F48: 49 | G48: Luis Eduardo Magalhães | H48: Vibra | I48: Operação Normal | J48: 0 | K48: 0 | L48: 89616.88 | M48: 3986 | N48: 103 | P48: =IF(BD_Receitas[[#This Row],[TIPO DE COBRANÇA]]="Operação Normal", _xlfn.XLOOKUP(BD_Receitas[[#This Row],[ID]],TabCondicoesComerciais[ID],TabCondicoesComerciais[Volume mínimo (m3)],0),"") -> 3300 | Q48: =_xlfn.XLOOKUP(BD_Receitas[[#This Row],[ID]],TabCondicoesComerciais[ID],TabCondicoesComerciais[Vol. 1ºGiro],0) -> 1070 | R48: =IF(BD_Receitas[[#This Row],[TIPO DE COBRANÇA]]="Avanço Espaço", _xlfn.XLOOKUP(BD_Receitas[[#This Row],[ID]],TabCondicoesComerciais[ID],TabCondicoesComerciais[Avanço Espaço],0), IF(BD_Receitas[[#This Row],[TIPO DE COBRANÇA]]="Avanço Horário", _xlfn.XLOOKUP(BD_Receitas[[#This Row],[ID]],TabCondicoesComerciais[ID],TabCondicoesComerciais[Avanço Horário],0), IF(BD_Receitas[[#This Row],[TIPO DE COBRANÇA]]="Operação Normal", _xlfn.XLOOKUP(BD_Receitas[[#This Row],[ID]],TabCondicoesComerciais[ID],TabCondicoesComerciais[Tarifa 1º Giro],0),0))) -> 23.42 | S48: =IF(BD_Receitas[[#This Row],[TIPO DE COBRANÇA]]="Operação Normal", _xlfn.XLOOKUP(BD_Receitas[[#This Row],[ID]],TabCondicoesComerciais[ID],TabCondicoesComerciais[Tarifa 2º Giro],0),0) -> 23.42 | T48: =IFERROR(IF(BD_Receitas[[#This Row],[TIPO DE COBRANÇA]]<>"Operação Normal","",BD_Receitas[[#This Row],[Valor Total R$]]/ MAX(BD_Receitas[[#This Row],[Vol. Movimentado M³]], BD_Receitas[[#This Row],[Volume Mínimo ]]) ),0) -> 22.48291 | U48: =IFERROR(IF(BD_Receitas[[#This Row],[TIPO DE COBRANÇA]]<>"Operação Normal","", SUMIFS(BD_Receitas[Valor Total R$],BD_Receitas[CONGENERE],BD_Receitas[[#This Row],[CONGENERE]],BD_Receitas[FILIAL],BD_Receitas[[#This Row],[FILIAL]],BD_Receitas[DATA CONTABIL],BD_Receitas[[#This Row],[DATA CONTABIL]]) /BD_Receitas[[#This Row],[Vol. Movimentado M³]] ),0) -> 22.48291 | V48: =IF(BD_Receitas[[#This Row],[TIPO DE COBRANÇA]]<>"Operação Normal","",(BD_Receitas[[#This Row],[Volume 1º Giro]]*BD_Receitas[[#This Row],[Tarifa 1º Giro]])+(BD_Receitas[[#This Row],[Volume Mínimo ]]-BD_Receitas[[#This Row],[Volume 1º Giro]])*BD_Receitas[[#This Row],[Tarifa 2º Giro]]) -> 77286 | W48: =IF(BD_Receitas[[#This Row],[TIPO DE COBRANÇA]]<>"OPERAÇÃO NORMAL","", IF(BD_Receitas[[#This Row],[Vol. Movimentado M³]]<BD_Receitas[[#This Row],[Volume 1º Giro]],BD_Receitas[[#This Row],[Vol. Movimentado M³]]* BD_Receitas[[#This Row],[Tarifa 1º Giro]], (BD_Receitas[[#This Row],[Volume 1º Giro]]*BD_Receitas[[#This Row],[Tarifa 1º Giro]])+(BD_Receitas[[#This Row],[Vol. Movimentado M³]]-BD_Receitas[[#This Row],[Volume 1º Giro]])*BD_Receitas[[#This Row],[Tarifa 2º Giro]]) ) -> 93352.12 | X48: =IF(BD_Receitas[[#This Row],[TIPO DE COBRANÇA]] <> "OPERAÇÃO NORMAL","", IF(BD_Receitas[[#This Row],[Vol. Movimentado M³]]= BD_Receitas[[#This Row],[Volume Mínimo ]], "Vol. Movimentado igual ao Vol. Mínimo", IF(ROUND(BD_Receitas[[#This Row],[Tarifa 1º Giro]],3) <> ROUND(BD_Receitas[[#This Row],[Tarifa Cobrada]],3), "Conferir tarifa cobrada", IF(BD_Receitas[[#This Row],[Volume Mínimo ]]=0,"Ok", IF(BD_Receitas[[#This Row],[Vol. Movimentado M³]]<= BD_Receitas[[#This Row],[Volume Mínimo ]], IF(ROUND(BD_Receitas[[#This Row],[Valor Total R$]],2) = ROUND(BD_Receitas[[#This Row],[Valor Total R$]],2), "Ok","Verificar Cobrança"), IF(ROUND(BD_Receitas[[#This Row],[Valor Contrato]],2) = ROUND(BD_Receitas[[#This Row],[Valor Movimentado]],2), "OK","Verificar cobrança") ))))) -> Conferir tarifa cobrada
A49: 49206 | B49: 45658 | C49: BRASILIA | D49: GUAMARE | E49: BAIANO | F49: 49 | G49: Luis Eduardo Magalhães | H49: Vibra | I49: Outras Receitas | J49: 0 | K49: 0 | P49: =IF(BD_Receitas[[#This Row],[TIPO DE COBRANÇA]]="Operação Normal", _xlfn.XLOOKUP(BD_Receitas[[#This Row],[ID]],TabCondicoesComerciais[ID],TabCondicoesComerciais[Volume mínimo (m3)],0),"") | Q49: =_xlfn.XLOOKUP(BD_Receitas[[#This Row],[ID]],TabCondicoesComerciais[ID],TabCondicoesComerciais[Vol. 1ºGiro],0) -> 1070 | R49: =IF(BD_Receitas[[#This Row],[TIPO DE COBRANÇA]]="Avanço Espaço", _xlfn.XLOOKUP(BD_Receitas[[#This Row],[ID]],TabCondicoesComerciais[ID],TabCondicoesComerciais[Avanço Espaço],0), IF(BD_Receitas[[#This Row],[TIPO DE COBRANÇA]]="Avanço Horário", _xlfn.XLOOKUP(BD_Receitas[[#This Row],[ID]],TabCondicoesComerciais[ID],TabCondicoesComerciais[Avanço Horário],0), IF(BD_Receitas[[#This Row],[TIPO DE COBRANÇA]]="Operação Normal", _xlfn.XLOOKUP(BD_Receitas[[#This Row],[ID]],TabCondicoesComerciais[ID],TabCondicoesComerciais[Tarifa 1º Giro],0),0))) -> 0 | S49: =IF(BD_Receitas[[#This Row],[TIPO DE COBRANÇA]]="Operação Normal", _xlfn.XLOOKUP(BD_Receitas[[#This Row],[ID]],TabCondicoesComerciais[ID],TabCondicoesComerciais[Tarifa 2º Giro],0),0) -> 0 | T49: =IFERROR(IF(BD_Receitas[[#This Row],[TIPO DE COBRANÇA]]<>"Operação Normal","",BD_Receitas[[#This Row],[Valor Total R$]]/ MAX(BD_Receitas[[#This Row],[Vol. Movimentado M³]], BD_Receitas[[#This Row],[Volume Mínimo ]]) ),0) | U49: =IFERROR(IF(BD_Receitas[[#This Row],[TIPO DE COBRANÇA]]<>"Operação Normal","", SUMIFS(BD_Receitas[Valor Total R$],BD_Receitas[CONGENERE],BD_Receitas[[#This Row],[CONGENERE]],BD_Receitas[FILIAL],BD_Receitas[[#This Row],[FILIAL]],BD_Receitas[DATA CONTABIL],BD_Receitas[[#This Row],[DATA CONTABIL]]) /BD_Receitas[[#This Row],[Vol. Movimentado M³]] ),0) | V49: =IF(BD_Receitas[[#This Row],[TIPO DE COBRANÇA]]<>"Operação Normal","",(BD_Receitas[[#This Row],[Volume 1º Giro]]*BD_Receitas[[#This Row],[Tarifa 1º Giro]])+(BD_Receitas[[#This Row],[Volume Mínimo ]]-BD_Receitas[[#This Row],[Volume 1º Giro]])*BD_Receitas[[#This Row],[Tarifa 2º Giro]]) | W49: =IF(BD_Receitas[[#This Row],[TIPO DE COBRANÇA]]<>"OPERAÇÃO NORMAL","", IF(BD_Receitas[[#This Row],[Vol. Movimentado M³]]<BD_Receitas[[#This Row],[Volume 1º Giro]],BD_Receitas[[#This Row],[Vol. Movimentado M³]]* BD_Receitas[[#This Row],[Tarifa 1º Giro]], (BD_Receitas[[#This Row],[Volume 1º Giro]]*BD_Receitas[[#This Row],[Tarifa 1º Giro]])+(BD_Receitas[[#This Row],[Vol. Movimentado M³]]-BD_Receitas[[#This Row],[Volume 1º Giro]])*BD_Receitas[[#This Row],[Tarifa 2º Giro]]) ) | X49: =IF(BD_Receitas[[#This Row],[TIPO DE COBRANÇA]] <> "OPERAÇÃO NORMAL","", IF(BD_Receitas[[#This Row],[Vol. Movimentado M³]]= BD_Receitas[[#This Row],[Volume Mínimo ]], "Vol. Movimentado igual ao Vol. Mínimo", IF(ROUND(BD_Receitas[[#This Row],[Tarifa 1º Giro]],3) <> ROUND(BD_Receitas[[#This Row],[Tarifa Cobrada]],3), "Conferir tarifa cobrada", IF(BD_Receitas[[#This Row],[Volume Mínimo ]]=0,"Ok", IF(BD_Receitas[[#This Row],[Vol. Movimentado M³]]<= BD_Receitas[[#This Row],[Volume Mínimo ]], IF(ROUND(BD_Receitas[[#This Row],[Valor Total R$]],2) = ROUND(BD_Receitas[[#This Row],[Valor Total R$]],2), "Ok","Verificar Cobrança"), IF(ROUND(BD_Receitas[[#This Row],[Valor Contrato]],2) = ROUND(BD_Receitas[[#This Row],[Valor Movimentado]],2), "OK","Verificar cobrança") )))))
A50: 20105 | B50: 45658 | C50: BRASILIA | D50: SAO PAULO | E50: PAULINIA | F50: 20 | G50: São José do Rio Preto | H50: Ruff | I50: Avanço Espaço | J50: 0 | K50: 0 | P50: =IF(BD_Receitas[[#This Row],[TIPO DE COBRANÇA]]="Operação Normal", _xlfn.XLOOKUP(BD_Receitas[[#This Row],[ID]],TabCondicoesComerciais[ID],TabCondicoesComerciais[Volume mínimo (m3)],0),"") | Q50: =_xlfn.XLOOKUP(BD_Receitas[[#This Row],[ID]],TabCondicoesComerciais[ID],TabCondicoesComerciais[Vol. 1ºGiro],0) -> 340 | R50: =IF(BD_Receitas[[#This Row],[TIPO DE COBRANÇA]]="Avanço Espaço", _xlfn.XLOOKUP(BD_Receitas[[#This Row],[ID]],TabCondicoesComerciais[ID],TabCondicoesComerciais[Avanço Espaço],0), IF(BD_Receitas[[#This Row],[TIPO DE COBRANÇA]]="Avanço Horário", _xlfn.XLOOKUP(BD_Receitas[[#This Row],[ID]],TabCondicoesComerciais[ID],TabCondicoesComerciais[Avanço Horário],0), IF(BD_Receitas[[#This Row],[TIPO DE COBRANÇA]]="Operação Normal", _xlfn.XLOOKUP(BD_Receitas[[#This Row],[ID]],TabCondicoesComerciais[ID],TabCondicoesComerciais[Tarifa 1º Giro],0),0))) -> 0 | S50: =IF(BD_Receitas[[#This Row],[TIPO DE COBRANÇA]]="Operação Normal", _xlfn.XLOOKUP(BD_Receitas[[#This Row],[ID]],TabCondicoesComerciais[ID],TabCondicoesComerciais[Tarifa 2º Giro],0),0) -> 0 | T50: =IFERROR(IF(BD_Receitas[[#This Row],[TIPO DE COBRANÇA]]<>"Operação Normal","",BD_Receitas[[#This Row],[Valor Total R$]]/ MAX(BD_Receitas[[#This Row],[Vol. Movimentado M³]], BD_Receitas[[#This Row],[Volume Mínimo ]]) ),0) | U50: =IFERROR(IF(BD_Receitas[[#This Row],[TIPO DE COBRANÇA]]<>"Operação Normal","", SUMIFS(BD_Receitas[Valor Total R$],BD_Receitas[CONGENERE],BD_Receitas[[#This Row],[CONGENERE]],BD_Receitas[FILIAL],BD_Receitas[[#This Row],[FILIAL]],BD_Receitas[DATA CONTABIL],BD_Receitas[[#This Row],[DATA CONTABIL]]) /BD_Receitas[[#This Row],[Vol. Movimentado M³]] ),0) | V50: =IF(BD_Receitas[[#This Row],[TIPO DE COBRANÇA]]<>"Operação Normal","",(BD_Receitas[[#This Row],[Volume 1º Giro]]*BD_Receitas[[#This Row],[Tarifa 1º Giro]])+(BD_Receitas[[#This Row],[Volume Mínimo ]]-BD_Receitas[[#This Row],[Volume 1º Giro]])*BD_Receitas[[#This Row],[Tarifa 2º Giro]]) | W50: =IF(BD_Receitas[[#This Row],[TIPO DE COBRANÇA]]<>"OPERAÇÃO NORMAL","", IF(BD_Receitas[[#This Row],[Vol. Movimentado M³]]<BD_Receitas[[#This Row],[Volume 1º Giro]],BD_Receitas[[#This Row],[Vol. Movimentado M³]]* BD_Receitas[[#This Row],[Tarifa 1º Giro]], (BD_Receitas[[#This Row],[Volume 1º Giro]]*BD_Receitas[[#This Row],[Tarifa 1º Giro]])+(BD_Receitas[[#This Row],[Vol. Movimentado M³]]-BD_Receitas[[#This Row],[Volume 1º Giro]])*BD_Receitas[[#This Row],[Tarifa 2º Giro]]) ) | X50: =IF(BD_Receitas[[#This Row],[TIPO DE COBRANÇA]] <> "OPERAÇÃO NORMAL","", IF(BD_Receitas[[#This Row],[Vol. Movimentado M³]]= BD_Receitas[[#This Row],[Volume Mínimo ]], "Vol. Movimentado igual ao Vol. Mínimo", IF(ROUND(BD_Receitas[[#This Row],[Tarifa 1º Giro]],3) <> ROUND(BD_Receitas[[#This Row],[Tarifa Cobrada]],3), "Conferir tarifa cobrada", IF(BD_Receitas[[#This Row],[Volume Mínimo ]]=0,"Ok", IF(BD_Receitas[[#This Row],[Vol. Movimentado M³]]<= BD_Receitas[[#This Row],[Volume Mínimo ]], IF(ROUND(BD_Receitas[[#This Row],[Valor Total R$]],2) = ROUND(BD_Receitas[[#This Row],[Valor Total R$]],2), "Ok","Verificar Cobrança"), IF(ROUND(BD_Receitas[[#This Row],[Valor Contrato]],2) = ROUND(BD_Receitas[[#This Row],[Valor Movimentado]],2), "OK","Verificar cobrança") )))))
A51: 20105 | B51: 45658 | C51: BRASILIA | D51: SAO PAULO | E51: PAULINIA | F51: 20 | G51: São José do Rio Preto | H51: Ruff | I51: Avanço Horário | J51: 0 | K51: 0 | P51: =IF(BD_Receitas[[#This Row],[TIPO DE COBRANÇA]]="Operação Normal", _xlfn.XLOOKUP(BD_Receitas[[#This Row],[ID]],TabCondicoesComerciais[ID],TabCondicoesComerciais[Volume mínimo (m3)],0),"") | Q51: =_xlfn.XLOOKUP(BD_Receitas[[#This Row],[ID]],TabCondicoesComerciais[ID],TabCondicoesComerciais[Vol. 1ºGiro],0) -> 340 | R51: =IF(BD_Receitas[[#This Row],[TIPO DE COBRANÇA]]="Avanço Espaço", _xlfn.XLOOKUP(BD_Receitas[[#This Row],[ID]],TabCondicoesComerciais[ID],TabCondicoesComerciais[Avanço Espaço],0), IF(BD_Receitas[[#This Row],[TIPO DE COBRANÇA]]="Avanço Horário", _xlfn.XLOOKUP(BD_Receitas[[#This Row],[ID]],TabCondicoesComerciais[ID],TabCondicoesComerciais[Avanço Horário],0), IF(BD_Receitas[[#This Row],[TIPO DE COBRANÇA]]="Operação Normal", _xlfn.XLOOKUP(BD_Receitas[[#This Row],[ID]],TabCondicoesComerciais[ID],TabCondicoesComerciais[Tarifa 1º Giro],0),0))) -> 12 | S51: =IF(BD_Receitas[[#This Row],[TIPO DE COBRANÇA]]="Operação Normal", _xlfn.XLOOKUP(BD_Receitas[[#This Row],[ID]],TabCondicoesComerciais[ID],TabCondicoesComerciais[Tarifa 2º Giro],0),0) -> 0 | T51: =IFERROR(IF(BD_Receitas[[#This Row],[TIPO DE COBRANÇA]]<>"Operação Normal","",BD_Receitas[[#This Row],[Valor Total R$]]/ MAX(BD_Receitas[[#This Row],[Vol. Movimentado M³]], BD_Receitas[[#This Row],[Volume Mínimo ]]) ),0) | U51: =IFERROR(IF(BD_Receitas[[#This Row],[TIPO DE COBRANÇA]]<>"Operação Normal","", SUMIFS(BD_Receitas[Valor Total R$],BD_Receitas[CONGENERE],BD_Receitas[[#This Row],[CONGENERE]],BD_Receitas[FILIAL],BD_Receitas[[#This Row],[FILIAL]],BD_Receitas[DATA CONTABIL],BD_Receitas[[#This Row],[DATA CONTABIL]]) /BD_Receitas[[#This Row],[Vol. Movimentado M³]] ),0) | V51: =IF(BD_Receitas[[#This Row],[TIPO DE COBRANÇA]]<>"Operação Normal","",(BD_Receitas[[#This Row],[Volume 1º Giro]]*BD_Receitas[[#This Row],[Tarifa 1º Giro]])+(BD_Receitas[[#This Row],[Volume Mínimo ]]-BD_Receitas[[#This Row],[Volume 1º Giro]])*BD_Receitas[[#This Row],[Tarifa 2º Giro]]) | W51: =IF(BD_Receitas[[#This Row],[TIPO DE COBRANÇA]]<>"OPERAÇÃO NORMAL","", IF(BD_Receitas[[#This Row],[Vol. Movimentado M³]]<BD_Receitas[[#This Row],[Volume 1º Giro]],BD_Receitas[[#This Row],[Vol. Movimentado M³]]* BD_Receitas[[#This Row],[Tarifa 1º Giro]], (BD_Receitas[[#This Row],[Volume 1º Giro]]*BD_Receitas[[#This Row],[Tarifa 1º Giro]])+(BD_Receitas[[#This Row],[Vol. Movimentado M³]]-BD_Receitas[[#This Row],[Volume 1º Giro]])*BD_Receitas[[#This Row],[Tarifa 2º Giro]]) ) | X51: =IF(BD_Receitas[[#This Row],[TIPO DE COBRANÇA]] <> "OPERAÇÃO NORMAL","", IF(BD_Receitas[[#This Row],[Vol. Movimentado M³]]= BD_Receitas[[#This Row],[Volume Mínimo ]], "Vol. Movimentado igual ao Vol. Mínimo", IF(ROUND(BD_Receitas[[#This Row],[Tarifa 1º Giro]],3) <> ROUND(BD_Receitas[[#This Row],[Tarifa Cobrada]],3), "Conferir tarifa cobrada", IF(BD_Receitas[[#This Row],[Volume Mínimo ]]=0,"Ok", IF(BD_Receitas[[#This Row],[Vol. Movimentado M³]]<= BD_Receitas[[#This Row],[Volume Mínimo ]], IF(ROUND(BD_Receitas[[#This Row],[Valor Total R$]],2) = ROUND(BD_Receitas[[#This Row],[Valor Total R$]],2), "Ok","Verificar Cobrança"), IF(ROUND(BD_Receitas[[#This Row],[Valor Contrato]],2) = ROUND(BD_Receitas[[#This Row],[Valor Movimentado]],2), "OK","Verificar cobrança") )))))
A52: 20105 | B52: 45658 | C52: BRASILIA | D52: SAO PAULO | E52: PAULINIA | F52: 20 | G52: São José do Rio Preto | H52: Ruff | I52: Operação Normal | J52: 16282.577 | K52: 545 | L52: 15260 | M52: 935 | N52: 378 | P52: =IF(BD_Receitas[[#This Row],[TIPO DE COBRANÇA]]="Operação Normal", _xlfn.XLOOKUP(BD_Receitas[[#This Row],[ID]],TabCondicoesComerciais[ID],TabCondicoesComerciais[Volume mínimo (m3)],0),"") -> 1020 | Q52: =_xlfn.XLOOKUP(BD_Receitas[[#This Row],[ID]],TabCondicoesComerciais[ID],TabCondicoesComerciais[Vol. 1ºGiro],0) -> 340 | R52: =IF(BD_Receitas[[#This Row],[TIPO DE COBRANÇA]]="Avanço Espaço", _xlfn.XLOOKUP(BD_Receitas[[#This Row],[ID]],TabCondicoesComerciais[ID],TabCondicoesComerciais[Avanço Espaço],0), IF(BD_Receitas[[#This Row],[TIPO DE COBRANÇA]]="Avanço Horário", _xlfn.XLOOKUP(BD_Receitas[[#This Row],[ID]],TabCondicoesComerciais[ID],TabCondicoesComerciais[Avanço Horário],0), IF(BD_Receitas[[#This Row],[TIPO DE COBRANÇA]]="Operação Normal", _xlfn.XLOOKUP(BD_Receitas[[#This Row],[ID]],TabCondicoesComerciais[ID],TabCondicoesComerciais[Tarifa 1º Giro],0),0))) -> 28 | S52: =IF(BD_Receitas[[#This Row],[TIPO DE COBRANÇA]]="Operação Normal", _xlfn.XLOOKUP(BD_Receitas[[#This Row],[ID]],TabCondicoesComerciais[ID],TabCondicoesComerciais[Tarifa 2º Giro],0),0) -> 28 | T52: =IFERROR(IF(BD_Receitas[[#This Row],[TIPO DE COBRANÇA]]<>"Operação Normal","",BD_Receitas[[#This Row],[Valor Total R$]]/ MAX(BD_Receitas[[#This Row],[Vol. Movimentado M³]], BD_Receitas[[#This Row],[Volume Mínimo ]]) ),0) -> 14.960784 | U52: =IFERROR(IF(BD_Receitas[[#This Row],[TIPO DE COBRANÇA]]<>"Operação Normal","", SUMIFS(BD_Receitas[Valor Total R$],BD_Receitas[CONGENERE],BD_Receitas[[#This Row],[CONGENERE]],BD_Receitas[FILIAL],BD_Receitas[[#This Row],[FILIAL]],BD_Receitas[DATA CONTABIL],BD_Receitas[[#This Row],[DATA CONTABIL]]) /BD_Receitas[[#This Row],[Vol. Movimentado M³]] ),0) -> 16.320856 | V52: =IF(BD_Receitas[[#This Row],[TIPO DE COBRANÇA]]<>"Operação Normal","",(BD_Receitas[[#This Row],[Volume 1º Giro]]*BD_Receitas[[#This Row],[Tarifa 1º Giro]])+(BD_Receitas[[#This Row],[Volume Mínimo ]]-BD_Receitas[[#This Row],[Volume 1º Giro]])*BD_Receitas[[#This Row],[Tarifa 2º Giro]]) -> 28560 | W52: =IF(BD_Receitas[[#This Row],[TIPO DE COBRANÇA]]<>"OPERAÇÃO NORMAL","", IF(BD_Receitas[[#This Row],[Vol. Movimentado M³]]<BD_Receitas[[#This Row],[Volume 1º Giro]],BD_Receitas[[#This Row],[Vol. Movimentado M³]]* BD_Receitas[[#This Row],[Tarifa 1º Giro]], (BD_Receitas[[#This Row],[Volume 1º Giro]]*BD_Receitas[[#This Row],[Tarifa 1º Giro]])+(BD_Receitas[[#This Row],[Vol. Movimentado M³]]-BD_Receitas[[#This Row],[Volume 1º Giro]])*BD_Receitas[[#This Row],[Tarifa 2º Giro]]) ) -> 26180 | X52: =IF(BD_Receitas[[#This Row],[TIPO DE COBRANÇA]] <> "OPERAÇÃO NORMAL","", IF(BD_Receitas[[#This Row],[Vol. Movimentado M³]]= BD_Receitas[[#This Row],[Volume Mínimo ]], "Vol. Movimentado igual ao Vol. Mínimo", IF(ROUND(BD_Receitas[[#This Row],[Tarifa 1º Giro]],3) <> ROUND(BD_Receitas[[#This Row],[Tarifa Cobrada]],3), "Conferir tarifa cobrada", IF(BD_Receitas[[#This Row],[Volume Mínimo ]]=0,"Ok", IF(BD_Receitas[[#This Row],[Vol. Movimentado M³]]<= BD_Receitas[[#This Row],[Volume Mínimo ]], IF(ROUND(BD_Receitas[[#This Row],[Valor Total R$]],2) = ROUND(BD_Receitas[[#This Row],[Valor Total R$]],2), "Ok","Verificar Cobrança"), IF(ROUND(BD_Receitas[[#This Row],[Valor Contrato]],2) = ROUND(BD_Receitas[[#This Row],[Valor Movimentado]],2), "OK","Verificar cobrança") ))))) -> Conferir tarifa cobrada
A53: 20105 | B53: 45658 | C53: BRASILIA | D53: SAO PAULO | E53: PAULINIA | F53: 20 | G53: São José do Rio Preto | H53: Ruff | I53: Outras Receitas | J53: 0 | K53: 0 | P53: =IF(BD_Receitas[[#This Row],[TIPO DE COBRANÇA]]="Operação Normal", _xlfn.XLOOKUP(BD_Receitas[[#This Row],[ID]],TabCondicoesComerciais[ID],TabCondicoesComerciais[Volume mínimo (m3)],0),"") | Q53: =_xlfn.XLOOKUP(BD_Receitas[[#This Row],[ID]],TabCondicoesComerciais[ID],TabCondicoesComerciais[Vol. 1ºGiro],0) -> 340 | R53: =IF(BD_Receitas[[#This Row],[TIPO DE COBRANÇA]]="Avanço Espaço", _xlfn.XLOOKUP(BD_Receitas[[#This Row],[ID]],TabCondicoesComerciais[ID],TabCondicoesComerciais[Avanço Espaço],0), IF(BD_Receitas[[#This Row],[TIPO DE COBRANÇA]]="Avanço Horário", _xlfn.XLOOKUP(BD_Receitas[[#This Row],[ID]],TabCondicoesComerciais[ID],TabCondicoesComerciais[Avanço Horário],0), IF(BD_Receitas[[#This Row],[TIPO DE COBRANÇA]]="Operação Normal", _xlfn.XLOOKUP(BD_Receitas[[#This Row],[ID]],TabCondicoesComerciais[ID],TabCondicoesComerciais[Tarifa 1º Giro],0),0))) -> 0 | S53: =IF(BD_Receitas[[#This Row],[TIPO DE COBRANÇA]]="Operação Normal", _xlfn.XLOOKUP(BD_Receitas[[#This Row],[ID]],TabCondicoesComerciais[ID],TabCondicoesComerciais[Tarifa 2º Giro],0),0) -> 0 | T53: =IFERROR(IF(BD_Receitas[[#This Row],[TIPO DE COBRANÇA]]<>"Operação Normal","",BD_Receitas[[#This Row],[Valor Total R$]]/ MAX(BD_Receitas[[#This Row],[Vol. Movimentado M³]], BD_Receitas[[#This Row],[Volume Mínimo ]]) ),0) | U53: =IFERROR(IF(BD_Receitas[[#This Row],[TIPO DE COBRANÇA]]<>"Operação Normal","", SUMIFS(BD_Receitas[Valor Total R$],BD_Receitas[CONGENERE],BD_Receitas[[#This Row],[CONGENERE]],BD_Receitas[FILIAL],BD_Receitas[[#This Row],[FILIAL]],BD_Receitas[DATA CONTABIL],BD_Receitas[[#This Row],[DATA CONTABIL]]) /BD_Receitas[[#This Row],[Vol. Movimentado M³]] ),0) | V53: =IF(BD_Receitas[[#This Row],[TIPO DE COBRANÇA]]<>"Operação Normal","",(BD_Receitas[[#This Row],[Volume 1º Giro]]*BD_Receitas[[#This Row],[Tarifa 1º Giro]])+(BD_Receitas[[#This Row],[Volume Mínimo ]]-BD_Receitas[[#This Row],[Volume 1º Giro]])*BD_Receitas[[#This Row],[Tarifa 2º Giro]]) | W53: =IF(BD_Receitas[[#This Row],[TIPO DE COBRANÇA]]<>"OPERAÇÃO NORMAL","", IF(BD_Receitas[[#This Row],[Vol. Movimentado M³]]<BD_Receitas[[#This Row],[Volume 1º Giro]],BD_Receitas[[#This Row],[Vol. Movimentado M³]]* BD_Receitas[[#This Row],[Tarifa 1º Giro]], (BD_Receitas[[#This Row],[Volume 1º Giro]]*BD_Receitas[[#This Row],[Tarifa 1º Giro]])+(BD_Receitas[[#This Row],[Vol. Movimentado M³]]-BD_Receitas[[#This Row],[Volume 1º Giro]])*BD_Receitas[[#This Row],[Tarifa 2º Giro]]) ) | X53: =IF(BD_Receitas[[#This Row],[TIPO DE COBRANÇA]] <> "OPERAÇÃO NORMAL","", IF(BD_Receitas[[#This Row],[Vol. Movimentado M³]]= BD_Receitas[[#This Row],[Volume Mínimo ]], "Vol. Movimentado igual ao Vol. Mínimo", IF(ROUND(BD_Receitas[[#This Row],[Tarifa 1º Giro]],3) <> ROUND(BD_Receitas[[#This Row],[Tarifa Cobrada]],3), "Conferir tarifa cobrada", IF(BD_Receitas[[#This Row],[Volume Mínimo ]]=0,"Ok", IF(BD_Receitas[[#This Row],[Vol. Movimentado M³]]<= BD_Receitas[[#This Row],[Volume Mínimo ]], IF(ROUND(BD_Receitas[[#This Row],[Valor Total R$]],2) = ROUND(BD_Receitas[[#This Row],[Valor Total R$]],2), "Ok","Verificar Cobrança"), IF(ROUND(BD_Receitas[[#This Row],[Valor Contrato]],2) = ROUND(BD_Receitas[[#This Row],[Valor Movimentado]],2), "OK","Verificar cobrança") )))))
A54: 1503 | B54: 45689 | C54: BRASILIA | D54: MG RJ ES | E54: MINAS CENTRAL | F54: 1 | G54: Betim | H54: Atlantica | I54: Avanço Espaço | J54: 0 | K54: 0 | P54: =IF(BD_Receitas[[#This Row],[TIPO DE COBRANÇA]]="Operação Normal", _xlfn.XLOOKUP(BD_Receitas[[#This Row],[ID]],TabCondicoesComerciais[ID],TabCondicoesComerciais[Volume mínimo (m3)],0),"") | Q54: =_xlfn.XLOOKUP(BD_Receitas[[#This Row],[ID]],TabCondicoesComerciais[ID],TabCondicoesComerciais[Vol. 1ºGiro],0) -> 360 | R54: =IF(BD_Receitas[[#This Row],[TIPO DE COBRANÇA]]="Avanço Espaço", _xlfn.XLOOKUP(BD_Receitas[[#This Row],[ID]],TabCondicoesComerciais[ID],TabCondicoesComerciais[Avanço Espaço],0), IF(BD_Receitas[[#This Row],[TIPO DE COBRANÇA]]="Avanço Horário", _xlfn.XLOOKUP(BD_Receitas[[#This Row],[ID]],TabCondicoesComerciais[ID],TabCondicoesComerciais[Avanço Horário],0), IF(BD_Receitas[[#This Row],[TIPO DE COBRANÇA]]="Operação Normal", _xlfn.XLOOKUP(BD_Receitas[[#This Row],[ID]],TabCondicoesComerciais[ID],TabCondicoesComerciais[Tarifa 1º Giro],0),0))) -> 16.364 | S54: =IF(BD_Receitas[[#This Row],[TIPO DE COBRANÇA]]="Operação Normal", _xlfn.XLOOKUP(BD_Receitas[[#This Row],[ID]],TabCondicoesComerciais[ID],TabCondicoesComerciais[Tarifa 2º Giro],0),0) -> 0 | T54: =IFERROR(IF(BD_Receitas[[#This Row],[TIPO DE COBRANÇA]]<>"Operação Normal","",BD_Receitas[[#This Row],[Valor Total R$]]/ MAX(BD_Receitas[[#This Row],[Vol. Movimentado M³]], BD_Receitas[[#This Row],[Volume Mínimo ]]) ),0) | U54: =IFERROR(IF(BD_Receitas[[#This Row],[TIPO DE COBRANÇA]]<>"Operação Normal","", SUMIFS(BD_Receitas[Valor Total R$],BD_Receitas[CONGENERE],BD_Receitas[[#This Row],[CONGENERE]],BD_Receitas[FILIAL],BD_Receitas[[#This Row],[FILIAL]],BD_Receitas[DATA CONTABIL],BD_Receitas[[#This Row],[DATA CONTABIL]]) /BD_Receitas[[#This Row],[Vol. Movimentado M³]] ),0) | V54: =IF(BD_Receitas[[#This Row],[TIPO DE COBRANÇA]]<>"Operação Normal","",(BD_Receitas[[#This Row],[Volume 1º Giro]]*BD_Receitas[[#This Row],[Tarifa 1º Giro]])+(BD_Receitas[[#This Row],[Volume Mínimo ]]-BD_Receitas[[#This Row],[Volume 1º Giro]])*BD_Receitas[[#This Row],[Tarifa 2º Giro]]) | W54: =IF(BD_Receitas[[#This Row],[TIPO DE COBRANÇA]]<>"OPERAÇÃO NORMAL","", IF(BD_Receitas[[#This Row],[Vol. Movimentado M³]]<BD_Receitas[[#This Row],[Volume 1º Giro]],BD_Receitas[[#This Row],[Vol. Movimentado M³]]* BD_Receitas[[#This Row],[Tarifa 1º Giro]], (BD_Receitas[[#This Row],[Volume 1º Giro]]*BD_Receitas[[#This Row],[Tarifa 1º Giro]])+(BD_Receitas[[#This Row],[Vol. Movimentado M³]]-BD_Receitas[[#This Row],[Volume 1º Giro]])*BD_Receitas[[#This Row],[Tarifa 2º Giro]]) ) | X54: =IF(BD_Receitas[[#This Row],[TIPO DE COBRANÇA]] <> "OPERAÇÃO NORMAL","", IF(BD_Receitas[[#This Row],[Vol. Movimentado M³]]= BD_Receitas[[#This Row],[Volume Mínimo ]], "Vol. Movimentado igual ao Vol. Mínimo", IF(ROUND(BD_Receitas[[#This Row],[Tarifa 1º Giro]],3) <> ROUND(BD_Receitas[[#This Row],[Tarifa Cobrada]],3), "Conferir tarifa cobrada", IF(BD_Receitas[[#This Row],[Volume Mínimo ]]=0,"Ok", IF(BD_Receitas[[#This Row],[Vol. Movimentado M³]]<= BD_Receitas[[#This Row],[Volume Mínimo ]], IF(ROUND(BD_Receitas[[#This Row],[Valor Total R$]],2) = ROUND(BD_Receitas[[#This Row],[Valor Total R$]],2), "Ok","Verificar Cobrança"), IF(ROUND(BD_Receitas[[#This Row],[Valor Contrato]],2) = ROUND(BD_Receitas[[#This Row],[Valor Movimentado]],2), "OK","Verificar cobrança") )))))
A55: 1503 | B55: 45689 | C55: BRASILIA | D55: MG RJ ES | E55: MINAS CENTRAL | F55: 1 | G55: Betim | H55: Atlantica | I55: Avanço Horário | J55: 0 | K55: 0 | P55: =IF(BD_Receitas[[#This Row],[TIPO DE COBRANÇA]]="Operação Normal", _xlfn.XLOOKUP(BD_Receitas[[#This Row],[ID]],TabCondicoesComerciais[ID],TabCondicoesComerciais[Volume mínimo (m3)],0),"") | Q55: =_xlfn.XLOOKUP(BD_Receitas[[#This Row],[ID]],TabCondicoesComerciais[ID],TabCondicoesComerciais[Vol. 1ºGiro],0) -> 360 | R55: =IF(BD_Receitas[[#This Row],[TIPO DE COBRANÇA]]="Avanço Espaço", _xlfn.XLOOKUP(BD_Receitas[[#This Row],[ID]],TabCondicoesComerciais[ID],TabCondicoesComerciais[Avanço Espaço],0), IF(BD_Receitas[[#This Row],[TIPO DE COBRANÇA]]="Avanço Horário", _xlfn.XLOOKUP(BD_Receitas[[#This Row],[ID]],TabCondicoesComerciais[ID],TabCondicoesComerciais[Avanço Horário],0), IF(BD_Receitas[[#This Row],[TIPO DE COBRANÇA]]="Operação Normal", _xlfn.XLOOKUP(BD_Receitas[[#This Row],[ID]],TabCondicoesComerciais[ID],TabCondicoesComerciais[Tarifa 1º Giro],0),0))) -> 15 | S55: =IF(BD_Receitas[[#This Row],[TIPO DE COBRANÇA]]="Operação Normal", _xlfn.XLOOKUP(BD_Receitas[[#This Row],[ID]],TabCondicoesComerciais[ID],TabCondicoesComerciais[Tarifa 2º Giro],0),0) -> 0 | T55: =IFERROR(IF(BD_Receitas[[#This Row],[TIPO DE COBRANÇA]]<>"Operação Normal","",BD_Receitas[[#This Row],[Valor Total R$]]/ MAX(BD_Receitas[[#This Row],[Vol. Movimentado M³]], BD_Receitas[[#This Row],[Volume Mínimo ]]) ),0) | U55: =IFERROR(IF(BD_Receitas[[#This Row],[TIPO DE COBRANÇA]]<>"Operação Normal","", SUMIFS(BD_Receitas[Valor Total R$],BD_Receitas[CONGENERE],BD_Receitas[[#This Row],[CONGENERE]],BD_Receitas[FILIAL],BD_Receitas[[#This Row],[FILIAL]],BD_Receitas[DATA CONTABIL],BD_Receitas[[#This Row],[DATA CONTABIL]]) /BD_Receitas[[#This Row],[Vol. Movimentado M³]] ),0) | V55: =IF(BD_Receitas[[#This Row],[TIPO DE COBRANÇA]]<>"Operação Normal","",(BD_Receitas[[#This Row],[Volume 1º Giro]]*BD_Receitas[[#This Row],[Tarifa 1º Giro]])+(BD_Receitas[[#This Row],[Volume Mínimo ]]-BD_Receitas[[#This Row],[Volume 1º Giro]])*BD_Receitas[[#This Row],[Tarifa 2º Giro]]) | W55: =IF(BD_Receitas[[#This Row],[TIPO DE COBRANÇA]]<>"OPERAÇÃO NORMAL","", IF(BD_Receitas[[#This Row],[Vol. Movimentado M³]]<BD_Receitas[[#This Row],[Volume 1º Giro]],BD_Receitas[[#This Row],[Vol. Movimentado M³]]* BD_Receitas[[#This Row],[Tarifa 1º Giro]], (BD_Receitas[[#This Row],[Volume 1º Giro]]*BD_Receitas[[#This Row],[Tarifa 1º Giro]])+(BD_Receitas[[#This Row],[Vol. Movimentado M³]]-BD_Receitas[[#This Row],[Volume 1º Giro]])*BD_Receitas[[#This Row],[Tarifa 2º Giro]]) ) | X55: =IF(BD_Receitas[[#This Row],[TIPO DE COBRANÇA]] <> "OPERAÇÃO NORMAL","", IF(BD_Receitas[[#This Row],[Vol. Movimentado M³]]= BD_Receitas[[#This Row],[Volume Mínimo ]], "Vol. Movimentado igual ao Vol. Mínimo", IF(ROUND(BD_Receitas[[#This Row],[Tarifa 1º Giro]],3) <> ROUND(BD_Receitas[[#This Row],[Tarifa Cobrada]],3), "Conferir tarifa cobrada", IF(BD_Receitas[[#This Row],[Volume Mínimo ]]=0,"Ok", IF(BD_Receitas[[#This Row],[Vol. Movimentado M³]]<= BD_Receitas[[#This Row],[Volume Mínimo ]], IF(ROUND(BD_Receitas[[#This Row],[Valor Total R$]],2) = ROUND(BD_Receitas[[#This Row],[Valor Total R$]],2), "Ok","Verificar Cobrança"), IF(ROUND(BD_Receitas[[#This Row],[Valor Contrato]],2) = ROUND(BD_Receitas[[#This Row],[Valor Movimentado]],2), "OK","Verificar cobrança") )))))
